Workbook
Name __Fieldmark__27_1863259733: 'INVOICE 94'!#REF!

Sheet Kangatang

Sheet packinglist
A2: PACKING LIST
A3: ='[2]commercial '!A2:C2 -> Seller : | D3: ='[2]commercial '!D2 -> Invoice No. and date : | E3: =+#REF! -> #REF!
A4: SCAVI HUE COMPANY | D4: 44455
A5: PHONG DIEN INDUSTRIAL ZONE, PHONG DIEN DISTRICT | D5: Term payment:
A6: THUA THIEN HUE PROVINCE, VIETNAM
A7: Consignee : | D7: Buyer :
A8: SUPREME MUNSINGWEAR CANADA INC. | D8: PEI VIETNAM OFFICE
A9: 1938 AVENUE RD - 2ND FLOOR, ONTARIO, TORONTO, M5M 4A1 | D9: F12, 24C Phan Dang Luu Street, Ward 06, Binh Thanh District,
A10: CANADA | D10: Ho Chi Minh, 70000, VIETNAM
A11: Notify : | D11: Actual manufacturer :
A12: SUPREME MUNSINGWEAR CANADA INC. | D12: F2526-SCAVI HUE COMPANY
A13: 1938 AVENUE RD - 2ND FLOOR, ONTARIO, TORONTO, M5M 4A1 | D13: PHONG DIEN INDUSTRIAL ZONE,
A14: CANADA | D14: PHONG DIEN TOWN, PHONG DIEN DISTRICT, PHONG DIEN, 530000
D15: VIETNAM
A16: PORT OF DEPARTURE: | B16: VANCOUVER, BC | D16: Other references
A17: ='[2]commercial '!A15 -> VESSEL NO: | B17: YM INITIATIVE 283N | D17: Country of origin: | E17: VIETNAM
A18: ='[2]commercial '!A16 -> FCR NO:
A19: Departure date : | D19: Term of delivery and payment:
A20: TO/ DESTINATION : | B20: TORONTO, ON | D20: FOB
A21: Shipping marks : | B21: No. & kind of pkgs : Good description | D21: Quantity | E21: Gross weight | F21: Measurement
B22: PO | C22: 03SU2932
B23: NESSC318 | C23: SWIMWEAR | D23: 820 | E23: 146.57 | F23: 0.99658171
A24: PEI | B24: NESSC318 | C24: SWIMWEAR | D24: 725 | E24: 127.36 | F24: 0.87476223
A25: STYLE#: | B25: NESSC320 | C25: SWIMWEAR | D25: 110 | E25: 16.4 | F25: 0.21218717
A26: P.O.: | B26: NESSC328 | C26: SWIMWEAR | D26: 671 | E26: 169.48 | F26: 1.6796574
A27: N.W.: KGS | B27: NESSC328 | C27: SWIMWEAR | D27: 85 | E27: 21.72 | F27: 0.21628665
A28: G.W.: KGS | B28: NESSC328 | C28: SWIMWEAR | D28: 671 | E28: 169.636 | F28: 1.6796574
A29: CARTON DIMENSION: INCH | B29: NESSC329 | C29: SWIMWEAR | D29: 671 | E29: 166.3 | F29: 1.7788132
A30: SIZE | B30: NESSC329 | C30: SWIMWEAR | D30: 671 | E30: 164.64 | F30: 1.7788132
A31: QTY | B31: NESSC330 | C31: SWIMWEAR | D31: 80 | E31: 13.88 | F31: 0.16833007
A32: COLOR NAME/ CODE: | B32: NESSC332 | C32: SWIMWEAR | D32: 769 | E32: 95.895833 | F32: 1.4839256
B33: NESSC332 | C33: SWIMWEAR | D33: 766 | E33: 92.96138 | F33: 1.4839256
D35: =SUM(D23:D34) -> 6039 | E35: =SUM(E23:E34) -> 1184.8432 | F35: =SUM(F23:F34) -> 12.35294
A36: PACKING INSTRUCTIONS: FOLD PACKED
A37: * WE HEREBY CERTIFY THAT EACH CARTON IS MARKED ON THE OUTSIDE WITH AT MINIMUM THE
A38: CORRESPONDING PURCHASE ORDER NUMBER, STYLE, SIZE(S), AND COLORS CONTAINED IN THE CARTON, NET AND
A39: GROSS WEIGHT AND CUBIC MEASUREMENTS, AS WELL AS ANY OTHER MARKINGS REQUIRED BY CORRESPONDING
A40: PURCHASE ORDER.
A41: THIS IS CERTIFY THAT THE NAME OF MANUFACTURER DOES NOT APPEAR ON THE CARTONS AND THAT NO
A42: IRREGULAR CARTONS HAVE BEEN SHIPPED.
A43: *PACKING DETAILS AS PER ATTACHED SHEET
D44: SIGNED BY:

Sheet INVOICE 94
A1: COMMERCIAL INVOICE
A2: Shipper: | C2: B'LAO SPORT COMPANY LIMITED | K2: Invoice No. and date: | M2: =+N2 -> 7726477 | N2: 7726477
C3: Lot CN 37B, Zone C, Phong Dien Industrial Zone, | M3: 46120
C4: Phong Thu Ward, Phong Dien Town, Hue City, Vietnam | K4: Method of Payment: | M4: By Trade Card
C6: TAX | E6: 3301677376
A7: Consignee: | C7: SUPREME INTERNATIONAL, LLC | K7: Buyer (if other than consignee):
C8: 3000 NW 107TH AVENUE
C9: DORAL, FL 33172 | L9: Same as consignee
C10: UNITED STATES OF AMERICA
A12: Notify Party: | K12: Other references:
C13: SINGAPORE UNISERVE EGDC, UNISERVE EDGC SINGAPORE ,
C14: 27 Greenwich Drive, #1M,OFC- #02-0, WHS, SINGAPORE, 533912, SINGAPORE | K14: DIVISION CODE: | M14: SWM
A16: Final Destination: | K16: Actual manufacturer
A17: SINGAPORE UNISERVE EGDC, UNISERVE EDGC SINGAPORE ,
A18: 27 Greenwich Drive, #1M,OFC- #02-0, WHS, SINGAPORE, 533912, SINGAPORE
A20: Departure date: | B20: 46033 | F20: From: | G20: DA NANG PORT | K20: M.I.D. CODE
A22: Vessel: | B22: YM HORIZON 413S | F22: To: | G22: SINGAPORE | K22: Term of delivery :
K23: FOB VIETNAM
A24: BL NO.: | Q24: DONG FANG FU 2420N
A25: PO | B25: Reference | C25: Color | D25: GENDER | E25: Composision | H25: Carton | I25: Carton Small | J25: Quantity | K25: Unit price (USD) | M25: Amount (USD ) | O25: CO FORM
A27: GIRL/MISSY- KNIT-SWIMWEAR
A29: AJ916 | B29: NESSG277 | C29: BLACK | D29: GIRL | E29: =+VLOOKUP(B29,'[3]danh muc PERRY, YMM'!F$2625:G$2747,2,0) -> 82/18 POLYESTER/ELASTANE | H29: 4 | I29: 4 | J29: 100 | K29: =+VLOOKUP(N29,'[4]he thong'!A$1:G$45,7,0) -> 3.42 | M29: =+K29*J29 -> 342 | N29: 800005744
A30: AJ916 | B30: NESSG278 | C30: BLACK | D30: GIRL | E30: =+VLOOKUP(B30,'[3]danh muc PERRY, YMM'!F$2625:G$2747,2,0) -> 82/18 POLYESTER/ELASTANE | H30: 7 | I30: 7 | J30: 200 | K30: =+VLOOKUP(N30,'[4]he thong'!A$1:G$45,7,0) -> 3.72 | M30: =+K30*J30 -> 744 | N30: 800005745
A31: DV10 | B31: NESSB711 | C31: BLACK | E31: =+VLOOKUP(B31,'[3]danh muc PERRY, YMM'!F$2625:G$2747,2,0) -> 80/20 POLYAMIDE/ELASTANE | H31: 15 | I31: 16 | J31: 500 | K31: =+VLOOKUP(N31,'[4]he thong'!A$1:G$45,7,0) -> 3.78 | M31: =+K31*J31 -> 1890 | N31: 800005535
A32: DV10 | B32: NESSB711 | C32: DESERT PINK | E32: =+VLOOKUP(B32,'[3]danh muc PERRY, YMM'!F$2625:G$2747,2,0) -> 80/20 POLYAMIDE/ELASTANE | H32: 8 | I32: 8 | J32: 250 | K32: =+VLOOKUP(N32,'[4]he thong'!A$1:G$45,7,0) -> 3.83 | M32: =+K32*J32 -> 957.5 | N32: 800005507
A33: DV6 | B33: NESSB711 | C33: BLACK | E33: =+VLOOKUP(B33,'[3]danh muc PERRY, YMM'!F$2625:G$2747,2,0) -> 80/20 POLYAMIDE/ELASTANE | H33: 30 | I33: 30 | J33: 990 | K33: =+VLOOKUP(N33,'[4]he thong'!A$1:G$45,7,0) -> 3.78 | M33: =+K33*J33 -> 3742.2 | N33: 800005536
A34: DV6 | B34: NESSB711 | C34: DESERT PINK | E34: =+VLOOKUP(B34,'[3]danh muc PERRY, YMM'!F$2625:G$2747,2,0) -> 80/20 POLYAMIDE/ELASTANE | H34: 15 | I34: 16 | J34: 500 | K34: =+VLOOKUP(N34,'[4]he thong'!A$1:G$45,7,0) -> 3.83 | M34: =+K34*J34 -> 1915 | N34: 800005537
A35: DV7 | B35: NESSB711 | C35: BLACK | E35: =+VLOOKUP(B35,'[3]danh muc PERRY, YMM'!F$2625:G$2747,2,0) -> 80/20 POLYAMIDE/ELASTANE | H35: 15 | I35: 16 | J35: 500 | K35: =+VLOOKUP(N35,'[4]he thong'!A$1:G$45,7,0) -> 3.78 | M35: =+K35*J35 -> 1890 | N35: 800005540
A36: DV7 | B36: NESSB711 | C36: DESERT PINK | E36: =+VLOOKUP(B36,'[3]danh muc PERRY, YMM'!F$2625:G$2747,2,0) -> 80/20 POLYAMIDE/ELASTANE | H36: 8 | I36: 8 | J36: 250 | K36: =+VLOOKUP(N36,'[4]he thong'!A$1:G$45,7,0) -> 3.83 | M36: =+K36*J36 -> 957.5 | N36: 800005541
A37: EQ349 | B37: NESSB711 | C37: ENERGY | E37: =+VLOOKUP(B37,'[3]danh muc PERRY, YMM'!F$2625:G$2747,2,0) -> 80/20 POLYAMIDE/ELASTANE | H37: 3 | I37: 4 | J37: 48 | K37: =+VLOOKUP(N37,'[4]he thong'!A$1:G$45,7,0) -> 3.81 | M37: =+K37*J37 -> 182.88 | N37: 800005754
A38: EV154 | B38: NESSB711 | C38: BLACK | E38: =+VLOOKUP(B38,'[3]danh muc PERRY, YMM'!F$2625:G$2747,2,0) -> 80/20 POLYAMIDE/ELASTANE | H38: 5 | I38: 5 | J38: 120 | K38: =+VLOOKUP(N38,'[4]he thong'!A$1:G$45,7,0) -> 3.75 | M38: =+K38*J38 -> 450 | N38: 800005755
A39: EV154 | B39: NESSB711 | C39: ENERGY | E39: =+VLOOKUP(B39,'[3]danh muc PERRY, YMM'!F$2625:G$2747,2,0) -> 80/20 POLYAMIDE/ELASTANE | H39: 5 | I39: 5 | J39: 120 | K39: =+VLOOKUP(N39,'[4]he thong'!A$1:G$45,7,0) -> 3.8 | M39: =+K39*J39 -> 456 | N39: 800005756
A40: EV154 | B40: NESSB711 | C40: DESERT PINK | E40: =+VLOOKUP(B40,'[3]danh muc PERRY, YMM'!F$2625:G$2747,2,0) -> 80/20 POLYAMIDE/ELASTANE | H40: 5 | I40: 5 | J40: 120 | K40: =+VLOOKUP(N40,'[4]he thong'!A$1:G$45,7,0) -> 3.8 | M40: =+K40*J40 -> 456 | N40: 800005757
A41: EV154 | B41: NESSG730 | C41: BLACK | E41: =+VLOOKUP(B41,'[3]danh muc PERRY, YMM'!F$2625:G$2747,2,0) -> 80/20 POLYAMIDE/ELASTANE | H41: 5 | I41: 5 | J41: 96 | K41: =+VLOOKUP(N41,'[4]he thong'!A$1:G$45,7,0) -> 5.18 | M41: =+K41*J41 -> 497.28 | N41: 800005758
A42: EV154 | B42: NESSG730 | C42: DESERT PINK | E42: =+VLOOKUP(B42,'[3]danh muc PERRY, YMM'!F$2625:G$2747,2,0) -> 80/20 POLYAMIDE/ELASTANE | H42: 5 | I42: 5 | J42: 96 | K42: =+VLOOKUP(N42,'[4]he thong'!A$1:G$45,7,0) -> 5.42 | M42: =+K42*J42 -> 520.32 | N42: 800005759
... A71: XL102 | B71: NESSB711 | C71: DESERT PINK | E71: =+VLOOKUP(B71,'[3]danh muc PERRY, YMM'!F$2625:G$2747,2,0) -> 80/20 POLYAMIDE/ELASTANE | H71: 1 | I71: 4 | J71: 24 | K71: =+VLOOKUP(N71,'[4]he thong'!A$1:G$45,7,0) -> 3.81 | M71: =+K71*J71 -> 91.44 | N71: 800005787
H74: =SUM(H29:H73) -> 243 | I74: =SUM(I29:I73) -> 282 | J74: =SUM(J29:J73) -> 6266 | M74: =SUM(M29:M73) -> 26432.36
A77: SAY TOTAL US DOLLARS | B77: {=+UPPER(_xll.USD(M74))} -> TWENTY SIX THOUSAND FOUR HUNDRED AND THIRTY TWO DOLLARS AND THIRTY SIX CENTS.
A78: TTL: | B78: =+H74 -> 243
A81: *WE HEREBY CERTIFY THAT THE FABRIC IS PIECE DYED AND THERE IS SOLID COLOR IN THE WARP AND FILLINGS.
A82: * WE HEREBY CERTIFY THAT CONCERNED SHIPMENT DOES NOT CONTAIN SOLID WOOD PACKAGING MATERIALS.
A84: *TOTAL NET NET WEIGHT: | F84: =+F85*0.9 -> 609.723 | G84: KGS
A85: *TOTAL NET WEIGHT: | F85: 677.47 | G85: KGS
A86: *TOTAL GROSS WEIGHT: | F86: 1010.4667 | G86: KGS
A87: *TOTAL MEASUREMENT: | F87: 5.3928845 | G87: M3 | P87: =0.18/10 -> 0.018
A89: *WE HEREBY CERTIFY THAT MERCHANDISE COVERED BY THIS INVOICE HAS BEEN LABELED IN ACCORDANCE | P89: =+P87*#REF! -> #REF!
A90: WITH UNITED STATES OF AMERICA GOVERNMENT REGULATIONS.
J91: B'LAO SPORT COMPANY LIMITED
J92: Signed by
A97: * WE CERTIFY THAT ALL STATEMENTS INDICATED ARE TRUE AND CORRECT

Sheet AJ916
A1: B'LAO SPORT COMPANY LIMITED
A2: Lot CN 37B, Zone C, Phong Dien Industrial Zone,
A3: Phong Thu Ward, Phong Dien Town, Hue City, Vietnam
A5: DETAIL BREAKDOWN - By MASTER BOX
A6: PO# | B6: AJ916
A7: CTNS: | B7: =+L24 -> 11
A9: STYLE | B9: COLOR | C9: COLOR CODE | D9: CASE FROM- TO | F9: Units/case | G9: xs | H9: S | I9: M | J9: L | K9: XL | L9: TOT CTNS | M9: TOT PCS | N9: GW | O9: DIM
A10: NESSG277 | B10: 001 BLACK | C10: 001 | D10: 1 | E10: 1 | F10: 5 | G10: 5 | L10: 1 | M10: 5 | N10: 0.84 | O10: 43.18*41.91*7.62 | P10: 9 | Q10: 9 | R10: 3 | S10: =+P10*2.54 -> 22.86 | T10: =+Q10*2.54 -> 22.86 | U10: =+R10*2.54 -> 7.62 | V10: =S10&"*"&T10&"*"&U10 -> 22.86*22.86*7.62
A11: NESSG277 | B11: 001 BLACK | C11: 001 | D11: 2 | E11: 2 | F11: 27 | H11: 27 | L11: 1 | M11: 27 | N11: 2.76 | O11: 43.18*41.91*7.62 | P11: 16 | Q11: 15.5 | R11: 4 | S11: =+P11*2.54 -> 40.64 | T11: =+Q11*2.54 -> 39.37 | U11: =+R11*2.54 -> 10.16 | V11: =S11&"*"&T11&"*"&U11 -> 40.64*39.37*10.16
A12: NESSG277 | B12: 001 BLACK | C12: 001 | D12: 3 | E12: 3 | F12: 35 | I12: 35 | L12: 1 | M12: 35 | N12: 3.84 | O12: 43.18*41.91*7.62 | P12: 16 | Q12: 15 | R12: 4.5 | S12: =+P12*2.54 -> 40.64 | T12: =+Q12*2.54 -> 38.1 | U12: =+R12*2.54 -> 11.43 | V12: =S12&"*"&T12&"*"&U12 -> 40.64*38.1*11.43
A13: NESSG277 | B13: 001 BLACK | C13: 001 | D13: 4 | E13: 4 | F13: 33 | J13: 33 | L13: 1 | M13: 33 | N13: 4.11 | O13: 44.45*44.45*8.89 | P13: 16 | Q13: 15 | R13: 5.5 | S13: =+P13*2.54 -> 40.64 | T13: =+Q13*2.54 -> 38.1 | U13: =+R13*2.54 -> 13.97 | V13: =S13&"*"&T13&"*"&U13 -> 40.64*38.1*13.97
L14: 4 | M14: 100 | N14: 11.55 | S14: =+P14*2.54 -> 0 | T14: =+Q14*2.54 -> 0 | U14: =+R14*2.54 -> 0 | V14: =S14&"*"&T14&"*"&U14 -> 0*0*0
A15: NESSG278 | B15: 001 BLACK | C15: 001 | D15: 5 | E15: 5 | F15: 36 | H15: 36 | L15: 1 | M15: 36 | N15: 3.9 | O15: 43.18*41.91*7.62 | P15: 16 | Q15: 15 | R15: 7.5 | S15: =+P15*2.54 -> 40.64 | T15: =+Q15*2.54 -> 38.1 | U15: =+R15*2.54 -> 19.05 | V15: =S15&"*"&T15&"*"&U15 -> 40.64*38.1*19.05
A16: NESSG278 | B16: 001 BLACK | C16: 001 | D16: 6 | E16: 6 | F16: 36 | I16: 36 | L16: 1 | M16: 36 | N16: 4.14 | O16: 43.18*41.91*7.62 | P16: 16 | Q16: 15 | R16: 7.5 | S16: =+P16*2.54 -> 40.64 | T16: =+Q16*2.54 -> 38.1 | U16: =+R16*2.54 -> 19.05 | V16: =S16&"*"&T16&"*"&U16 -> 40.64*38.1*19.05
A17: NESSG278 | B17: 001 BLACK | C17: 001 | D17: 7 | E17: 7 | F17: 36 | J17: 36 | L17: 1 | M17: 36 | N17: 4.41 | O17: 43.18*41.91*7.62 | P17: 16 | Q17: 15 | R17: 7.5 | S17: =+P17*2.54 -> 40.64 | T17: =+Q17*2.54 -> 38.1 | U17: =+R17*2.54 -> 19.05 | V17: =S17&"*"&T17&"*"&U17 -> 40.64*38.1*19.05
A18: NESSG278 | B18: 001 BLACK | C18: 001 | D18: 8 | E18: 8 | F18: 26 | G18: 26 | L18: 1 | M18: 26 | N18: 2.665 | O18: 44.45*44.45*8.89 | P18: 16 | Q18: 15 | R18: 5.5 | S18: =+P18*2.54 -> 40.64 | T18: =+Q18*2.54 -> 38.1 | U18: =+R18*2.54 -> 13.97 | V18: =S18&"*"&T18&"*"&U18 -> 40.64*38.1*13.97
A19: NESSG278 | B19: 001 BLACK | C19: 001 | D19: 9 | E19: 9 | F19: 14 | H19: 14 | L19: 1 | M19: 14 | N19: 1.5166667 | O19: 44.45*44.45*8.89 | P19: 16 | Q19: 15.5 | R19: 3 | S19: =+P19*2.54 -> 40.64 | T19: =+Q19*2.54 -> 39.37 | U19: =+R19*2.54 -> 7.62 | V19: =S19&"*"&T19&"*"&U19 -> 40.64*39.37*7.62
A20: NESSG278 | B20: 001 BLACK | C20: 001 | D20: 10 | E20: 10 | F20: 34 | I20: 34 | L20: 1 | M20: 34 | N20: 3.91 | O20: 44.45*44.45*8.89 | P20: 16 | Q20: 15 | R20: 7.5 | S20: =+P20*2.54 -> 40.64 | T20: =+Q20*2.54 -> 38.1 | U20: =+R20*2.54 -> 19.05 | V20: =S20&"*"&T20&"*"&U20 -> 40.64*38.1*19.05
A21: NESSG278 | B21: 001 BLACK | C21: 001 | D21: 11 | E21: 11 | F21: 18 | J21: 18 | L21: 1 | M21: 18 | N21: 2.205 | O21: 44.45*44.45*8.89 | P21: 16 | Q21: 15.5 | R21: 4 | S21: =+P21*2.54 -> 40.64 | T21: =+Q21*2.54 -> 39.37 | U21: =+R21*2.54 -> 10.16 | V21: =S21&"*"&T21&"*"&U21 -> 40.64*39.37*10.16
L22: 7 | M22: 200 | N22: 22.746667 | S22: =+P22*2.54 -> 0 | T22: =+Q22*2.54 -> 0 | U22: =+R22*2.54 -> 0 | V22: =S22&"*"&T22&"*"&U22 -> 0*0*0
L24: =+L22+L14 -> 11 | M24: =+M22+M14 -> 300 | N24: =+N22+N14 -> 34.296667

Sheet PLS AJ916
A1: PACKING LIST - By MASTER BOX
A2: SUMMARY BREAKDOWN
A4: PO# | B4: =+'AJ916'!B6 -> AJ916
A5: CTNS: | B5: =+I10 -> 11
A6: STYLE | B6: COLOR | C6: COLOR CODE | D6: xs | E6: S | F6: M | G6: L | H6: XL | I6: TOT CTNS | J6: TOT PCS
A7: NESSG277 | B7: BLACK | C7: 001 | D7: 5 | E7: 27 | F7: 35 | G7: 33 | I7: 4 | J7: 100 | K7: =+SUM(D7:H7) -> 100 | L7: =+K7-J7 -> 0
A8: NESSG278 | B8: BLACK | C8: 001 | D8: 26 | E8: 50 | F8: 70 | G8: 54 | I8: 7 | J8: 200 | K8: =+SUM(D8:H8) -> 200 | L8: =+K8-J8 -> 0
A10: TOTAL | I10: =SUM(I7:I9) -> 11 | J10: =SUM(J7:J9) -> 300
A11: Carton Specs & Shipment Specs :
A12: Purchase Order: | B12: =+B4 -> AJ916 | C12: GRAND TOTAL | D12: SIGNED BY:
A13: Total cartons: | B13: =+C13 -> 11 | C13: =+I10 -> 11
A14: Total Gross Wt:(kgs) | B14: =+C14/$B$13 -> 3.1178788 | C14: 34.296667
A15: Total Net Wt:(kgs) | B15: =+C15/$B$13 -> 2.4554545 | C15: 27.01
A16: Total Net Net Wt:(kgs)
A17: Empty carton Wt
A18: CMB: | B18: =+C18/$B$13 -> 0.021467909 | C18: 0.236147
A19: Carton Dimensions:
A20: CM
N26: =SUM(N10:N25) -> 0
B286: -52 | C286: -39
B287: -52 | C287: -39
B288: -52 | C288: -39
B289: -52 | C289: -39
B290: -52 | C290: -39
B291: -52 | C291: -39
B292: -52 | C292: -39
A293: TOTAL: | C293: -39
B294: -52 | C294: -39
B296: -52 | C296: -39
B297: -52 | C297: -39
B298: -52 | C298: -39
B299: -52 | C299: -39
B300: -52 | C300: -39
B301: -52 | C301: -39
B302: -52 | C302: -39
B304: 0 | C304: 0
A311: TOTAL:
A312: GRAND TOTAL:

Sheet SOLID PL DV10
A4: PACKING LIST
H5: PEI
A6: ISSUE TO : | E6: =+'[1]INVOICE 11'!C7 -> SUPREME INTERNATIONAL, LLC | H6: STYLE:
H7: LABEL
H8: P.O.:
H9: PCS
H10: SIZES
A12: PAYMENT: T/C | H12: MADE IN
A13: PO NO: | B13: DV10 | H13: C# UP
A14: CUSTOMER PO.: | E14: =+B13 -> DV10
A15: INVOICE NO: | D15: =+'INVOICE 94'!M2 -> 7726477
A16: Detail Breakdown
A18: CASE FROM-TO | D18: REMARKS | E18: Style | F18: Color Name | G18: Color code | H18: Units/case | I18: xs | J18: S | K18: M | L18: L | M18: 4 | N18: 5 | O18: 6 | P18: 6X | Q18: TOT CTNS | R18: TOT PCS | S18: NW | T18: GW | U18: TTL NW | V18: TTL GW | W18: CARTON SIZE ( CM)
A19: 1 | C19: 2 | E19: NESSB711 | F19: 001 BLACK | G19: 001 | H19: 36 | J19: 36 | Q19: 2 | R19: 72 | S19: =+U19/Q19 -> 3.32 | T19: =+V19/Q19 -> 4.32 | U19: 6.64 | V19: 8.64 | W19: =AA19&"*"&AB19&"*"&AC19 -> 50.8*43.18*11.43 | X19: 20 | Y19: 17 | Z19: 4.5 | AA19: =+X19*2.54 -> 50.8 | AB19: =+Y19*2.54 -> 43.18 | AC19: =+Z19*2.54 -> 11.43
A20: 3 | C20: 6 | H20: 36 | K20: 36 | Q20: 4 | R20: 144 | S20: =+U20/Q20 -> 3.64 | T20: =+V20/Q20 -> 4.64 | U20: 14.56 | V20: 18.56 | W20: =AA20&"*"&AB20&"*"&AC20 -> 50.8*43.18*11.43 | X20: 20 | Y20: 17 | Z20: 4.5 | AA20: =+X20*2.54 -> 50.8 | AB20: =+Y20*2.54 -> 43.18 | AC20: =+Z20*2.54 -> 11.43
A21: 7 | C21: 10 | H21: 36 | L21: 36 | Q21: 4 | R21: 144 | S21: =+U21/Q21 -> 3.93 | T21: =+V21/Q21 -> 4.96 | U21: 15.72 | V21: 19.84 | W21: =AA21&"*"&AB21&"*"&AC21 -> 50.8*43.18*12.7 | X21: 20 | Y21: 17 | Z21: 5 | AA21: =+X21*2.54 -> 50.8 | AB21: =+Y21*2.54 -> 43.18 | AC21: =+Z21*2.54 -> 12.7
A22: 11 | C22: 12 | H22: 36 | M22: 36 | Q22: 2 | R22: 72 | S22: =+U22/Q22 -> 4.25 | T22: =+V22/Q22 -> 5.28 | U22: 8.5 | V22: 10.56 | W22: =AA22&"*"&AB22&"*"&AC22 -> 50.8*43.18*12.7 | X22: 20 | Y22: 17 | Z22: 5 | AA22: =+X22*2.54 -> 50.8 | AB22: =+Y22*2.54 -> 43.18 | AC22: =+Z22*2.54 -> 12.7
A23: 13 | C23: 13 | D23: ODD CARTON | H23: 28 | J23: 28 | Q23: 1 | R23: 28 | S23: =+U23/Q23 -> 2.36 | T23: =+V23/Q23 -> 3.36 | U23: 2.36 | V23: 3.36 | W23: =AA23&"*"&AB23&"*"&AC23 -> 50.8*43.18*10.16 | X23: 20 | Y23: 17 | Z23: 4 | AA23: =+X23*2.54 -> 50.8 | AB23: =+Y23*2.54 -> 43.18 | AC23: =+Z23*2.54 -> 10.16
A24: 14 | C24: 14 | D24: ODD CARTON | H24: 28 | M24: 28 | Q24: 1 | R24: 28 | S24: =+U24/Q24 -> 3.1 | T24: =+V24/Q24 -> 4.1 | U24: 3.1 | V24: 4.1 | W24: =AA24&"*"&AB24&"*"&AC24 -> 50.8*43.18*11.43 | X24: 20 | Y24: 17 | Z24: 4.5 | AA24: =+X24*2.54 -> 50.8 | AB24: =+Y24*2.54 -> 43.18 | AC24: =+Z24*2.54 -> 11.43
A25: Master box 15-16 | D25: Master box | X25: 19 | Y25: 11 | Z25: 4.5 | AA25: =+X25*2.54 -> 48.26 | AB25: =+Y25*2.54 -> 27.94 | AC25: =+Z25*2.54 -> 11.43
A26: 15 | C26: 15 | D26: Small box | H26: 6 | K26: 6 | Q26: 1 | R26: 6 | S26: =+U26/Q26 -> 1.75 | T26: =+V26/Q26 -> 2.22 | U26: 1.75 | V26: 2.22 | W26: =AA26&"*"&AB26&"*"&AC26 -> 25.4*22.86*8.89 | X26: 10 | Y26: 9 | Z26: 3.5 | AA26: =+X26*2.54 -> 25.4 | AB26: =+Y26*2.54 -> 22.86 | AC26: =+Z26*2.54 -> 8.89
A27: 16 | C27: 16 | D27: Small box | H27: 6 | L27: 6 | R27: 6 | W27: =AA27&"*"&AB27&"*"&AC27 -> 25.4*22.86*8.89 | X27: 10 | Y27: 9 | Z27: 3.5 | AA27: =+X27*2.54 -> 25.4 | AB27: =+Y27*2.54 -> 22.86 | AC27: =+Z27*2.54 -> 8.89
M28: 100
A29: 17 | C29: 17 | E29: NESSB711 | F29: 655 DESERT PINK | G29: 655 | H29: 36 | J29: 36 | Q29: 1 | R29: 36 | S29: =+U29/Q29 -> 3.32 | T29: =+V29/Q29 -> 4.32 | U29: 3.32 | V29: 4.32 | W29: =AA29&"*"&AB29&"*"&AC29 -> 50.8*43.18*11.43 | X29: 20 | Y29: 17 | Z29: 4.5 | AA29: =+X29*2.54 -> 50.8 | AB29: =+Y29*2.54 -> 43.18 | AC29: =+Z29*2.54 -> 11.43
A30: 18 | C30: 18 | H30: 36 | K30: 36 | Q30: 1 | R30: 36 | S30: =+U30/Q30 -> 3.64 | T30: =+V30/Q30 -> 4.64 | U30: 3.64 | V30: 4.64 | W30: =AA30&"*"&AB30&"*"&AC30 -> 50.8*43.18*11.43 | X30: 20 | Y30: 17 | Z30: 4.5 | AA30: =+X30*2.54 -> 50.8 | AB30: =+Y30*2.54 -> 43.18 | AC30: =+Z30*2.54 -> 11.43
A31: 19 | C31: 19 | H31: 39 | K31: 39 | Q31: 1 | R31: 39 | S31: =+U31/Q31 -> 1.84 | T31: =+V31/Q31 -> 4.84 | U31: 1.84 | V31: 4.84 | W31: =AA31&"*"&AB31&"*"&AC31 -> 50.8*43.18*12.7 | X31: 20 | Y31: 17 | Z31: 5 | AA31: =+X31*2.54 -> 50.8 | AB31: =+Y31*2.54 -> 43.18 | AC31: =+Z31*2.54 -> 12.7
A32: 20 | C32: 20 | H32: 36 | L32: 36 | Q32: 1 | R32: 36 | S32: =+U32/Q32 -> 3.96 | T32: =+V32/Q32 -> 4.96 | U32: 3.96 | V32: 4.96 | W32: =AA32&"*"&AB32&"*"&AC32 -> 50.8*43.18*11.43 | X32: 20 | Y32: 17 | Z32: 4.5 | AA32: =+X32*2.54 -> 50.8 | AB32: =+Y32*2.54 -> 43.18 | AC32: =+Z32*2.54 -> 11.43
A33: 21 | C33: 21 | H33: 39 | L33: 39 | Q33: 1 | R33: 39 | S33: =+U33/Q33 -> 2.02 | T33: =+V33/Q33 -> 5.02 | U33: 2.02 | V33: 5.02 | W33: =AA33&"*"&AB33&"*"&AC33 -> 50.8*43.18*12.7 | X33: 20 | Y33: 17 | Z33: 5 | AA33: =+X33*2.54 -> 50.8 | AB33: =+Y33*2.54 -> 43.18 | AC33: =+Z33*2.54 -> 12.7
A34: 22 | C34: 22 | H34: 36 | M34: 36 | Q34: 1 | R34: 36 | S34: =+U34/Q34 -> 2.28 | T34: =+V34/Q34 -> 5.28 | U34: 2.28 | V34: 5.28 | W34: =AA34&"*"&AB34&"*"&AC34 -> 50.8*43.18*12.7 | X34: 20 | Y34: 17 | Z34: 5 | AA34: =+X34*2.54 -> 50.8 | AB34: =+Y34*2.54 -> 43.18 | AC34: =+Z34*2.54 -> 12.7
A35: 23 | C35: 23 | D35: ODD CARTON | H35: 14 | J35: 14 | Q35: 1 | R35: 14 | S35: =+U35/Q35 -> 1.24 | T35: =+V35/Q35 -> 1.68 | U35: 1.24 | V35: 1.68 | W35: =AA35&"*"&AB35&"*"&AC35 -> 44.45*25.4*7.62 | X35: 17.5 | Y35: 10 | Z35: 3 | AA35: =+X35*2.54 -> 44.45 | AB35: =+Y35*2.54 -> 25.4 | AC35: =+Z35*2.54 -> 7.62
A36: 24 | C36: 24 | D36: ODD CARTON | H36: 14 | M36: 14 | Q36: 1 | R36: 14 | S36: =+U36/Q36 -> 1.61 | T36: =+V36/Q36 -> 2.05 | U36: 1.61 | V36: 2.05 | W36: =AA36&"*"&AB36&"*"&AC36 -> 44.45*25.4*7.62 | X36: 17.5 | Y36: 10 | Z36: 3 | AA36: =+X36*2.54 -> 44.45 | AB36: =+Y36*2.54 -> 25.4 | AC36: =+Z36*2.54 -> 7.62
M37: 50
M39: =SUM(M19:M38) -> 264 | N39: =SUM(N19:N38) -> 0 | O39: =SUM(O19:O38) -> 0 | P39: =SUM(P19:P38) -> 0 | Q39: =SUM(Q19:Q38) -> 23 | R39: =SUM(R19:R38) -> 750 | U39: =SUM(U19:U38) -> 72.54 | V39: =SUM(V19:V38) -> 100.07
D42: CUSTOMER PO | E42: Style | F42: Color | G42: Color Code | H42: xs | I42: S | J42: M | K42: L | L42: XL | Q42: TOT CTNS | R42: TOT PCS
D43: DV10 | E43: NESSB711 | F43: BLACK | G43: 001 | I43: 100 | J43: 150 | K43: 150 | L43: 100 | Q43: 15 | R43: 500 | X43: =+SUM(H43:L43) -> 500 | Y43: =+R43-X43 -> 0
D44: DV10 | E44: NESSB711 | F44: DESERT PINK | G44: 655 | I44: 50 | J44: 75 | K44: 75 | L44: 50 | Q44: 8 | R44: 250 | X44: =+SUM(H44:L44) -> 250 | Y44: =+R44-X44 -> 0
K46: TOTAL | Q46: =SUM(Q43:Q44) -> 23 | R46: =SUM(R43:R44) -> 750

Sheet IRREGULAR SS PLDV10
A4: PACKING LIST
H5: PEI
A6: ISSUE TO : | E6: =+'[1]INVOICE 11'!C7 -> SUPREME INTERNATIONAL, LLC | H6: STYLE:
H7: LABEL
H8: P.O.:
H9: PCS
H10: SIZES
A12: PAYMENT: T/C | H12: MADE IN
A13: PO NO: | B13: DV10 | H13: C# UP
A14: CUSTOMER PO.: | E14: =+B13 -> DV10
A15: INVOICE NO: | D15: =+'INVOICE 94'!M2 -> 7726477
A16: Detail Breakdown
A18: CASE FROM-TO | D18: REMARKS | E18: Style | F18: Color Name | G18: Color code | H18: Units/case | I18: xs | J18: S | K18: M | L18: L | M18: 4 | N18: 5 | O18: 6 | P18: 6X | Q18: TOT CTNS | R18: TOT PCS | S18: NW | T18: GW | U18: TTL NW | V18: TTL GW | W18: CARTON SIZE ( CM)
A19: 1 | C19: 2 | E19: NESSB711 | F19: 001 BLACK | G19: 001 | H19: 36 | J19: 36 | Q19: 2 | R19: 72 | S19: =+U19/Q19 -> 3.32 | T19: =+V19/Q19 -> 4.32 | U19: 6.64 | V19: 8.64 | W19: =AA19&"*"&AB19&"*"&AC19 -> 50.8*43.18*11.43 | X19: 20 | Y19: 17 | Z19: 4.5 | AA19: =+X19*2.54 -> 50.8 | AB19: =+Y19*2.54 -> 43.18 | AC19: =+Z19*2.54 -> 11.43
A20: 3 | C20: 6 | H20: 36 | K20: 36 | Q20: 4 | R20: 144 | S20: =+U20/Q20 -> 3.64 | T20: =+V20/Q20 -> 4.64 | U20: 14.56 | V20: 18.56 | W20: =AA20&"*"&AB20&"*"&AC20 -> 50.8*43.18*11.43 | X20: 20 | Y20: 17 | Z20: 4.5 | AA20: =+X20*2.54 -> 50.8 | AB20: =+Y20*2.54 -> 43.18 | AC20: =+Z20*2.54 -> 11.43
A21: 7 | C21: 10 | H21: 36 | L21: 36 | Q21: 4 | R21: 144 | S21: =+U21/Q21 -> 3.93 | T21: =+V21/Q21 -> 4.96 | U21: 15.72 | V21: 19.84 | W21: =AA21&"*"&AB21&"*"&AC21 -> 50.8*43.18*12.7 | X21: 20 | Y21: 17 | Z21: 5 | AA21: =+X21*2.54 -> 50.8 | AB21: =+Y21*2.54 -> 43.18 | AC21: =+Z21*2.54 -> 12.7
A22: 11 | C22: 12 | H22: 36 | M22: 36 | Q22: 2 | R22: 72 | S22: =+U22/Q22 -> 4.25 | T22: =+V22/Q22 -> 5.28 | U22: 8.5 | V22: 10.56 | W22: =AA22&"*"&AB22&"*"&AC22 -> 50.8*43.18*12.7 | X22: 20 | Y22: 17 | Z22: 5 | AA22: =+X22*2.54 -> 50.8 | AB22: =+Y22*2.54 -> 43.18 | AC22: =+Z22*2.54 -> 12.7
A23: 13 | C23: 13 | D23: ODD CARTON | H23: 28 | J23: 28 | Q23: 1 | R23: 28 | S23: =+U23/Q23 -> 2.36 | T23: =+V23/Q23 -> 3.36 | U23: 2.36 | V23: 3.36 | W23: =AA23&"*"&AB23&"*"&AC23 -> 50.8*43.18*10.16 | X23: 20 | Y23: 17 | Z23: 4 | AA23: =+X23*2.54 -> 50.8 | AB23: =+Y23*2.54 -> 43.18 | AC23: =+Z23*2.54 -> 10.16
A24: 14 | C24: 14 | D24: ODD CARTON | H24: 28 | M24: 28 | Q24: 1 | R24: 28 | S24: =+U24/Q24 -> 3.1 | T24: =+V24/Q24 -> 4.1 | U24: 3.1 | V24: 4.1 | W24: =AA24&"*"&AB24&"*"&AC24 -> 50.8*43.18*11.43 | X24: 20 | Y24: 17 | Z24: 4.5 | AA24: =+X24*2.54 -> 50.8 | AB24: =+Y24*2.54 -> 43.18 | AC24: =+Z24*2.54 -> 11.43
A25: Master box 15-16 | D25: Master box | X25: 19 | Y25: 11 | Z25: 4.5 | AA25: =+X25*2.54 -> 48.26 | AB25: =+Y25*2.54 -> 27.94 | AC25: =+Z25*2.54 -> 11.43
A26: 15 | C26: 15 | D26: Small box | H26: 6 | K26: 6 | Q26: 1 | R26: 6 | S26: =+U26/Q26 -> 1.75 | T26: =+V26/Q26 -> 2.22 | U26: 1.75 | V26: 2.22 | W26: =AA26&"*"&AB26&"*"&AC26 -> 25.4*22.86*8.89 | X26: 10 | Y26: 9 | Z26: 3.5 | AA26: =+X26*2.54 -> 25.4 | AB26: =+Y26*2.54 -> 22.86 | AC26: =+Z26*2.54 -> 8.89
A27: 16 | C27: 16 | D27: Small box | H27: 6 | L27: 6 | Q27: 1 | R27: 6 | W27: =AA27&"*"&AB27&"*"&AC27 -> 25.4*22.86*8.89 | X27: 10 | Y27: 9 | Z27: 3.5 | AA27: =+X27*2.54 -> 25.4 | AB27: =+Y27*2.54 -> 22.86 | AC27: =+Z27*2.54 -> 8.89
M28: 100
A29: 17 | C29: 17 | E29: NESSB711 | F29: 655 DESERT PINK | G29: 655 | H29: 36 | J29: 36 | Q29: 1 | R29: 36 | S29: =+U29/Q29 -> 3.32 | T29: =+V29/Q29 -> 4.32 | U29: 3.32 | V29: 4.32 | W29: =AA29&"*"&AB29&"*"&AC29 -> 50.8*43.18*11.43 | X29: 20 | Y29: 17 | Z29: 4.5 | AA29: =+X29*2.54 -> 50.8 | AB29: =+Y29*2.54 -> 43.18 | AC29: =+Z29*2.54 -> 11.43
A30: 18 | C30: 18 | H30: 36 | K30: 36 | Q30: 1 | R30: 36 | S30: =+U30/Q30 -> 3.64 | T30: =+V30/Q30 -> 4.64 | U30: 3.64 | V30: 4.64 | W30: =AA30&"*"&AB30&"*"&AC30 -> 50.8*43.18*11.43 | X30: 20 | Y30: 17 | Z30: 4.5 | AA30: =+X30*2.54 -> 50.8 | AB30: =+Y30*2.54 -> 43.18 | AC30: =+Z30*2.54 -> 11.43
A31: 19 | C31: 19 | H31: 39 | K31: 39 | Q31: 1 | R31: 39 | S31: =+U31/Q31 -> 1.84 | T31: =+V31/Q31 -> 4.84 | U31: 1.84 | V31: 4.84 | W31: =AA31&"*"&AB31&"*"&AC31 -> 50.8*43.18*12.7 | X31: 20 | Y31: 17 | Z31: 5 | AA31: =+X31*2.54 -> 50.8 | AB31: =+Y31*2.54 -> 43.18 | AC31: =+Z31*2.54 -> 12.7
A32: 20 | C32: 20 | H32: 36 | L32: 36 | Q32: 1 | R32: 36 | S32: =+U32/Q32 -> 3.96 | T32: =+V32/Q32 -> 4.96 | U32: 3.96 | V32: 4.96 | W32: =AA32&"*"&AB32&"*"&AC32 -> 50.8*43.18*11.43 | X32: 20 | Y32: 17 | Z32: 4.5 | AA32: =+X32*2.54 -> 50.8 | AB32: =+Y32*2.54 -> 43.18 | AC32: =+Z32*2.54 -> 11.43
A33: 21 | C33: 21 | H33: 39 | L33: 39 | Q33: 1 | R33: 39 | S33: =+U33/Q33 -> 2.02 | T33: =+V33/Q33 -> 5.02 | U33: 2.02 | V33: 5.02 | W33: =AA33&"*"&AB33&"*"&AC33 -> 50.8*43.18*12.7 | X33: 20 | Y33: 17 | Z33: 5 | AA33: =+X33*2.54 -> 50.8 | AB33: =+Y33*2.54 -> 43.18 | AC33: =+Z33*2.54 -> 12.7
A34: 22 | C34: 22 | H34: 36 | M34: 36 | Q34: 1 | R34: 36 | S34: =+U34/Q34 -> 2.28 | T34: =+V34/Q34 -> 5.28 | U34: 2.28 | V34: 5.28 | W34: =AA34&"*"&AB34&"*"&AC34 -> 50.8*43.18*12.7 | X34: 20 | Y34: 17 | Z34: 5 | AA34: =+X34*2.54 -> 50.8 | AB34: =+Y34*2.54 -> 43.18 | AC34: =+Z34*2.54 -> 12.7
A35: 23 | C35: 23 | D35: ODD CARTON | H35: 14 | J35: 14 | Q35: 1 | R35: 14 | S35: =+U35/Q35 -> 1.24 | T35: =+V35/Q35 -> 1.68 | U35: 1.24 | V35: 1.68 | W35: =AA35&"*"&AB35&"*"&AC35 -> 44.45*25.4*7.62 | X35: 17.5 | Y35: 10 | Z35: 3 | AA35: =+X35*2.54 -> 44.45 | AB35: =+Y35*2.54 -> 25.4 | AC35: =+Z35*2.54 -> 7.62
A36: 24 | C36: 24 | D36: ODD CARTON | H36: 14 | M36: 14 | Q36: 1 | R36: 14 | S36: =+U36/Q36 -> 1.61 | T36: =+V36/Q36 -> 2.05 | U36: 1.61 | V36: 2.05 | W36: =AA36&"*"&AB36&"*"&AC36 -> 44.45*25.4*7.62 | X36: 17.5 | Y36: 10 | Z36: 3 | AA36: =+X36*2.54 -> 44.45 | AB36: =+Y36*2.54 -> 25.4 | AC36: =+Z36*2.54 -> 7.62
M37: 50
M39: =SUM(M19:M38) -> 264 | N39: =SUM(N19:N38) -> 0 | O39: =SUM(O19:O38) -> 0 | P39: =SUM(P19:P38) -> 0 | Q39: =SUM(Q19:Q38) -> 24 | R39: =SUM(R19:R38) -> 750 | U39: =SUM(U19:U38) -> 72.54 | V39: =SUM(V19:V38) -> 100.07
D42: CUSTOMER PO | E42: Style | F42: Color | G42: Color Code | H42: xs | I42: S | J42: M | K42: L | L42: XL | Q42: TOT CTNS | R42: TOT PCS
D43: DV10 | E43: NESSB711 | F43: BLACK | G43: 001 | I43: 100 | J43: 150 | K43: 150 | L43: 100 | Q43: 16 | R43: 500 | X43: =+SUM(H43:L43) -> 500 | Y43: =+R43-X43 -> 0
D44: DV10 | E44: NESSB711 | F44: DESERT PINK | G44: 655 | I44: 50 | J44: 75 | K44: 75 | L44: 50 | Q44: 8 | R44: 250 | X44: =+SUM(H44:L44) -> 250 | Y44: =+R44-X44 -> 0
K46: TOTAL | Q46: =SUM(Q43:Q44) -> 24 | R46: =SUM(R43:R44) -> 750

Sheet SOLID PL DV6
A4: PACKING LIST
H5: PEI
A6: ISSUE TO : | E6: =+'[1]INVOICE 11'!C7 -> SUPREME INTERNATIONAL, LLC | H6: STYLE:
H7: LABEL
H8: P.O.:
H9: PCS
H10: SIZES
A12: PAYMENT: T/C | H12: MADE IN
A13: PO NO: | B13: DV6 | H13: C# UP
A14: CUSTOMER PO.: | E14: =+B13 -> DV6
A15: INVOICE NO: | D15: =+'INVOICE 94'!M2 -> 7726477
A16: Detail Breakdown
A18: CASE FROM-TO | D18: REMARKS | E18: Style | F18: Color Name | G18: Color code | H18: Units/case | I18: xs | J18: S | K18: M | L18: L | M18: 4 | N18: 5 | O18: 6 | P18: 6X | Q18: TOT CTNS | R18: TOT PCS | S18: NW | T18: GW | U18: TTL NW | V18: TTL GW | W18: CARTON SIZE ( CM)
A19: 1 | C19: 5 | E19: NESSB711 | F19: 001 BLACK | G19: 001 | H19: 36 | J19: 36 | Q19: 5 | R19: 180 | S19: =+U19/Q19 -> 3.32 | T19: =+V19/Q19 -> 4.32 | U19: 16.6 | V19: 21.6 | W19: =AA19&"*"&AB19&"*"&AC19 -> 50.8*43.18*11.43 | X19: 20 | Y19: 17 | Z19: 4.5 | AA19: =+X19*2.54 -> 50.8 | AB19: =+Y19*2.54 -> 43.18 | AC19: =+Z19*2.54 -> 11.43
A20: 6 | C20: 13 | H20: 36 | K20: 36 | Q20: 8 | R20: 288 | S20: =+U20/Q20 -> 3.64 | T20: =+V20/Q20 -> 4.64 | U20: 29.12 | V20: 37.12 | W20: =AA20&"*"&AB20&"*"&AC20 -> 50.8*43.18*11.43 | X20: 20 | Y20: 17 | Z20: 4.5 | AA20: =+X20*2.54 -> 50.8 | AB20: =+Y20*2.54 -> 43.18 | AC20: =+Z20*2.54 -> 11.43
A21: 14 | C21: 21 | H21: 36 | L21: 36 | Q21: 8 | R21: 288 | S21: =+U21/Q21 -> 3.93 | T21: =+V21/Q21 -> 4.96 | U21: 31.44 | V21: 39.68 | W21: =AA21&"*"&AB21&"*"&AC21 -> 50.8*43.18*12.7 | X21: 20 | Y21: 17 | Z21: 5 | AA21: =+X21*2.54 -> 50.8 | AB21: =+Y21*2.54 -> 43.18 | AC21: =+Z21*2.54 -> 12.7
A22: 22 | C22: 26 | H22: 36 | M22: 36 | Q22: 5 | R22: 180 | S22: =+U22/Q22 -> 4.25 | T22: =+V22/Q22 -> 5.28 | U22: 21.25 | V22: 26.4 | W22: =AA22&"*"&AB22&"*"&AC22 -> 50.8*43.18*12.7 | X22: 20 | Y22: 17 | Z22: 5 | AA22: =+X22*2.54 -> 50.8 | AB22: =+Y22*2.54 -> 43.18 | AC22: =+Z22*2.54 -> 12.7
A23: 27 | C23: 27 | D23: ODD CARTON | H23: 18 | J23: 18 | Q23: 1 | R23: 18 | S23: =+U23/Q23 -> 1.66 | T23: =+V23/Q23 -> 2.23 | U23: 1.66 | V23: 2.23 | W23: =AA23&"*"&AB23&"*"&AC23 -> 50.8*43.18*7.62 | X23: 20 | Y23: 17 | Z23: 3 | AA23: =+X23*2.54 -> 50.8 | AB23: =+Y23*2.54 -> 43.18 | AC23: =+Z23*2.54 -> 7.62
A24: 28 | C24: 28 | D24: ODD CARTON | H24: 9 | K24: 9 | Q24: 1 | R24: 9 | S24: =+U24/Q24 -> 0.91 | T24: =+V24/Q24 -> 1.66 | U24: 0.91 | V24: 1.66 | W24: =AA24&"*"&AB24&"*"&AC24 -> 44.45*25.4*7.62 | X24: 17.5 | Y24: 10 | Z24: 3 | AA24: =+X24*2.54 -> 44.45 | AB24: =+Y24*2.54 -> 25.4 | AC24: =+Z24*2.54 -> 7.62
A25: 29 | C25: 29 | D25: ODD CARTON | H25: 9 | L25: 9 | Q25: 1 | R25: 9 | S25: =+U25/Q25 -> 0.98 | T25: =+V25/Q25 -> 1.72 | U25: 0.98 | V25: 1.72 | W25: =AA25&"*"&AB25&"*"&AC25 -> 44.45*25.4*7.62 | X25: 17.5 | Y25: 10 | Z25: 3 | AA25: =+X25*2.54 -> 44.45 | AB25: =+Y25*2.54 -> 25.4 | AC25: =+Z25*2.54 -> 7.62
A26: 30 | C26: 30 | D26: ODD CARTON | H26: 18 | M26: 18 | Q26: 1 | R26: 18 | S26: =+U26/Q26 -> 2.12 | T26: =+V26/Q26 -> 3.04 | U26: 2.12 | V26: 3.04 | W26: =AA26&"*"&AB26&"*"&AC26 -> 50.8*43.18*7.62 | X26: 20 | Y26: 17 | Z26: 3 | AA26: =+X26*2.54 -> 50.8 | AB26: =+Y26*2.54 -> 43.18 | AC26: =+Z26*2.54 -> 7.62
M27: 198 | AA27: =+X27*2.54 -> 0 | AB27: =+Y27*2.54 -> 0 | AC27: =+Z27*2.54 -> 0
A28: 31 | C28: 32 | E28: NESSB711 | F28: 655 DESERT PINK | G28: 655 | H28: 36 | J28: 36 | Q28: 2 | R28: 72 | S28: =+U28/Q28 -> 3.32 | T28: =+V28/Q28 -> 4.32 | U28: 6.64 | V28: 8.64 | W28: =AA28&"*"&AB28&"*"&AC28 -> 50.8*43.18*11.43 | X28: 20 | Y28: 17 | Z28: 4.5 | AA28: =+X28*2.54 -> 50.8 | AB28: =+Y28*2.54 -> 43.18 | AC28: =+Z28*2.54 -> 11.43
A29: 33 | C29: 36 | H29: 36 | K29: 36 | Q29: 4 | R29: 144 | S29: =+U29/Q29 -> 3.64 | T29: =+V29/Q29 -> 4.64 | U29: 14.56 | V29: 18.56 | W29: =AA29&"*"&AB29&"*"&AC29 -> 50.8*43.18*11.43 | X29: 20 | Y29: 17 | Z29: 4.5 | AA29: =+X29*2.54 -> 50.8 | AB29: =+Y29*2.54 -> 43.18 | AC29: =+Z29*2.54 -> 11.43
A30: 37 | C30: 40 | H30: 36 | L30: 36 | Q30: 4 | R30: 144 | S30: =+U30/Q30 -> 3.93 | T30: =+V30/Q30 -> 4.96 | U30: 15.72 | V30: 19.84 | W30: =AA30&"*"&AB30&"*"&AC30 -> 50.8*43.18*12.7 | X30: 20 | Y30: 17 | Z30: 5 | AA30: =+X30*2.54 -> 50.8 | AB30: =+Y30*2.54 -> 43.18 | AC30: =+Z30*2.54 -> 12.7
A31: 41 | C31: 42 | H31: 36 | M31: 36 | Q31: 2 | R31: 72 | S31: =+U31/Q31 -> 4.25 | T31: =+V31/Q31 -> 5.28 | U31: 8.5 | V31: 10.56 | W31: =AA31&"*"&AB31&"*"&AC31 -> 50.8*43.18*12.7 | X31: 20 | Y31: 17 | Z31: 5 | AA31: =+X31*2.54 -> 50.8 | AB31: =+Y31*2.54 -> 43.18 | AC31: =+Z31*2.54 -> 12.7
A32: 43 | C32: 43 | D32: ODD CARTON | H32: 28 | J32: 28 | Q32: 1 | R32: 28 | S32: =+U32/Q32 -> 2.58 | T32: =+V32/Q32 -> 3.55 | U32: 2.58 | V32: 3.55 | W32: =AA32&"*"&AB32&"*"&AC32 -> 50.8*43.18*10.16 | X32: 20 | Y32: 17 | Z32: 4 | AA32: =+X32*2.54 -> 50.8 | AB32: =+Y32*2.54 -> 43.18 | AC32: =+Z32*2.54 -> 10.16
A33: 44 | C33: 44 | D33: ODD CARTON | H33: 28 | M33: 28 | Q33: 1 | R33: 28 | S33: =+U33/Q33 -> 3.3 | T33: =+V33/Q33 -> 4.12 | U33: 3.3 | V33: 4.12 | W33: =AA33&"*"&AB33&"*"&AC33 -> 50.8*43.18*11.43 | X33: 20 | Y33: 17 | Z33: 4.5 | AA33: =+X33*2.54 -> 50.8 | AB33: =+Y33*2.54 -> 43.18 | AC33: =+Z33*2.54 -> 11.43
A34: Master box 45-46 | D34: Master box | X34: 19 | Y34: 11 | Z34: 4.5 | AA34: =+X34*2.54 -> 48.26 | AB34: =+Y34*2.54 -> 27.94 | AC34: =+Z34*2.54 -> 11.43
A35: 45 | C35: 45 | D35: Small box | H35: 6 | K35: 6 | Q35: 1 | R35: 6 | S35: =+U35/Q35 -> 1.12 | T35: =+V35/Q35 -> 2.04 | U35: 1.12 | V35: 2.04 | W35: =AA35&"*"&AB35&"*"&AC35 -> 25.4*22.86*8.89 | X35: 10 | Y35: 9 | Z35: 3.5 | AA35: =+X35*2.54 -> 25.4 | AB35: =+Y35*2.54 -> 22.86 | AC35: =+Z35*2.54 -> 8.89
A36: 46 | C36: 46 | D36: Small box | H36: 6 | L36: 6 | R36: 6 | W36: =AA36&"*"&AB36&"*"&AC36 -> 25.4*22.86*8.89 | X36: 10 | Y36: 9 | Z36: 3.5 | AA36: =+X36*2.54 -> 25.4 | AB36: =+Y36*2.54 -> 22.86 | AC36: =+Z36*2.54 -> 8.89
M37: 50
M39: =SUM(M19:M38) -> 366 | N39: =SUM(N19:N38) -> 0 | O39: =SUM(O19:O38) -> 0 | P39: =SUM(P19:P38) -> 0 | Q39: =SUM(Q19:Q38) -> 45 | R39: =SUM(R19:R38) -> 1490 | U39: =SUM(U19:U38) -> 156.5 | V39: =SUM(V19:V38) -> 200.76
D42: CUSTOMER PO | E42: Style | F42: Color | G42: Color Code | H42: xs | I42: S | J42: M | K42: L | L42: XL | Q42: TOT CTNS | R42: TOT PCS
D43: DV6 | E43: NESSB711 | F43: BLACK | G43: 001 | I43: 198 | J43: 297 | K43: 297 | L43: 198 | Q43: 30 | R43: 990 | X43: =+SUM(H43:L43) -> 990 | Y43: =+R43-X43 -> 0
D44: DV6 | E44: NESSB711 | F44: DESERT PINK | G44: 655 | I44: 100 | J44: 150 | K44: 150 | L44: 100 | Q44: 15 | R44: 500 | X44: =+SUM(H44:L44) -> 500 | Y44: =+R44-X44 -> 0
K46: TOTAL | Q46: =SUM(Q43:Q44) -> 45 | R46: =SUM(R43:R44) -> 1490

Sheet IRREGULAR SS PL DV6
A4: PACKING LIST
H5: PEI
A6: ISSUE TO : | E6: =+'[1]INVOICE 11'!C7 -> SUPREME INTERNATIONAL, LLC | H6: STYLE:
H7: LABEL
H8: P.O.:
H9: PCS
H10: SIZES
A12: PAYMENT: T/C | H12: MADE IN
A13: PO NO: | B13: DV6 | H13: C# UP
A14: CUSTOMER PO.: | E14: =+B13 -> DV6
A15: INVOICE NO: | D15: =+'INVOICE 94'!M2 -> 7726477
A16: Detail Breakdown
A18: CASE FROM-TO | D18: REMARKS | E18: Style | F18: Color Name | G18: Color code | H18: Units/case | I18: xs | J18: S | K18: M | L18: L | M18: 4 | N18: 5 | O18: 6 | P18: 6X | Q18: TOT CTNS | R18: TOT PCS | S18: NW | T18: GW | U18: TTL NW | V18: TTL GW | W18: CARTON SIZE ( CM)
A19: 1 | C19: 5 | E19: NESSB711 | F19: 001 BLACK | G19: 001 | H19: 36 | J19: 36 | Q19: 5 | R19: 180 | S19: =+U19/Q19 -> 3.32 | T19: =+V19/Q19 -> 4.32 | U19: 16.6 | V19: 21.6 | W19: =AA19&"*"&AB19&"*"&AC19 -> 50.8*43.18*11.43 | X19: 20 | Y19: 17 | Z19: 4.5 | AA19: =+X19*2.54 -> 50.8 | AB19: =+Y19*2.54 -> 43.18 | AC19: =+Z19*2.54 -> 11.43
A20: 6 | C20: 13 | H20: 36 | K20: 36 | Q20: 8 | R20: 288 | S20: =+U20/Q20 -> 3.64 | T20: =+V20/Q20 -> 4.64 | U20: 29.12 | V20: 37.12 | W20: =AA20&"*"&AB20&"*"&AC20 -> 50.8*43.18*11.43 | X20: 20 | Y20: 17 | Z20: 4.5 | AA20: =+X20*2.54 -> 50.8 | AB20: =+Y20*2.54 -> 43.18 | AC20: =+Z20*2.54 -> 11.43
A21: 14 | C21: 21 | H21: 36 | L21: 36 | Q21: 8 | R21: 288 | S21: =+U21/Q21 -> 3.93 | T21: =+V21/Q21 -> 4.96 | U21: 31.44 | V21: 39.68 | W21: =AA21&"*"&AB21&"*"&AC21 -> 50.8*43.18*12.7 | X21: 20 | Y21: 17 | Z21: 5 | AA21: =+X21*2.54 -> 50.8 | AB21: =+Y21*2.54 -> 43.18 | AC21: =+Z21*2.54 -> 12.7
A22: 22 | C22: 26 | H22: 36 | M22: 36 | Q22: 5 | R22: 180 | S22: =+U22/Q22 -> 4.25 | T22: =+V22/Q22 -> 5.28 | U22: 21.25 | V22: 26.4 | W22: =AA22&"*"&AB22&"*"&AC22 -> 50.8*43.18*12.7 | X22: 20 | Y22: 17 | Z22: 5 | AA22: =+X22*2.54 -> 50.8 | AB22: =+Y22*2.54 -> 43.18 | AC22: =+Z22*2.54 -> 12.7
A23: 27 | C23: 27 | D23: ODD CARTON | H23: 18 | J23: 18 | Q23: 1 | R23: 18 | S23: =+U23/Q23 -> 1.66 | T23: =+V23/Q23 -> 2.23 | U23: 1.66 | V23: 2.23 | W23: =AA23&"*"&AB23&"*"&AC23 -> 50.8*43.18*7.62 | X23: 20 | Y23: 17 | Z23: 3 | AA23: =+X23*2.54 -> 50.8 | AB23: =+Y23*2.54 -> 43.18 | AC23: =+Z23*2.54 -> 7.62
A24: 28 | C24: 28 | D24: ODD CARTON | H24: 9 | K24: 9 | Q24: 1 | R24: 9 | S24: =+U24/Q24 -> 0.91 | T24: =+V24/Q24 -> 1.66 | U24: 0.91 | V24: 1.66 | W24: =AA24&"*"&AB24&"*"&AC24 -> 44.45*25.4*7.62 | X24: 17.5 | Y24: 10 | Z24: 3 | AA24: =+X24*2.54 -> 44.45 | AB24: =+Y24*2.54 -> 25.4 | AC24: =+Z24*2.54 -> 7.62
A25: 29 | C25: 29 | D25: ODD CARTON | H25: 9 | L25: 9 | Q25: 1 | R25: 9 | S25: =+U25/Q25 -> 0.98 | T25: =+V25/Q25 -> 1.72 | U25: 0.98 | V25: 1.72 | W25: =AA25&"*"&AB25&"*"&AC25 -> 44.45*25.4*7.62 | X25: 17.5 | Y25: 10 | Z25: 3 | AA25: =+X25*2.54 -> 44.45 | AB25: =+Y25*2.54 -> 25.4 | AC25: =+Z25*2.54 -> 7.62
A26: 30 | C26: 30 | D26: ODD CARTON | H26: 18 | M26: 18 | Q26: 1 | R26: 18 | S26: =+U26/Q26 -> 2.12 | T26: =+V26/Q26 -> 3.04 | U26: 2.12 | V26: 3.04 | W26: =AA26&"*"&AB26&"*"&AC26 -> 50.8*43.18*7.62 | X26: 20 | Y26: 17 | Z26: 3 | AA26: =+X26*2.54 -> 50.8 | AB26: =+Y26*2.54 -> 43.18 | AC26: =+Z26*2.54 -> 7.62
M27: 198 | AA27: =+X27*2.54 -> 0 | AB27: =+Y27*2.54 -> 0 | AC27: =+Z27*2.54 -> 0
A28: 31 | C28: 32 | E28: NESSB711 | F28: 655 DESERT PINK | G28: 655 | H28: 36 | J28: 36 | Q28: 2 | R28: 72 | S28: =+U28/Q28 -> 3.32 | T28: =+V28/Q28 -> 4.32 | U28: 6.64 | V28: 8.64 | W28: =AA28&"*"&AB28&"*"&AC28 -> 50.8*43.18*11.43 | X28: 20 | Y28: 17 | Z28: 4.5 | AA28: =+X28*2.54 -> 50.8 | AB28: =+Y28*2.54 -> 43.18 | AC28: =+Z28*2.54 -> 11.43
A29: 33 | C29: 36 | H29: 36 | K29: 36 | Q29: 4 | R29: 144 | S29: =+U29/Q29 -> 3.64 | T29: =+V29/Q29 -> 4.64 | U29: 14.56 | V29: 18.56 | W29: =AA29&"*"&AB29&"*"&AC29 -> 50.8*43.18*11.43 | X29: 20 | Y29: 17 | Z29: 4.5 | AA29: =+X29*2.54 -> 50.8 | AB29: =+Y29*2.54 -> 43.18 | AC29: =+Z29*2.54 -> 11.43
A30: 37 | C30: 40 | H30: 36 | L30: 36 | Q30: 4 | R30: 144 | S30: =+U30/Q30 -> 3.93 | T30: =+V30/Q30 -> 4.96 | U30: 15.72 | V30: 19.84 | W30: =AA30&"*"&AB30&"*"&AC30 -> 50.8*43.18*12.7 | X30: 20 | Y30: 17 | Z30: 5 | AA30: =+X30*2.54 -> 50.8 | AB30: =+Y30*2.54 -> 43.18 | AC30: =+Z30*2.54 -> 12.7
A31: 41 | C31: 42 | H31: 36 | M31: 36 | Q31: 2 | R31: 72 | S31: =+U31/Q31 -> 4.25 | T31: =+V31/Q31 -> 5.28 | U31: 8.5 | V31: 10.56 | W31: =AA31&"*"&AB31&"*"&AC31 -> 50.8*43.18*12.7 | X31: 20 | Y31: 17 | Z31: 5 | AA31: =+X31*2.54 -> 50.8 | AB31: =+Y31*2.54 -> 43.18 | AC31: =+Z31*2.54 -> 12.7
A32: 43 | C32: 43 | D32: ODD CARTON | H32: 28 | J32: 28 | Q32: 1 | R32: 28 | S32: =+U32/Q32 -> 2.58 | T32: =+V32/Q32 -> 3.55 | U32: 2.58 | V32: 3.55 | W32: =AA32&"*"&AB32&"*"&AC32 -> 50.8*43.18*10.16 | X32: 20 | Y32: 17 | Z32: 4 | AA32: =+X32*2.54 -> 50.8 | AB32: =+Y32*2.54 -> 43.18 | AC32: =+Z32*2.54 -> 10.16
A33: 44 | C33: 44 | D33: ODD CARTON | H33: 28 | M33: 28 | Q33: 1 | R33: 28 | S33: =+U33/Q33 -> 3.3 | T33: =+V33/Q33 -> 4.12 | U33: 3.3 | V33: 4.12 | W33: =AA33&"*"&AB33&"*"&AC33 -> 50.8*43.18*11.43 | X33: 20 | Y33: 17 | Z33: 4.5 | AA33: =+X33*2.54 -> 50.8 | AB33: =+Y33*2.54 -> 43.18 | AC33: =+Z33*2.54 -> 11.43
A34: Master box 45-46 | D34: Master box | X34: 19 | Y34: 11 | Z34: 4.5 | AA34: =+X34*2.54 -> 48.26 | AB34: =+Y34*2.54 -> 27.94 | AC34: =+Z34*2.54 -> 11.43
A35: 45 | C35: 45 | D35: Small box | H35: 6 | K35: 6 | Q35: 1 | R35: 6 | S35: =+U35/Q35 -> 1.12 | T35: =+V35/Q35 -> 2.04 | U35: 1.12 | V35: 2.04 | W35: =AA35&"*"&AB35&"*"&AC35 -> 25.4*22.86*8.89 | X35: 10 | Y35: 9 | Z35: 3.5 | AA35: =+X35*2.54 -> 25.4 | AB35: =+Y35*2.54 -> 22.86 | AC35: =+Z35*2.54 -> 8.89
A36: 46 | C36: 46 | D36: Small box | H36: 6 | L36: 6 | Q36: 1 | R36: 6 | W36: =AA36&"*"&AB36&"*"&AC36 -> 25.4*22.86*8.89 | X36: 10 | Y36: 9 | Z36: 3.5 | AA36: =+X36*2.54 -> 25.4 | AB36: =+Y36*2.54 -> 22.86 | AC36: =+Z36*2.54 -> 8.89
M37: 50
M39: =SUM(M19:M38) -> 366 | N39: =SUM(N19:N38) -> 0 | O39: =SUM(O19:O38) -> 0 | P39: =SUM(P19:P38) -> 0 | Q39: =SUM(Q19:Q38) -> 46 | R39: =SUM(R19:R38) -> 1490 | U39: =SUM(U19:U38) -> 156.5 | V39: =SUM(V19:V38) -> 200.76
D42: CUSTOMER PO | E42: Style | F42: Color | G42: Color Code | H42: xs | I42: S | J42: M | K42: L | L42: XL | Q42: TOT CTNS | R42: TOT PCS
D43: DV6 | E43: NESSB711 | F43: BLACK | G43: 001 | I43: 198 | J43: 297 | K43: 297 | L43: 198 | Q43: 30 | R43: 990 | X43: =+SUM(H43:L43) -> 990 | Y43: =+R43-X43 -> 0
D44: DV6 | E44: NESSB711 | F44: DESERT PINK | G44: 655 | I44: 100 | J44: 150 | K44: 150 | L44: 100 | Q44: 16 | R44: 500 | X44: =+SUM(H44:L44) -> 500 | Y44: =+R44-X44 -> 0
K46: TOTAL | Q46: =SUM(Q43:Q44) -> 46 | R46: =SUM(R43:R44) -> 1490

Sheet SOLID PL DV7
A4: PACKING LIST
H5: PEI
A6: ISSUE TO : | E6: =+'[1]INVOICE 11'!C7 -> SUPREME INTERNATIONAL, LLC | H6: STYLE:
H7: LABEL
H8: P.O.:
H9: PCS
H10: SIZES
A12: PAYMENT: T/C | H12: MADE IN
A13: PO NO: | B13: DV7 | H13: C# UP
A14: CUSTOMER PO.: | E14: =+B13 -> DV7
A15: INVOICE NO: | D15: =+'INVOICE 94'!M2 -> 7726477
A16: Detail Breakdown
A18: CASE FROM-TO | D18: REMARKS | E18: Style | F18: Color Name | G18: Color code | H18: Units/case | I18: xs | J18: S | K18: M | L18: L | M18: 4 | N18: 5 | O18: 6 | P18: 6X | Q18: TOT CTNS | R18: TOT PCS | S18: NW | T18: GW | U18: TTL NW | V18: TTL GW | W18: CARTON SIZE ( CM)
A19: 1 | C19: 2 | E19: NESSB711 | F19: 001 BLACK | G19: 001 | H19: 36 | J19: 36 | Q19: 2 | R19: 72 | S19: =+U19/Q19 -> 3.32 | T19: =+V19/Q19 -> 4.32 | U19: 6.64 | V19: 8.64 | W19: =AA19&"*"&AB19&"*"&AC19 -> 50.8*43.18*11.43 | X19: 20 | Y19: 17 | Z19: 4.5 | AA19: =+X19*2.54 -> 50.8 | AB19: =+Y19*2.54 -> 43.18 | AC19: =+Z19*2.54 -> 11.43
A20: 3 | C20: 6 | H20: 36 | K20: 36 | Q20: 4 | R20: 144 | S20: =+U20/Q20 -> 3.64 | T20: =+V20/Q20 -> 4.64 | U20: 14.56 | V20: 18.56 | W20: =AA20&"*"&AB20&"*"&AC20 -> 50.8*43.18*11.43 | X20: 20 | Y20: 17 | Z20: 4.5 | AA20: =+X20*2.54 -> 50.8 | AB20: =+Y20*2.54 -> 43.18 | AC20: =+Z20*2.54 -> 11.43
A21: 7 | C21: 10 | H21: 36 | L21: 36 | Q21: 4 | R21: 144 | S21: =+U21/Q21 -> 3.93 | T21: =+V21/Q21 -> 4.96 | U21: 15.72 | V21: 19.84 | W21: =AA21&"*"&AB21&"*"&AC21 -> 50.8*43.18*12.7 | X21: 20 | Y21: 17 | Z21: 5 | AA21: =+X21*2.54 -> 50.8 | AB21: =+Y21*2.54 -> 43.18 | AC21: =+Z21*2.54 -> 12.7
A22: 11 | C22: 12 | H22: 36 | M22: 36 | Q22: 2 | R22: 72 | S22: =+U22/Q22 -> 4.25 | T22: =+V22/Q22 -> 5.28 | U22: 8.5 | V22: 10.56 | W22: =AA22&"*"&AB22&"*"&AC22 -> 50.8*43.18*12.7 | X22: 20 | Y22: 17 | Z22: 5 | AA22: =+X22*2.54 -> 50.8 | AB22: =+Y22*2.54 -> 43.18 | AC22: =+Z22*2.54 -> 12.7
A23: 13 | C23: 13 | D23: ODD CARTON | H23: 28 | J23: 28 | Q23: 1 | R23: 28 | S23: =+U23/Q23 -> 2.58 | T23: =+V23/Q23 -> 3.48 | U23: 2.58 | V23: 3.48 | W23: =AA23&"*"&AB23&"*"&AC23 -> 50.8*43.18*10.16 | X23: 20 | Y23: 17 | Z23: 4 | AA23: =+X23*2.54 -> 50.8 | AB23: =+Y23*2.54 -> 43.18 | AC23: =+Z23*2.54 -> 10.16
A24: 14 | C24: 14 | D24: ODD CARTON | H24: 28 | M24: 28 | Q24: 1 | R24: 28 | S24: =+U24/Q24 -> 3.3 | T24: =+V24/Q24 -> 4.27 | U24: 3.3 | V24: 4.27 | W24: =AA24&"*"&AB24&"*"&AC24 -> 50.8*43.18*11.43 | X24: 20 | Y24: 17 | Z24: 4.5 | AA24: =+X24*2.54 -> 50.8 | AB24: =+Y24*2.54 -> 43.18 | AC24: =+Z24*2.54 -> 11.43
A25: Master box 15-16 | D25: Master box | W25: =AA25&"*"&AB25&"*"&AC25 -> 48.26*27.94*11.43 | X25: 19 | Y25: 11 | Z25: 4.5 | AA25: =+X25*2.54 -> 48.26 | AB25: =+Y25*2.54 -> 27.94 | AC25: =+Z25*2.54 -> 11.43
A26: 15 | C26: 15 | D26: Small box | H26: 6 | K26: 6 | Q26: 1 | R26: 6 | S26: =+U26/Q26 -> 1.28 | T26: =+V26/Q26 -> 2.14 | U26: 1.28 | V26: 2.14 | W26: =AA26&"*"&AB26&"*"&AC26 -> 25.4*22.86*8.89 | X26: 10 | Y26: 9 | Z26: 3.5 | AA26: =+X26*2.54 -> 25.4 | AB26: =+Y26*2.54 -> 22.86 | AC26: =+Z26*2.54 -> 8.89
A27: 16 | C27: 16 | D27: Small box | H27: 6 | L27: 6 | R27: 6 | W27: =AA27&"*"&AB27&"*"&AC27 -> 25.4*22.86*8.89 | X27: 10 | Y27: 9 | Z27: 3.5 | AA27: =+X27*2.54 -> 25.4 | AB27: =+Y27*2.54 -> 22.86 | AC27: =+Z27*2.54 -> 8.89
M28: 100 | AA28: =+X28*2.54 -> 0 | AB28: =+Y28*2.54 -> 0 | AC28: =+Z28*2.54 -> 0
A29: 17 | C29: 17 | E29: NESSB711 | F29: 655 DESERT PINK | G29: 655 | H29: 36 | J29: 36 | Q29: 1 | R29: 36 | S29: =+U29/Q29 -> 3.32 | T29: =+V29/Q29 -> 4.32 | U29: 3.32 | V29: 4.32 | W29: =AA29&"*"&AB29&"*"&AC29 -> 50.8*43.18*11.43 | X29: 20 | Y29: 17 | Z29: 4.5 | AA29: =+X29*2.54 -> 50.8 | AB29: =+Y29*2.54 -> 43.18 | AC29: =+Z29*2.54 -> 11.43
A30: 18 | C30: 18 | H30: 36 | K30: 36 | Q30: 1 | R30: 36 | S30: =+U30/Q30 -> 3.64 | T30: =+V30/Q30 -> 4.64 | U30: 3.64 | V30: 4.64 | W30: =AA30&"*"&AB30&"*"&AC30 -> 50.8*43.18*11.43 | X30: 20 | Y30: 17 | Z30: 4.5 | AA30: =+X30*2.54 -> 50.8 | AB30: =+Y30*2.54 -> 43.18 | AC30: =+Z30*2.54 -> 11.43
A31: 19 | C31: 19 | H31: 39 | K31: 39 | Q31: 1 | R31: 39 | S31: =+U31/Q31 -> 3.94 | T31: =+V31/Q31 -> 4.96 | U31: 3.94 | V31: 4.96 | W31: =AA31&"*"&AB31&"*"&AC31 -> 50.8*43.18*12.7 | X31: 20 | Y31: 17 | Z31: 5 | AA31: =+X31*2.54 -> 50.8 | AB31: =+Y31*2.54 -> 43.18 | AC31: =+Z31*2.54 -> 12.7
A32: 20 | C32: 20 | H32: 36 | L32: 36 | Q32: 1 | R32: 36 | S32: =+U32/Q32 -> 3.93 | T32: =+V32/Q32 -> 4.96 | U32: 3.93 | V32: 4.96 | W32: =AA32&"*"&AB32&"*"&AC32 -> 50.8*43.18*11.43 | X32: 20 | Y32: 17 | Z32: 4.5 | AA32: =+X32*2.54 -> 50.8 | AB32: =+Y32*2.54 -> 43.18 | AC32: =+Z32*2.54 -> 11.43
A33: 21 | C33: 21 | H33: 39 | L33: 39 | Q33: 1 | R33: 39 | S33: =+U33/Q33 -> 4.26 | T33: =+V33/Q33 -> 5.3 | U33: 4.26 | V33: 5.3 | W33: =AA33&"*"&AB33&"*"&AC33 -> 50.8*43.18*12.7 | X33: 20 | Y33: 17 | Z33: 5 | AA33: =+X33*2.54 -> 50.8 | AB33: =+Y33*2.54 -> 43.18 | AC33: =+Z33*2.54 -> 12.7
A34: 22 | C34: 22 | H34: 36 | M34: 36 | Q34: 1 | R34: 36 | S34: =+U34/Q34 -> 4.25 | T34: =+V34/Q34 -> 5.28 | U34: 4.25 | V34: 5.28 | W34: =AA34&"*"&AB34&"*"&AC34 -> 50.8*43.18*12.7 | X34: 20 | Y34: 17 | Z34: 5 | AA34: =+X34*2.54 -> 50.8 | AB34: =+Y34*2.54 -> 43.18 | AC34: =+Z34*2.54 -> 12.7
A35: 23 | C35: 23 | D35: ODD CARTON | H35: 14 | J35: 14 | Q35: 1 | R35: 14 | S35: =+U35/Q35 -> 1.29 | T35: =+V35/Q35 -> 2.19 | U35: 1.29 | V35: 2.19 | W35: =AA35&"*"&AB35&"*"&AC35 -> 44.45*25.4*7.62 | X35: 17.5 | Y35: 10 | Z35: 3 | AA35: =+X35*2.54 -> 44.45 | AB35: =+Y35*2.54 -> 25.4 | AC35: =+Z35*2.54 -> 7.62
A36: 24 | C36: 24 | D36: ODD CARTON | H36: 14 | M36: 14 | Q36: 1 | R36: 14 | S36: =+U36/Q36 -> 1.65 | T36: =+V36/Q36 -> 2.51 | U36: 1.65 | V36: 2.51 | W36: =AA36&"*"&AB36&"*"&AC36 -> 44.45*25.4*7.62 | X36: 17.5 | Y36: 10 | Z36: 3 | AA36: =+X36*2.54 -> 44.45 | AB36: =+Y36*2.54 -> 25.4 | AC36: =+Z36*2.54 -> 7.62
M37: 50
M39: =SUM(M19:M38) -> 264 | N39: =SUM(N19:N38) -> 0 | O39: =SUM(O19:O38) -> 0 | P39: =SUM(P19:P38) -> 0 | Q39: =SUM(Q19:Q38) -> 23 | R39: =SUM(R19:R38) -> 750 | U39: =SUM(U19:U38) -> 78.86 | V39: =SUM(V19:V38) -> 101.65
D42: CUSTOMER PO | E42: Style | F42: Color | G42: Color Code | H42: xs | I42: S | J42: M | K42: L | L42: XL | Q42: TOT CTNS | R42: TOT PCS
D43: DV7 | E43: NESSB711 | F43: BLACK | G43: 001 | I43: 100 | J43: 150 | K43: 150 | L43: 100 | Q43: 15 | R43: 500 | X43: =+SUM(H43:L43) -> 500 | Y43: =+R43-X43 -> 0
D44: DV7 | E44: NESSB711 | F44: DESERT PINK | G44: 655 | I44: 50 | J44: 75 | K44: 75 | L44: 50 | Q44: 8 | R44: 250 | X44: =+SUM(H44:L44) -> 250 | Y44: =+R44-X44 -> 0
K46: TOTAL | Q46: =SUM(Q43:Q44) -> 23 | R46: =SUM(R43:R44) -> 750

Sheet IRREGULAR SS PLDV7
A4: PACKING LIST
H5: PEI
A6: ISSUE TO : | E6: =+'[1]INVOICE 11'!C7 -> SUPREME INTERNATIONAL, LLC | H6: STYLE:
H7: LABEL
H8: P.O.:
H9: PCS
H10: SIZES
A12: PAYMENT: T/C | H12: MADE IN
A13: PO NO: | B13: DV7 | H13: C# UP
A14: CUSTOMER PO.: | E14: =+B13 -> DV7
A15: INVOICE NO: | D15: =+'INVOICE 94'!M2 -> 7726477
A16: Detail Breakdown
A18: CASE FROM-TO | D18: REMARKS | E18: Style | F18: Color Name | G18: Color code | H18: Units/case | I18: xs | J18: S | K18: M | L18: L | M18: 4 | N18: 5 | O18: 6 | P18: 6X | Q18: TOT CTNS | R18: TOT PCS | S18: NW | T18: GW | U18: TTL NW | V18: TTL GW | W18: CARTON SIZE ( CM)
A19: 1 | C19: 2 | E19: NESSB711 | F19: 001 BLACK | G19: 001 | H19: 36 | J19: 36 | Q19: 2 | R19: 72 | S19: =+U19/Q19 -> 3.32 | T19: =+V19/Q19 -> 4.32 | U19: 6.64 | V19: 8.64 | W19: =AA19&"*"&AB19&"*"&AC19 -> 50.8*43.18*11.43 | X19: 20 | Y19: 17 | Z19: 4.5 | AA19: =+X19*2.54 -> 50.8 | AB19: =+Y19*2.54 -> 43.18 | AC19: =+Z19*2.54 -> 11.43
A20: 3 | C20: 6 | H20: 36 | K20: 36 | Q20: 4 | R20: 144 | S20: =+U20/Q20 -> 3.64 | T20: =+V20/Q20 -> 4.64 | U20: 14.56 | V20: 18.56 | W20: =AA20&"*"&AB20&"*"&AC20 -> 50.8*43.18*11.43 | X20: 20 | Y20: 17 | Z20: 4.5 | AA20: =+X20*2.54 -> 50.8 | AB20: =+Y20*2.54 -> 43.18 | AC20: =+Z20*2.54 -> 11.43
A21: 7 | C21: 10 | H21: 36 | L21: 36 | Q21: 4 | R21: 144 | S21: =+U21/Q21 -> 3.93 | T21: =+V21/Q21 -> 4.96 | U21: 15.72 | V21: 19.84 | W21: =AA21&"*"&AB21&"*"&AC21 -> 50.8*43.18*12.7 | X21: 20 | Y21: 17 | Z21: 5 | AA21: =+X21*2.54 -> 50.8 | AB21: =+Y21*2.54 -> 43.18 | AC21: =+Z21*2.54 -> 12.7
A22: 11 | C22: 12 | H22: 36 | M22: 36 | Q22: 2 | R22: 72 | S22: =+U22/Q22 -> 4.25 | T22: =+V22/Q22 -> 5.28 | U22: 8.5 | V22: 10.56 | W22: =AA22&"*"&AB22&"*"&AC22 -> 50.8*43.18*12.7 | X22: 20 | Y22: 17 | Z22: 5 | AA22: =+X22*2.54 -> 50.8 | AB22: =+Y22*2.54 -> 43.18 | AC22: =+Z22*2.54 -> 12.7
A23: 13 | C23: 13 | D23: ODD CARTON | H23: 28 | J23: 28 | Q23: 1 | R23: 28 | S23: =+U23/Q23 -> 2.58 | T23: =+V23/Q23 -> 3.48 | U23: 2.58 | V23: 3.48 | W23: =AA23&"*"&AB23&"*"&AC23 -> 50.8*43.18*10.16 | X23: 20 | Y23: 17 | Z23: 4 | AA23: =+X23*2.54 -> 50.8 | AB23: =+Y23*2.54 -> 43.18 | AC23: =+Z23*2.54 -> 10.16
A24: 14 | C24: 14 | D24: ODD CARTON | H24: 28 | M24: 28 | Q24: 1 | R24: 28 | S24: =+U24/Q24 -> 3.3 | T24: =+V24/Q24 -> 4.27 | U24: 3.3 | V24: 4.27 | W24: =AA24&"*"&AB24&"*"&AC24 -> 50.8*43.18*11.43 | X24: 20 | Y24: 17 | Z24: 4.5 | AA24: =+X24*2.54 -> 50.8 | AB24: =+Y24*2.54 -> 43.18 | AC24: =+Z24*2.54 -> 11.43
A25: Master box 15-16 | D25: Master box | W25: =AA25&"*"&AB25&"*"&AC25 -> 48.26*27.94*11.43 | X25: 19 | Y25: 11 | Z25: 4.5 | AA25: =+X25*2.54 -> 48.26 | AB25: =+Y25*2.54 -> 27.94 | AC25: =+Z25*2.54 -> 11.43
A26: 15 | C26: 15 | D26: Small box | H26: 6 | K26: 6 | Q26: 1 | R26: 6 | S26: =+U26/Q26 -> 1.28 | T26: =+V26/Q26 -> 2.14 | U26: 1.28 | V26: 2.14 | W26: =AA26&"*"&AB26&"*"&AC26 -> 25.4*22.86*8.89 | X26: 10 | Y26: 9 | Z26: 3.5 | AA26: =+X26*2.54 -> 25.4 | AB26: =+Y26*2.54 -> 22.86 | AC26: =+Z26*2.54 -> 8.89
A27: 16 | C27: 16 | D27: Small box | H27: 6 | L27: 6 | Q27: 1 | R27: 6 | W27: =AA27&"*"&AB27&"*"&AC27 -> 25.4*22.86*8.89 | X27: 10 | Y27: 9 | Z27: 3.5 | AA27: =+X27*2.54 -> 25.4 | AB27: =+Y27*2.54 -> 22.86 | AC27: =+Z27*2.54 -> 8.89
M28: 100 | AA28: =+X28*2.54 -> 0 | AB28: =+Y28*2.54 -> 0 | AC28: =+Z28*2.54 -> 0
A29: 17 | C29: 17 | E29: NESSB711 | F29: 655 DESERT PINK | G29: 655 | H29: 36 | J29: 36 | Q29: 1 | R29: 36 | S29: =+U29/Q29 -> 3.32 | T29: =+V29/Q29 -> 4.32 | U29: 3.32 | V29: 4.32 | W29: =AA29&"*"&AB29&"*"&AC29 -> 50.8*43.18*11.43 | X29: 20 | Y29: 17 | Z29: 4.5 | AA29: =+X29*2.54 -> 50.8 | AB29: =+Y29*2.54 -> 43.18 | AC29: =+Z29*2.54 -> 11.43
A30: 18 | C30: 18 | H30: 36 | K30: 36 | Q30: 1 | R30: 36 | S30: =+U30/Q30 -> 3.64 | T30: =+V30/Q30 -> 4.64 | U30: 3.64 | V30: 4.64 | W30: =AA30&"*"&AB30&"*"&AC30 -> 50.8*43.18*11.43 | X30: 20 | Y30: 17 | Z30: 4.5 | AA30: =+X30*2.54 -> 50.8 | AB30: =+Y30*2.54 -> 43.18 | AC30: =+Z30*2.54 -> 11.43
A31: 19 | C31: 19 | H31: 39 | K31: 39 | Q31: 1 | R31: 39 | S31: =+U31/Q31 -> 3.94 | T31: =+V31/Q31 -> 4.96 | U31: 3.94 | V31: 4.96 | W31: =AA31&"*"&AB31&"*"&AC31 -> 50.8*43.18*12.7 | X31: 20 | Y31: 17 | Z31: 5 | AA31: =+X31*2.54 -> 50.8 | AB31: =+Y31*2.54 -> 43.18 | AC31: =+Z31*2.54 -> 12.7
A32: 20 | C32: 20 | H32: 36 | L32: 36 | Q32: 1 | R32: 36 | S32: =+U32/Q32 -> 3.93 | T32: =+V32/Q32 -> 4.96 | U32: 3.93 | V32: 4.96 | W32: =AA32&"*"&AB32&"*"&AC32 -> 50.8*43.18*11.43 | X32: 20 | Y32: 17 | Z32: 4.5 | AA32: =+X32*2.54 -> 50.8 | AB32: =+Y32*2.54 -> 43.18 | AC32: =+Z32*2.54 -> 11.43
A33: 21 | C33: 21 | H33: 39 | L33: 39 | Q33: 1 | R33: 39 | S33: =+U33/Q33 -> 4.26 | T33: =+V33/Q33 -> 5.3 | U33: 4.26 | V33: 5.3 | W33: =AA33&"*"&AB33&"*"&AC33 -> 50.8*43.18*12.7 | X33: 20 | Y33: 17 | Z33: 5 | AA33: =+X33*2.54 -> 50.8 | AB33: =+Y33*2.54 -> 43.18 | AC33: =+Z33*2.54 -> 12.7
A34: 22 | C34: 22 | H34: 36 | M34: 36 | Q34: 1 | R34: 36 | S34: =+U34/Q34 -> 4.25 | T34: =+V34/Q34 -> 5.28 | U34: 4.25 | V34: 5.28 | W34: =AA34&"*"&AB34&"*"&AC34 -> 50.8*43.18*12.7 | X34: 20 | Y34: 17 | Z34: 5 | AA34: =+X34*2.54 -> 50.8 | AB34: =+Y34*2.54 -> 43.18 | AC34: =+Z34*2.54 -> 12.7
A35: 23 | C35: 23 | D35: ODD CARTON | H35: 14 | J35: 14 | Q35: 1 | R35: 14 | S35: =+U35/Q35 -> 1.29 | T35: =+V35/Q35 -> 2.19 | U35: 1.29 | V35: 2.19 | W35: =AA35&"*"&AB35&"*"&AC35 -> 44.45*25.4*7.62 | X35: 17.5 | Y35: 10 | Z35: 3 | AA35: =+X35*2.54 -> 44.45 | AB35: =+Y35*2.54 -> 25.4 | AC35: =+Z35*2.54 -> 7.62
A36: 24 | C36: 24 | D36: ODD CARTON | H36: 14 | M36: 14 | Q36: 1 | R36: 14 | S36: =+U36/Q36 -> 1.65 | T36: =+V36/Q36 -> 2.51 | U36: 1.65 | V36: 2.51 | W36: =AA36&"*"&AB36&"*"&AC36 -> 44.45*25.4*7.62 | X36: 17.5 | Y36: 10 | Z36: 3 | AA36: =+X36*2.54 -> 44.45 | AB36: =+Y36*2.54 -> 25.4 | AC36: =+Z36*2.54 -> 7.62
M37: 50
M39: =SUM(M19:M38) -> 264 | N39: =SUM(N19:N38) -> 0 | O39: =SUM(O19:O38) -> 0 | P39: =SUM(P19:P38) -> 0 | Q39: =SUM(Q19:Q38) -> 24 | R39: =SUM(R19:R38) -> 750 | U39: =SUM(U19:U38) -> 78.86 | V39: =SUM(V19:V38) -> 101.65
D42: CUSTOMER PO | E42: Style | F42: Color | G42: Color Code | H42: xs | I42: S | J42: M | K42: L | L42: XL | Q42: TOT CTNS | R42: TOT PCS
D43: DV7 | E43: NESSB711 | F43: BLACK | G43: 001 | I43: 100 | J43: 150 | K43: 150 | L43: 100 | Q43: 16 | R43: 500 | X43: =+SUM(H43:L43) -> 500 | Y43: =+R43-X43 -> 0
D44: DV7 | E44: NESSB711 | F44: DESERT PINK | G44: 655 | I44: 50 | J44: 75 | K44: 75 | L44: 50 | Q44: 8 | R44: 250 | X44: =+SUM(H44:L44) -> 250 | Y44: =+R44-X44 -> 0
K46: TOTAL | Q46: =SUM(Q43:Q44) -> 24 | R46: =SUM(R43:R44) -> 750

Sheet SOLID PL EQ349
A4: PACKING LIST
H5: PEI
A6: ISSUE TO : | E6: =+'[1]INVOICE 11'!C7 -> SUPREME INTERNATIONAL, LLC | H6: STYLE:
H7: LABEL
H8: P.O.:
H9: PCS
H10: SIZES
A12: PAYMENT: T/C | H12: MADE IN
A13: PO NO: | B13: EQ349 | H13: C# UP
A14: CUSTOMER PO.: | E14: =+B13 -> EQ349
A15: INVOICE NO: | D15: =+'INVOICE 94'!M2 -> 7726477
A16: Detail Breakdown
A18: CASE FROM-TO | D18: REMARKS | E18: Style | F18: Color Name | G18: Color code | H18: Units/case | I18: xs | J18: S | K18: M | L18: L | M18: 4 | N18: 5 | O18: 6 | P18: 6X | Q18: TOT CTNS | R18: TOT PCS | S18: NW | T18: GW | U18: TTL NW | V18: TTL GW | W18: CARTON SIZE ( CM)
A19: 1 | C19: 1 | E19: NESSB711 | F19: 385 ENERGY | G19: 385 | H19: 16 | J19: 16 | Q19: 1 | R19: 16 | S19: =+U19/Q19 -> 1.61 | T19: =+V19/Q19 -> 2.54 | U19: 1.61 | V19: 2.54 | W19: =AA19&"*"&AB19&"*"&AC19 -> 50.8*43.18*7.62 | X19: 20 | Y19: 17 | Z19: 3 | AA19: =+X19*2.54 -> 50.8 | AB19: =+Y19*2.54 -> 43.18 | AC19: =+Z19*2.54 -> 7.62
A20: 2 | C20: 2 | H20: 16 | K20: 16 | Q20: 1 | R20: 16 | S20: =+U20/Q20 -> 1.74 | T20: =+V20/Q20 -> 2.63 | U20: 1.74 | V20: 2.63 | W20: =AA20&"*"&AB20&"*"&AC20 -> 50.8*43.18*7.62 | X20: 20 | Y20: 17 | Z20: 3 | AA20: =+X20*2.54 -> 50.8 | AB20: =+Y20*2.54 -> 43.18 | AC20: =+Z20*2.54 -> 7.62
A21: Master box 3-4 | D21: Master box | W21: =AA21&"*"&AB21&"*"&AC21 -> 48.26*27.94*11.43 | X21: 19 | Y21: 11 | Z21: 4.5 | AA21: =+X21*2.54 -> 48.26 | AB21: =+Y21*2.54 -> 27.94 | AC21: =+Z21*2.54 -> 11.43
A22: 3 | C22: 3 | D22: Small box | H22: 8 | I22: 8 | M22: 36 | Q22: 1 | R22: 8 | S22: =+U22/Q22 -> 1.14 | T22: =+V22/Q22 -> 2.09 | U22: 1.14 | V22: 2.09 | W22: =AA22&"*"&AB22&"*"&AC22 -> 25.4*22.86*8.89 | X22: 10 | Y22: 9 | Z22: 3.5 | AA22: =+X22*2.54 -> 25.4 | AB22: =+Y22*2.54 -> 22.86 | AC22: =+Z22*2.54 -> 8.89
A23: 4 | C23: 4 | D23: Small box | H23: 8 | L23: 8 | R23: 8 | W23: =AA23&"*"&AB23&"*"&AC23 -> 25.4*22.86*8.89 | X23: 10 | Y23: 9 | Z23: 3.5 | AA23: =+X23*2.54 -> 25.4 | AB23: =+Y23*2.54 -> 22.86 | AC23: =+Z23*2.54 -> 8.89
M24: 50
M26: =SUM(M19:M25) -> 86 | N26: =SUM(N19:N25) -> 0 | O26: =SUM(O19:O25) -> 0 | P26: =SUM(P19:P25) -> 0 | Q26: =SUM(Q19:Q25) -> 3 | R26: =SUM(R19:R25) -> 48 | U26: =SUM(U19:U25) -> 4.49 | V26: =SUM(V19:V25) -> 7.26
D29: CUSTOMER PO | E29: Style | F29: Color | G29: Color Code | H29: xs | I29: S | J29: M | K29: L | L29: XL | Q29: TOT CTNS | R29: TOT PCS
D30: EQ349 | E30: NESSB711 | F30: ENERGY | G30: 385 | H30: 8 | I30: 16 | J30: 16 | K30: 8 | Q30: 3 | R30: 48 | X30: =+SUM(H30:L30) -> 48 | Y30: =+R30-X30 -> 0
K33: TOTAL | Q33: =SUM(Q30:Q31) -> 3 | R33: =SUM(R30:R31) -> 48

Sheet IRREGULAR SS PL EQ349
A4: PACKING LIST
H5: PEI
A6: ISSUE TO : | E6: =+'[1]INVOICE 11'!C7 -> SUPREME INTERNATIONAL, LLC | H6: STYLE:
H7: LABEL
H8: P.O.:
H9: PCS
H10: SIZES
A12: PAYMENT: T/C | H12: MADE IN
A13: PO NO: | B13: EQ349 | H13: C# UP
A14: CUSTOMER PO.: | E14: =+B13 -> EQ349
A15: INVOICE NO: | D15: =+'INVOICE 94'!M2 -> 7726477
A16: Detail Breakdown
A18: CASE FROM-TO | D18: REMARKS | E18: Style | F18: Color Name | G18: Color code | H18: Units/case | I18: xs | J18: S | K18: M | L18: L | M18: 4 | N18: 5 | O18: 6 | P18: 6X | Q18: TOT CTNS | R18: TOT PCS | S18: NW | T18: GW | U18: TTL NW | V18: TTL GW | W18: CARTON SIZE ( CM)
A19: 1 | C19: 1 | E19: NESSB711 | F19: 385 ENERGY | G19: 385 | H19: 16 | J19: 16 | Q19: 1 | R19: 16 | S19: =+U19/Q19 -> 1.61 | T19: =+V19/Q19 -> 2.54 | U19: 1.61 | V19: 2.54 | W19: =AA19&"*"&AB19&"*"&AC19 -> 50.8*43.18*7.62 | X19: 20 | Y19: 17 | Z19: 3 | AA19: =+X19*2.54 -> 50.8 | AB19: =+Y19*2.54 -> 43.18 | AC19: =+Z19*2.54 -> 7.62
A20: 2 | C20: 2 | H20: 16 | K20: 16 | Q20: 1 | R20: 16 | S20: =+U20/Q20 -> 1.74 | T20: =+V20/Q20 -> 2.63 | U20: 1.74 | V20: 2.63 | W20: =AA20&"*"&AB20&"*"&AC20 -> 50.8*43.18*7.62 | X20: 20 | Y20: 17 | Z20: 3 | AA20: =+X20*2.54 -> 50.8 | AB20: =+Y20*2.54 -> 43.18 | AC20: =+Z20*2.54 -> 7.62
A21: Master box 3-4 | D21: Master box | W21: =AA21&"*"&AB21&"*"&AC21 -> 48.26*27.94*11.43 | X21: 19 | Y21: 11 | Z21: 4.5 | AA21: =+X21*2.54 -> 48.26 | AB21: =+Y21*2.54 -> 27.94 | AC21: =+Z21*2.54 -> 11.43
A22: 3 | C22: 3 | D22: Small box | H22: 8 | I22: 8 | M22: 36 | Q22: 1 | R22: 8 | S22: =+U22/Q22 -> 1.14 | T22: =+V22/Q22 -> 2.09 | U22: 1.14 | V22: 2.09 | W22: =AA22&"*"&AB22&"*"&AC22 -> 25.4*22.86*8.89 | X22: 10 | Y22: 9 | Z22: 3.5 | AA22: =+X22*2.54 -> 25.4 | AB22: =+Y22*2.54 -> 22.86 | AC22: =+Z22*2.54 -> 8.89
A23: 4 | C23: 4 | D23: Small box | H23: 8 | L23: 8 | Q23: 1 | R23: 8 | W23: =AA23&"*"&AB23&"*"&AC23 -> 25.4*22.86*8.89 | X23: 10 | Y23: 9 | Z23: 3.5 | AA23: =+X23*2.54 -> 25.4 | AB23: =+Y23*2.54 -> 22.86 | AC23: =+Z23*2.54 -> 8.89
M24: 50
M26: =SUM(M19:M25) -> 86 | N26: =SUM(N19:N25) -> 0 | O26: =SUM(O19:O25) -> 0 | P26: =SUM(P19:P25) -> 0 | Q26: =SUM(Q19:Q25) -> 4 | R26: =SUM(R19:R25) -> 48 | U26: =SUM(U19:U25) -> 4.49 | V26: =SUM(V19:V25) -> 7.26
D29: CUSTOMER PO | E29: Style | F29: Color | G29: Color Code | H29: xs | I29: S | J29: M | K29: L | L29: XL | Q29: TOT CTNS | R29: TOT PCS
D30: EQ349 | E30: NESSB711 | F30: ENERGY | G30: 385 | H30: 8 | I30: 16 | J30: 16 | K30: 8 | Q30: 4 | R30: 48 | X30: =+SUM(H30:L30) -> 48 | Y30: =+R30-X30 -> 0
K33: TOTAL | Q33: =SUM(Q30:Q31) -> 4 | R33: =SUM(R30:R31) -> 48

Sheet SOLID PL EV154
A4: PACKING LIST
G5: PEI
A6: ISSUE TO : | D6: =+'[1]INVOICE 11'!C7 -> SUPREME INTERNATIONAL, LLC | G6: STYLE:
G7: LABEL
G8: P.O.:
G9: PCS
G10: SIZES
A12: PAYMENT: T/C | G12: MADE IN
A13: PO NO: | B13: EV154 | G13: C# UP
A14: CUSTOMER PO.: | D14: =+B13 -> EV154
A15: INVOICE NO: | C15: =+'INVOICE 94'!M2 -> 7726477
A16: Detail Breakdown
A18: CASE FROM-TO | C18: REMARKS | D18: Style | E18: Color Name | F18: Color code | G18: Units/case | H18: xs | I18: S | J18: M | K18: L | L18: 4 | M18: 5 | N18: 6 | O18: 6X | P18: TOT CTNS | Q18: TOT PCS | R18: NW | S18: GW | T18: TTL NW | U18: TTL GW | V18: CARTON SIZE ( CM)
A19: 1 | B19: 1 | D19: NESSB711 | E19: 001 BLACK | F19: 001 | G19: 8 | H19: 8 | P19: 1 | Q19: 8 | R19: =+T19/P19 -> 0.7 | S19: =+U19/P19 -> 1 | T19: 0.7 | U19: 1 | V19: =Z19&"*"&AA19&"*"&AB19 -> 25.4*22.86*8.89 | W19: 10 | X19: 9 | Y19: 3.5 | Z19: =+W19*2.54 -> 25.4 | AA19: =+X19*2.54 -> 22.86 | AB19: =+Y19*2.54 -> 8.89
A20: 2 | B20: 2 | G20: 25 | I20: 25 | P20: 1 | Q20: 25 | R20: =+T20/P20 -> 2.42 | S20: =+U20/P20 -> 3.38 | T20: 2.42 | U20: 3.38 | V20: =Z20&"*"&AA20&"*"&AB20 -> 50.8*43.18*8.89 | W20: 20 | X20: 17 | Y20: 3.5 | Z20: =+W20*2.54 -> 50.8 | AA20: =+X20*2.54 -> 43.18 | AB20: =+Y20*2.54 -> 8.89
A21: 3 | B21: 3 | G21: 32 | J21: 32 | P21: 1 | Q21: 32 | R21: =+T21/P21 -> 3.16 | S21: =+U21/P21 -> 4.14 | T21: 3.16 | U21: 4.14 | V21: =Z21&"*"&AA21&"*"&AB21 -> 50.8*43.18*10.16 | W21: 20 | X21: 17 | Y21: 4 | Z21: =+W21*2.54 -> 50.8 | AA21: =+X21*2.54 -> 43.18 | AB21: =+Y21*2.54 -> 10.16
A22: 4 | B22: 4 | G22: 31 | K22: 31 | P22: 1 | Q22: 31 | R22: =+T22/P22 -> 3.7 | S22: =+U22/P22 -> 4.7 | T22: 3.7 | U22: 4.7 | V22: =Z22&"*"&AA22&"*"&AB22 -> 50.8*43.18*11.43 | W22: 20 | X22: 17 | Y22: 4.5 | Z22: =+W22*2.54 -> 50.8 | AA22: =+X22*2.54 -> 43.18 | AB22: =+Y22*2.54 -> 11.43
A23: 5 | B23: 5 | G23: 24 | L23: 24 | P23: 1 | Q23: 24 | R23: =+T23/P23 -> 2.98 | S23: =+U23/P23 -> 3.96 | T23: 2.98 | U23: 3.96 | V23: =Z23&"*"&AA23&"*"&AB23 -> 50.8*43.18*10.16 | W23: 20 | X23: 17 | Y23: 4 | Z23: =+W23*2.54 -> 50.8 | AA23: =+X23*2.54 -> 43.18 | AB23: =+Y23*2.54 -> 10.16
L24: 24 | Z24: =+W24*2.54 -> 0 | AA24: =+X24*2.54 -> 0 | AB24: =+Y24*2.54 -> 0
A25: 6 | B25: 6 | D25: NESSB711 | E25: 385 ENERGY | F25: 385 | G25: 8 | H25: 8 | P25: 1 | Q25: 8 | R25: =+T25/P25 -> 0.7 | S25: =+U25/P25 -> 1 | T25: 0.7 | U25: 1 | V25: =Z25&"*"&AA25&"*"&AB25 -> 25.4*22.86*8.89 | W25: 10 | X25: 9 | Y25: 3.5 | Z25: =+W25*2.54 -> 25.4 | AA25: =+X25*2.54 -> 22.86 | AB25: =+Y25*2.54 -> 8.89
A26: 7 | B26: 7 | G26: 25 | I26: 25 | P26: 1 | Q26: 25 | R26: =+T26/P26 -> 2.42 | S26: =+U26/P26 -> 3.38 | T26: 2.42 | U26: 3.38 | V26: =Z26&"*"&AA26&"*"&AB26 -> 50.8*43.18*8.89 | W26: 20 | X26: 17 | Y26: 3.5 | Z26: =+W26*2.54 -> 50.8 | AA26: =+X26*2.54 -> 43.18 | AB26: =+Y26*2.54 -> 8.89
A27: 8 | B27: 8 | G27: 32 | J27: 32 | P27: 1 | Q27: 32 | R27: =+T27/P27 -> 3.16 | S27: =+U27/P27 -> 4.14 | T27: 3.16 | U27: 4.14 | V27: =Z27&"*"&AA27&"*"&AB27 -> 50.8*43.18*10.16 | W27: 20 | X27: 17 | Y27: 4 | Z27: =+W27*2.54 -> 50.8 | AA27: =+X27*2.54 -> 43.18 | AB27: =+Y27*2.54 -> 10.16
A28: 9 | B28: 9 | G28: 31 | K28: 31 | P28: 1 | Q28: 31 | R28: =+T28/P28 -> 3.7 | S28: =+U28/P28 -> 4.7 | T28: 3.7 | U28: 4.7 | V28: =Z28&"*"&AA28&"*"&AB28 -> 50.8*43.18*11.43 | W28: 20 | X28: 17 | Y28: 4.5 | Z28: =+W28*2.54 -> 50.8 | AA28: =+X28*2.54 -> 43.18 | AB28: =+Y28*2.54 -> 11.43
A29: 10 | B29: 10 | G29: 24 | L29: 24 | P29: 1 | Q29: 24 | R29: =+T29/P29 -> 2.98 | S29: =+U29/P29 -> 3.96 | T29: 2.98 | U29: 3.96 | V29: =Z29&"*"&AA29&"*"&AB29 -> 50.8*43.18*10.16 | W29: 20 | X29: 17 | Y29: 4 | Z29: =+W29*2.54 -> 50.8 | AA29: =+X29*2.54 -> 43.18 | AB29: =+Y29*2.54 -> 10.16
L30: 24 | Z30: =+W30*2.54 -> 0 | AA30: =+X30*2.54 -> 0 | AB30: =+Y30*2.54 -> 0
A31: 11 | B31: 11 | D31: NESSB711 | E31: 655 DESERT PINK | F31: 655 | G31: 8 | H31: 8 | P31: 1 | Q31: 8 | R31: =+T31/P31 -> 0.7 | S31: =+U31/P31 -> 1 | T31: 0.7 | U31: 1 | V31: =Z31&"*"&AA31&"*"&AB31 -> 25.4*22.86*8.89 | W31: 10 | X31: 9 | Y31: 3.5 | Z31: =+W31*2.54 -> 25.4 | AA31: =+X31*2.54 -> 22.86 | AB31: =+Y31*2.54 -> 8.89
A32: 12 | B32: 12 | G32: 25 | I32: 25 | P32: 1 | Q32: 25 | R32: =+T32/P32 -> 2.42 | S32: =+U32/P32 -> 3.38 | T32: 2.42 | U32: 3.38 | V32: =Z32&"*"&AA32&"*"&AB32 -> 50.8*43.18*8.89 | W32: 20 | X32: 17 | Y32: 3.5 | Z32: =+W32*2.54 -> 50.8 | AA32: =+X32*2.54 -> 43.18 | AB32: =+Y32*2.54 -> 8.89
A33: 13 | B33: 13 | G33: 32 | J33: 32 | P33: 1 | Q33: 32 | R33: =+T33/P33 -> 3.16 | S33: =+U33/P33 -> 4.14 | T33: 3.16 | U33: 4.14 | V33: =Z33&"*"&AA33&"*"&AB33 -> 50.8*43.18*10.16 | W33: 20 | X33: 17 | Y33: 4 | Z33: =+W33*2.54 -> 50.8 | AA33: =+X33*2.54 -> 43.18 | AB33: =+Y33*2.54 -> 10.16
A34: 14 | B34: 14 | G34: 31 | K34: 31 | P34: 1 | Q34: 31 | R34: =+T34/P34 -> 3.7 | S34: =+U34/P34 -> 4.7 | T34: 3.7 | U34: 4.7 | V34: =Z34&"*"&AA34&"*"&AB34 -> 50.8*43.18*11.43 | W34: 20 | X34: 17 | Y34: 4.5 | Z34: =+W34*2.54 -> 50.8 | AA34: =+X34*2.54 -> 43.18 | AB34: =+Y34*2.54 -> 11.43
A35: 15 | B35: 15 | G35: 24 | L35: 24 | P35: 1 | Q35: 24 | R35: =+T35/P35 -> 2.98 | S35: =+U35/P35 -> 3.96 | T35: 2.98 | U35: 3.96 | V35: =Z35&"*"&AA35&"*"&AB35 -> 50.8*43.18*10.16 | W35: 20 | X35: 17 | Y35: 4 | Z35: =+W35*2.54 -> 50.8 | AA35: =+X35*2.54 -> 43.18 | AB35: =+Y35*2.54 -> 10.16
L36: 24 | Z36: =+W36*2.54 -> 0 | AA36: =+X36*2.54 -> 0 | AB36: =+Y36*2.54 -> 0
A37: 16 | B37: 16 | D37: NESSG730 | E37: 001 BLACK | F37: 001 | G37: 9 | H37: 9 | P37: 1 | Q37: 9 | R37: =+T37/P37 -> 0.9 | S37: =+U37/P37 -> 1.7 | T37: 0.9 | U37: 1.7 | V37: =Z37&"*"&AA37&"*"&AB37 -> 50.8*43.18*7.62 | W37: 20 | X37: 17 | Y37: 3 | Z37: =+W37*2.54 -> 50.8 | AA37: =+X37*2.54 -> 43.18 | AB37: =+Y37*2.54 -> 7.62
A38: 17 | B38: 17 | G38: 19 | I38: 19 | P38: 1 | Q38: 19 | R38: =+T38/P38 -> 2.06 | S38: =+U38/P38 -> 2.86 | T38: 2.06 | U38: 2.86 | V38: =Z38&"*"&AA38&"*"&AB38 -> 50.8*43.18*7.62 | W38: 20 | X38: 17 | Y38: 3 | Z38: =+W38*2.54 -> 50.8 | AA38: =+X38*2.54 -> 43.18 | AB38: =+Y38*2.54 -> 7.62
A39: 18 | B39: 18 | G39: 26 | J39: 26 | P39: 1 | Q39: 26 | R39: =+T39/P39 -> 3.17 | S39: =+U39/P39 -> 4 | T39: 3.17 | U39: 4 | V39: =Z39&"*"&AA39&"*"&AB39 -> 53.34*43.18*8.89 | W39: 21 | X39: 17 | Y39: 3.5 | Z39: =+W39*2.54 -> 53.34 | AA39: =+X39*2.54 -> 43.18 | AB39: =+Y39*2.54 -> 8.89
A40: 19 | B40: 19 | G40: 26 | K40: 26 | P40: 1 | Q40: 26 | R40: =+T40/P40 -> 3.59 | S40: =+U40/P40 -> 4.42 | T40: 3.59 | U40: 4.42 | V40: =Z40&"*"&AA40&"*"&AB40 -> 53.34*43.18*8.89 | W40: 21 | X40: 17 | Y40: 3.5 | Z40: =+W40*2.54 -> 53.34 | AA40: =+X40*2.54 -> 43.18 | AB40: =+Y40*2.54 -> 8.89
A41: 20 | B41: 20 | G41: 16 | L41: 16 | P41: 1 | Q41: 16 | R41: =+T41/P41 -> 2.35 | S41: =+U41/P41 -> 3.15 | T41: 2.35 | U41: 3.15 | V41: =Z41&"*"&AA41&"*"&AB41 -> 53.34*43.18*7.62 | W41: 21 | X41: 17 | Y41: 3 | Z41: =+W41*2.54 -> 53.34 | AA41: =+X41*2.54 -> 43.18 | AB41: =+Y41*2.54 -> 7.62
L42: 16 | Z42: =+W42*2.54 -> 0 | AA42: =+X42*2.54 -> 0 | AB42: =+Y42*2.54 -> 0
A43: 21 | B43: 21 | D43: NESSG730 | E43: 655 DESERT PINK | F43: 655 | G43: 9 | H43: 9 | P43: 1 | Q43: 9 | R43: =+T43/P43 -> 0.9 | S43: =+U43/P43 -> 1.7 | T43: 0.9 | U43: 1.7 | V43: =Z43&"*"&AA43&"*"&AB43 -> 50.8*43.18*7.62 | W43: 20 | X43: 17 | Y43: 3 | Z43: =+W43*2.54 -> 50.8 | AA43: =+X43*2.54 -> 43.18 | AB43: =+Y43*2.54 -> 7.62
A44: 22 | B44: 22 | G44: 19 | I44: 19 | P44: 1 | Q44: 19 | R44: =+T44/P44 -> 2.06 | S44: =+U44/P44 -> 2.86 | T44: 2.06 | U44: 2.86 | V44: =Z44&"*"&AA44&"*"&AB44 -> 50.8*43.18*7.62 | W44: 20 | X44: 17 | Y44: 3 | Z44: =+W44*2.54 -> 50.8 | AA44: =+X44*2.54 -> 43.18 | AB44: =+Y44*2.54 -> 7.62
A45: 23 | B45: 23 | G45: 26 | J45: 26 | P45: 1 | Q45: 26 | R45: =+T45/P45 -> 3.17 | S45: =+U45/P45 -> 4 | T45: 3.17 | U45: 4 | V45: =Z45&"*"&AA45&"*"&AB45 -> 53.34*43.18*8.89 | W45: 21 | X45: 17 | Y45: 3.5 | Z45: =+W45*2.54 -> 53.34 | AA45: =+X45*2.54 -> 43.18 | AB45: =+Y45*2.54 -> 8.89
A46: 24 | B46: 24 | G46: 26 | K46: 26 | P46: 1 | Q46: 26 | R46: =+T46/P46 -> 3.59 | S46: =+U46/P46 -> 4.42 | T46: 3.59 | U46: 4.42 | V46: =Z46&"*"&AA46&"*"&AB46 -> 53.34*43.18*8.89 | W46: 21 | X46: 17 | Y46: 3.5 | Z46: =+W46*2.54 -> 53.34 | AA46: =+X46*2.54 -> 43.18 | AB46: =+Y46*2.54 -> 8.89
A47: 25 | B47: 25 | G47: 16 | L47: 16 | P47: 1 | Q47: 16 | R47: =+T47/P47 -> 2.35 | S47: =+U47/P47 -> 3.15 | T47: 2.35 | U47: 3.15 | V47: =Z47&"*"&AA47&"*"&AB47 -> 53.34*43.18*7.62 | W47: 21 | X47: 17 | Y47: 3 | Z47: =+W47*2.54 -> 53.34 | AA47: =+X47*2.54 -> 43.18 | AB47: =+Y47*2.54 -> 7.62
L48: 16 | Z48: =+W48*2.54 -> 0 | AA48: =+X48*2.54 -> 0 | AB48: =+Y48*2.54 -> 0
A49: Master box 26-27 | C49: Master box | W49: 19 | X49: 11 | Y49: 8.5 | Z49: =+W49*2.54 -> 48.26 | AA49: =+X49*2.54 -> 27.94 | AB49: =+Y49*2.54 -> 21.59
A50: 26 | B50: 26 | C50: Small box | D50: NESSG758 | E50: 385 ENERGY | F50: 385 | G50: 7 | H50: 7 | P50: 1 | Q50: 7 | R50: =+T50/P50 -> 0.72 | S50: =+U50/P50 -> 0.96 | T50: 0.72 | U50: 0.96 | V50: =Z50&"*"&AA50&"*"&AB50 -> 25.4*22.86*8.89 | W50: 10 | X50: 9 | Y50: 3.5 | Z50: =+W50*2.54 -> 25.4 | AA50: =+X50*2.54 -> 22.86 | AB50: =+Y50*2.54 -> 8.89
A51: 27 | B51: 27 | C51: Small box | G51: 14 | I51: 14 | Q51: 14 | V51: =Z51&"*"&AA51&"*"&AB51 -> 44.45*25.4*7.62 | W51: 17.5 | X51: 10 | Y51: 3 | Z51: =+W51*2.54 -> 44.45 | AA51: =+X51*2.54 -> 25.4 | AB51: =+Y51*2.54 -> 7.62
A52: 28 | B52: 28 | C52: ODD CARTON | G52: 19 | J52: 19 | P52: 1 | Q52: 19 | R52: =+T52/P52 -> 2.28 | S52: =+U52/P52 -> 3.08 | T52: 2.28 | U52: 3.08 | V52: =Z52&"*"&AA52&"*"&AB52 -> 53.34*43.18*7.62 | W52: 21 | X52: 17 | Y52: 3 | Z52: =+W52*2.54 -> 53.34 | AA52: =+X52*2.54 -> 43.18 | AB52: =+Y52*2.54 -> 7.62
A53: 29 | B53: 29 | C53: ODD CARTON | G53: 18 | K53: 18 | P53: 1 | Q53: 18 | R53: =+T53/P53 -> 2.44 | S53: =+U53/P53 -> 3.24 | T53: 2.44 | U53: 3.24 | V53: =Z53&"*"&AA53&"*"&AB53 -> 50.8*43.18*7.62 | W53: 20 | X53: 17 | Y53: 3 | Z53: =+W53*2.54 -> 50.8 | AA53: =+X53*2.54 -> 43.18 | AB53: =+Y53*2.54 -> 7.62
A54: 30 | B54: 30 | C54: ODD CARTON | G54: 14 | L54: 14 | P54: 1 | Q54: 14 | R54: =+T54/P54 -> 2.06 | S54: =+U54/P54 -> 2.54 | T54: 2.06 | U54: 2.54 | V54: =Z54&"*"&AA54&"*"&AB54 -> 43.18*25.4*11.43 | W54: 17 | X54: 10 | Y54: 4.5 | Z54: =+W54*2.54 -> 43.18 | AA54: =+X54*2.54 -> 25.4 | AB54: =+Y54*2.54 -> 11.43
L55: 14 | Z55: =+W55*2.54 -> 0 | AA55: =+X55*2.54 -> 0 | AB55: =+Y55*2.54 -> 0
A56: Master box 31-32 | C56: Master box | W56: 19 | X56: 11 | Y56: 8.5 | Z56: =+W56*2.54 -> 48.26 | AA56: =+X56*2.54 -> 27.94 | AB56: =+Y56*2.54 -> 21.59
A57: 31 | B57: 31 | C57: Small box | D57: NESSG758 | E57: 655 DESERT PINK | F57: 655 | G57: 7 | H57: 7 | P57: 1 | Q57: 7 | R57: =+T57/P57 -> 0.72 | S57: =+U57/P57 -> 0.96 | T57: 0.72 | U57: 0.96 | V57: =Z57&"*"&AA57&"*"&AB57 -> 25.4*22.86*8.89 | W57: 10 | X57: 9 | Y57: 3.5 | Z57: =+W57*2.54 -> 25.4 | AA57: =+X57*2.54 -> 22.86 | AB57: =+Y57*2.54 -> 8.89
A58: 32 | B58: 32 | C58: Small box | G58: 14 | I58: 14 | Q58: 14 | V58: =Z58&"*"&AA58&"*"&AB58 -> 44.45*25.4*7.62 | W58: 17.5 | X58: 10 | Y58: 3 | Z58: =+W58*2.54 -> 44.45 | AA58: =+X58*2.54 -> 25.4 | AB58: =+Y58*2.54 -> 7.62
A59: 33 | B59: 33 | C59: ODD CARTON | G59: 19 | J59: 19 | P59: 1 | Q59: 19 | R59: =+T59/P59 -> 2.28 | S59: =+U59/P59 -> 3.08 | T59: 2.28 | U59: 3.08 | V59: =Z59&"*"&AA59&"*"&AB59 -> 53.34*43.18*7.62 | W59: 21 | X59: 17 | Y59: 3 | Z59: =+W59*2.54 -> 53.34 | AA59: =+X59*2.54 -> 43.18 | AB59: =+Y59*2.54 -> 7.62
A60: 34 | B60: 34 | C60: ODD CARTON | G60: 18 | K60: 18 | P60: 1 | Q60: 18 | R60: =+T60/P60 -> 2.44 | S60: =+U60/P60 -> 3.24 | T60: 2.44 | U60: 3.24 | V60: =Z60&"*"&AA60&"*"&AB60 -> 50.8*43.18*7.62 | W60: 20 | X60: 17 | Y60: 3 | Z60: =+W60*2.54 -> 50.8 | AA60: =+X60*2.54 -> 43.18 | AB60: =+Y60*2.54 -> 7.62
A61: 35 | B61: 35 | C61: ODD CARTON | G61: 14 | L61: 14 | P61: 1 | Q61: 14 | R61: =+T61/P61 -> 2.06 | S61: =+U61/P61 -> 2.54 | T61: 2.06 | U61: 2.54 | V61: =Z61&"*"&AA61&"*"&AB61 -> 43.18*25.4*11.43 | W61: 17 | X61: 10 | Y61: 4.5 | Z61: =+W61*2.54 -> 43.18 | AA61: =+X61*2.54 -> 25.4 | AB61: =+Y61*2.54 -> 11.43
L62: 14
L65: =SUM(L19:L64) -> 264 | M65: =SUM(M19:M64) -> 0 | N65: =SUM(N19:N64) -> 0 | O65: =SUM(O19:O64) -> 0 | P65: =SUM(P19:P64) -> 33 | Q65: =SUM(Q19:Q64) -> 696 | T65: =SUM(T19:T64) -> 78.02 | U65: =SUM(U19:U64) -> 103.44
C68: CUSTOMER PO | D68: Style | E68: Color | F68: Color Code | G68: xs | H68: S | I68: M | J68: L | K68: XL | P68: TOT CTNS | Q68: TOT PCS
C69: EV154 | D69: NESSB711 | E69: BLACK | F69: 001 | G69: 8 | H69: 25 | I69: 32 | J69: 31 | K69: 24 | P69: 5 | Q69: 120 | W69: =+SUM(G69:K69) -> 120 | X69: =+Q69-W69 -> 0
C70: EV154 | D70: NESSB711 | E70: ENERGY | F70: 385 | G70: 8 | H70: 25 | I70: 32 | J70: 31 | K70: 24 | P70: 5 | Q70: 120
C71: EV154 | D71: NESSB711 | E71: DESERT PINK | F71: 655 | G71: 8 | H71: 25 | I71: 32 | J71: 31 | K71: 24 | P71: 5 | Q71: 120
C72: EV154 | D72: NESSG730 | E72: BLACK | F72: 001 | G72: 9 | H72: 19 | I72: 26 | J72: 26 | K72: 16 | P72: 5 | Q72: 96
C73: EV154 | D73: NESSG730 | E73: DESERT PINK | F73: 655 | G73: 9 | H73: 19 | I73: 26 | J73: 26 | K73: 16 | P73: 5 | Q73: 96
C74: EV154 | D74: NESSG758 | E74: ENERGY | F74: 385 | G74: 7 | H74: 14 | I74: 19 | J74: 18 | K74: 14 | P74: 4 | Q74: 72
C75: EV154 | D75: NESSG758 | E75: DESERT PINK | F75: 655 | G75: 7 | H75: 14 | I75: 19 | J75: 18 | K75: 14 | P75: 4 | Q75: 72
J78: TOTAL | P78: =SUM(P69:P76) -> 33 | Q78: =SUM(Q69:Q76) -> 696

Sheet IRREGULAR SS PL EV154
A4: PACKING LIST
G5: PEI
A6: ISSUE TO : | D6: =+'[1]INVOICE 11'!C7 -> SUPREME INTERNATIONAL, LLC | G6: STYLE:
G7: LABEL
G8: P.O.:
G9: PCS
G10: SIZES
A12: PAYMENT: T/C | G12: MADE IN
A13: PO NO: | B13: EV154 | G13: C# UP
A14: CUSTOMER PO.: | D14: =+B13 -> EV154
A15: INVOICE NO: | C15: =+'INVOICE 94'!M2 -> 7726477
A16: Detail Breakdown
A18: CASE FROM-TO | C18: REMARKS | D18: Style | E18: Color Name | F18: Color code | G18: Units/case | H18: xs | I18: S | J18: M | K18: L | L18: 4 | M18: 5 | N18: 6 | O18: 6X | P18: TOT CTNS | Q18: TOT PCS | R18: NW | S18: GW | T18: TTL NW | U18: TTL GW | V18: CARTON SIZE ( CM)
A19: 1 | B19: 1 | D19: NESSB711 | E19: 001 BLACK | F19: 001 | G19: 8 | H19: 8 | P19: 1 | Q19: 8 | R19: =+T19/P19 -> 0.7 | S19: =+U19/P19 -> 1 | T19: 0.7 | U19: 1 | V19: =Z19&"*"&AA19&"*"&AB19 -> 25.4*22.86*8.89 | W19: 10 | X19: 9 | Y19: 3.5 | Z19: =+W19*2.54 -> 25.4 | AA19: =+X19*2.54 -> 22.86 | AB19: =+Y19*2.54 -> 8.89
A20: 2 | B20: 2 | G20: 25 | I20: 25 | P20: 1 | Q20: 25 | R20: =+T20/P20 -> 2.42 | S20: =+U20/P20 -> 3.38 | T20: 2.42 | U20: 3.38 | V20: =Z20&"*"&AA20&"*"&AB20 -> 50.8*43.18*8.89 | W20: 20 | X20: 17 | Y20: 3.5 | Z20: =+W20*2.54 -> 50.8 | AA20: =+X20*2.54 -> 43.18 | AB20: =+Y20*2.54 -> 8.89
A21: 3 | B21: 3 | G21: 32 | J21: 32 | P21: 1 | Q21: 32 | R21: =+T21/P21 -> 3.16 | S21: =+U21/P21 -> 4.14 | T21: 3.16 | U21: 4.14 | V21: =Z21&"*"&AA21&"*"&AB21 -> 50.8*43.18*10.16 | W21: 20 | X21: 17 | Y21: 4 | Z21: =+W21*2.54 -> 50.8 | AA21: =+X21*2.54 -> 43.18 | AB21: =+Y21*2.54 -> 10.16
A22: 4 | B22: 4 | G22: 31 | K22: 31 | P22: 1 | Q22: 31 | R22: =+T22/P22 -> 3.7 | S22: =+U22/P22 -> 4.7 | T22: 3.7 | U22: 4.7 | V22: =Z22&"*"&AA22&"*"&AB22 -> 50.8*43.18*11.43 | W22: 20 | X22: 17 | Y22: 4.5 | Z22: =+W22*2.54 -> 50.8 | AA22: =+X22*2.54 -> 43.18 | AB22: =+Y22*2.54 -> 11.43
A23: 5 | B23: 5 | G23: 24 | L23: 24 | P23: 1 | Q23: 24 | R23: =+T23/P23 -> 2.98 | S23: =+U23/P23 -> 3.96 | T23: 2.98 | U23: 3.96 | V23: =Z23&"*"&AA23&"*"&AB23 -> 50.8*43.18*10.16 | W23: 20 | X23: 17 | Y23: 4 | Z23: =+W23*2.54 -> 50.8 | AA23: =+X23*2.54 -> 43.18 | AB23: =+Y23*2.54 -> 10.16
L24: 24 | Z24: =+W24*2.54 -> 0 | AA24: =+X24*2.54 -> 0 | AB24: =+Y24*2.54 -> 0
A25: 6 | B25: 6 | D25: NESSB711 | E25: 385 ENERGY | F25: 385 | G25: 8 | H25: 8 | P25: 1 | Q25: 8 | R25: =+T25/P25 -> 0.7 | S25: =+U25/P25 -> 1 | T25: 0.7 | U25: 1 | V25: =Z25&"*"&AA25&"*"&AB25 -> 25.4*22.86*8.89 | W25: 10 | X25: 9 | Y25: 3.5 | Z25: =+W25*2.54 -> 25.4 | AA25: =+X25*2.54 -> 22.86 | AB25: =+Y25*2.54 -> 8.89
A26: 7 | B26: 7 | G26: 25 | I26: 25 | P26: 1 | Q26: 25 | R26: =+T26/P26 -> 2.42 | S26: =+U26/P26 -> 3.38 | T26: 2.42 | U26: 3.38 | V26: =Z26&"*"&AA26&"*"&AB26 -> 50.8*43.18*8.89 | W26: 20 | X26: 17 | Y26: 3.5 | Z26: =+W26*2.54 -> 50.8 | AA26: =+X26*2.54 -> 43.18 | AB26: =+Y26*2.54 -> 8.89
A27: 8 | B27: 8 | G27: 32 | J27: 32 | P27: 1 | Q27: 32 | R27: =+T27/P27 -> 3.16 | S27: =+U27/P27 -> 4.14 | T27: 3.16 | U27: 4.14 | V27: =Z27&"*"&AA27&"*"&AB27 -> 50.8*43.18*10.16 | W27: 20 | X27: 17 | Y27: 4 | Z27: =+W27*2.54 -> 50.8 | AA27: =+X27*2.54 -> 43.18 | AB27: =+Y27*2.54 -> 10.16
A28: 9 | B28: 9 | G28: 31 | K28: 31 | P28: 1 | Q28: 31 | R28: =+T28/P28 -> 3.7 | S28: =+U28/P28 -> 4.7 | T28: 3.7 | U28: 4.7 | V28: =Z28&"*"&AA28&"*"&AB28 -> 50.8*43.18*11.43 | W28: 20 | X28: 17 | Y28: 4.5 | Z28: =+W28*2.54 -> 50.8 | AA28: =+X28*2.54 -> 43.18 | AB28: =+Y28*2.54 -> 11.43
A29: 10 | B29: 10 | G29: 24 | L29: 24 | P29: 1 | Q29: 24 | R29: =+T29/P29 -> 2.98 | S29: =+U29/P29 -> 3.96 | T29: 2.98 | U29: 3.96 | V29: =Z29&"*"&AA29&"*"&AB29 -> 50.8*43.18*10.16 | W29: 20 | X29: 17 | Y29: 4 | Z29: =+W29*2.54 -> 50.8 | AA29: =+X29*2.54 -> 43.18 | AB29: =+Y29*2.54 -> 10.16
L30: 24 | Z30: =+W30*2.54 -> 0 | AA30: =+X30*2.54 -> 0 | AB30: =+Y30*2.54 -> 0
A31: 11 | B31: 11 | D31: NESSB711 | E31: 655 DESERT PINK | F31: 655 | G31: 8 | H31: 8 | P31: 1 | Q31: 8 | R31: =+T31/P31 -> 0.7 | S31: =+U31/P31 -> 1 | T31: 0.7 | U31: 1 | V31: =Z31&"*"&AA31&"*"&AB31 -> 25.4*22.86*8.89 | W31: 10 | X31: 9 | Y31: 3.5 | Z31: =+W31*2.54 -> 25.4 | AA31: =+X31*2.54 -> 22.86 | AB31: =+Y31*2.54 -> 8.89
A32: 12 | B32: 12 | G32: 25 | I32: 25 | P32: 1 | Q32: 25 | R32: =+T32/P32 -> 2.42 | S32: =+U32/P32 -> 3.38 | T32: 2.42 | U32: 3.38 | V32: =Z32&"*"&AA32&"*"&AB32 -> 50.8*43.18*8.89 | W32: 20 | X32: 17 | Y32: 3.5 | Z32: =+W32*2.54 -> 50.8 | AA32: =+X32*2.54 -> 43.18 | AB32: =+Y32*2.54 -> 8.89
A33: 13 | B33: 13 | G33: 32 | J33: 32 | P33: 1 | Q33: 32 | R33: =+T33/P33 -> 3.16 | S33: =+U33/P33 -> 4.14 | T33: 3.16 | U33: 4.14 | V33: =Z33&"*"&AA33&"*"&AB33 -> 50.8*43.18*10.16 | W33: 20 | X33: 17 | Y33: 4 | Z33: =+W33*2.54 -> 50.8 | AA33: =+X33*2.54 -> 43.18 | AB33: =+Y33*2.54 -> 10.16
A34: 14 | B34: 14 | G34: 31 | K34: 31 | P34: 1 | Q34: 31 | R34: =+T34/P34 -> 3.7 | S34: =+U34/P34 -> 4.7 | T34: 3.7 | U34: 4.7 | V34: =Z34&"*"&AA34&"*"&AB34 -> 50.8*43.18*11.43 | W34: 20 | X34: 17 | Y34: 4.5 | Z34: =+W34*2.54 -> 50.8 | AA34: =+X34*2.54 -> 43.18 | AB34: =+Y34*2.54 -> 11.43
A35: 15 | B35: 15 | G35: 24 | L35: 24 | P35: 1 | Q35: 24 | R35: =+T35/P35 -> 2.98 | S35: =+U35/P35 -> 3.96 | T35: 2.98 | U35: 3.96 | V35: =Z35&"*"&AA35&"*"&AB35 -> 50.8*43.18*10.16 | W35: 20 | X35: 17 | Y35: 4 | Z35: =+W35*2.54 -> 50.8 | AA35: =+X35*2.54 -> 43.18 | AB35: =+Y35*2.54 -> 10.16
L36: 24 | Z36: =+W36*2.54 -> 0 | AA36: =+X36*2.54 -> 0 | AB36: =+Y36*2.54 -> 0
A37: 16 | B37: 16 | D37: NESSG730 | E37: 001 BLACK | F37: 001 | G37: 9 | H37: 9 | P37: 1 | Q37: 9 | R37: =+T37/P37 -> 0.9 | S37: =+U37/P37 -> 1.7 | T37: 0.9 | U37: 1.7 | V37: =Z37&"*"&AA37&"*"&AB37 -> 50.8*43.18*7.62 | W37: 20 | X37: 17 | Y37: 3 | Z37: =+W37*2.54 -> 50.8 | AA37: =+X37*2.54 -> 43.18 | AB37: =+Y37*2.54 -> 7.62
A38: 17 | B38: 17 | G38: 19 | I38: 19 | P38: 1 | Q38: 19 | R38: =+T38/P38 -> 2.06 | S38: =+U38/P38 -> 2.86 | T38: 2.06 | U38: 2.86 | V38: =Z38&"*"&AA38&"*"&AB38 -> 50.8*43.18*7.62 | W38: 20 | X38: 17 | Y38: 3 | Z38: =+W38*2.54 -> 50.8 | AA38: =+X38*2.54 -> 43.18 | AB38: =+Y38*2.54 -> 7.62
A39: 18 | B39: 18 | G39: 26 | J39: 26 | P39: 1 | Q39: 26 | R39: =+T39/P39 -> 3.17 | S39: =+U39/P39 -> 4 | T39: 3.17 | U39: 4 | V39: =Z39&"*"&AA39&"*"&AB39 -> 53.34*43.18*8.89 | W39: 21 | X39: 17 | Y39: 3.5 | Z39: =+W39*2.54 -> 53.34 | AA39: =+X39*2.54 -> 43.18 | AB39: =+Y39*2.54 -> 8.89
A40: 19 | B40: 19 | G40: 26 | K40: 26 | P40: 1 | Q40: 26 | R40: =+T40/P40 -> 3.59 | S40: =+U40/P40 -> 4.42 | T40: 3.59 | U40: 4.42 | V40: =Z40&"*"&AA40&"*"&AB40 -> 53.34*43.18*8.89 | W40: 21 | X40: 17 | Y40: 3.5 | Z40: =+W40*2.54 -> 53.34 | AA40: =+X40*2.54 -> 43.18 | AB40: =+Y40*2.54 -> 8.89
A41: 20 | B41: 20 | G41: 16 | L41: 16 | P41: 1 | Q41: 16 | R41: =+T41/P41 -> 2.35 | S41: =+U41/P41 -> 3.15 | T41: 2.35 | U41: 3.15 | V41: =Z41&"*"&AA41&"*"&AB41 -> 53.34*43.18*7.62 | W41: 21 | X41: 17 | Y41: 3 | Z41: =+W41*2.54 -> 53.34 | AA41: =+X41*2.54 -> 43.18 | AB41: =+Y41*2.54 -> 7.62
L42: 16 | Z42: =+W42*2.54 -> 0 | AA42: =+X42*2.54 -> 0 | AB42: =+Y42*2.54 -> 0
A43: 21 | B43: 21 | D43: NESSG730 | E43: 655 DESERT PINK | F43: 655 | G43: 9 | H43: 9 | P43: 1 | Q43: 9 | R43: =+T43/P43 -> 0.9 | S43: =+U43/P43 -> 1.7 | T43: 0.9 | U43: 1.7 | V43: =Z43&"*"&AA43&"*"&AB43 -> 50.8*43.18*7.62 | W43: 20 | X43: 17 | Y43: 3 | Z43: =+W43*2.54 -> 50.8 | AA43: =+X43*2.54 -> 43.18 | AB43: =+Y43*2.54 -> 7.62
A44: 22 | B44: 22 | G44: 19 | I44: 19 | P44: 1 | Q44: 19 | R44: =+T44/P44 -> 2.06 | S44: =+U44/P44 -> 2.86 | T44: 2.06 | U44: 2.86 | V44: =Z44&"*"&AA44&"*"&AB44 -> 50.8*43.18*7.62 | W44: 20 | X44: 17 | Y44: 3 | Z44: =+W44*2.54 -> 50.8 | AA44: =+X44*2.54 -> 43.18 | AB44: =+Y44*2.54 -> 7.62
A45: 23 | B45: 23 | G45: 26 | J45: 26 | P45: 1 | Q45: 26 | R45: =+T45/P45 -> 3.17 | S45: =+U45/P45 -> 4 | T45: 3.17 | U45: 4 | V45: =Z45&"*"&AA45&"*"&AB45 -> 53.34*43.18*8.89 | W45: 21 | X45: 17 | Y45: 3.5 | Z45: =+W45*2.54 -> 53.34 | AA45: =+X45*2.54 -> 43.18 | AB45: =+Y45*2.54 -> 8.89
A46: 24 | B46: 24 | G46: 26 | K46: 26 | P46: 1 | Q46: 26 | R46: =+T46/P46 -> 3.59 | S46: =+U46/P46 -> 4.42 | T46: 3.59 | U46: 4.42 | V46: =Z46&"*"&AA46&"*"&AB46 -> 53.34*43.18*8.89 | W46: 21 | X46: 17 | Y46: 3.5 | Z46: =+W46*2.54 -> 53.34 | AA46: =+X46*2.54 -> 43.18 | AB46: =+Y46*2.54 -> 8.89
A47: 25 | B47: 25 | G47: 16 | L47: 16 | P47: 1 | Q47: 16 | R47: =+T47/P47 -> 2.35 | S47: =+U47/P47 -> 3.15 | T47: 2.35 | U47: 3.15 | V47: =Z47&"*"&AA47&"*"&AB47 -> 53.34*43.18*7.62 | W47: 21 | X47: 17 | Y47: 3 | Z47: =+W47*2.54 -> 53.34 | AA47: =+X47*2.54 -> 43.18 | AB47: =+Y47*2.54 -> 7.62
L48: 16 | Z48: =+W48*2.54 -> 0 | AA48: =+X48*2.54 -> 0 | AB48: =+Y48*2.54 -> 0
A49: Master box 26-27 | C49: Master box | W49: 19 | X49: 11 | Y49: 8.5 | Z49: =+W49*2.54 -> 48.26 | AA49: =+X49*2.54 -> 27.94 | AB49: =+Y49*2.54 -> 21.59
A50: 26 | B50: 26 | C50: Small box | D50: NESSG758 | E50: 385 ENERGY | F50: 385 | G50: 7 | H50: 7 | P50: 1 | Q50: 7 | R50: =+T50/P50 -> 0.72 | S50: =+U50/P50 -> 0.96 | T50: 0.72 | U50: 0.96 | V50: =Z50&"*"&AA50&"*"&AB50 -> 25.4*22.86*8.89 | W50: 10 | X50: 9 | Y50: 3.5 | Z50: =+W50*2.54 -> 25.4 | AA50: =+X50*2.54 -> 22.86 | AB50: =+Y50*2.54 -> 8.89
A51: 27 | B51: 27 | C51: Small box | G51: 14 | I51: 14 | P51: 1 | Q51: 14 | V51: =Z51&"*"&AA51&"*"&AB51 -> 44.45*25.4*7.62 | W51: 17.5 | X51: 10 | Y51: 3 | Z51: =+W51*2.54 -> 44.45 | AA51: =+X51*2.54 -> 25.4 | AB51: =+Y51*2.54 -> 7.62
A52: 28 | B52: 28 | C52: ODD CARTON | G52: 19 | J52: 19 | P52: 1 | Q52: 19 | R52: =+T52/P52 -> 2.28 | S52: =+U52/P52 -> 3.08 | T52: 2.28 | U52: 3.08 | V52: =Z52&"*"&AA52&"*"&AB52 -> 53.34*43.18*7.62 | W52: 21 | X52: 17 | Y52: 3 | Z52: =+W52*2.54 -> 53.34 | AA52: =+X52*2.54 -> 43.18 | AB52: =+Y52*2.54 -> 7.62
A53: 29 | B53: 29 | C53: ODD CARTON | G53: 18 | K53: 18 | P53: 1 | Q53: 18 | R53: =+T53/P53 -> 2.44 | S53: =+U53/P53 -> 3.24 | T53: 2.44 | U53: 3.24 | V53: =Z53&"*"&AA53&"*"&AB53 -> 50.8*43.18*7.62 | W53: 20 | X53: 17 | Y53: 3 | Z53: =+W53*2.54 -> 50.8 | AA53: =+X53*2.54 -> 43.18 | AB53: =+Y53*2.54 -> 7.62
A54: 30 | B54: 30 | C54: ODD CARTON | G54: 14 | L54: 14 | P54: 1 | Q54: 14 | R54: =+T54/P54 -> 2.06 | S54: =+U54/P54 -> 2.54 | T54: 2.06 | U54: 2.54 | V54: =Z54&"*"&AA54&"*"&AB54 -> 43.18*25.4*11.43 | W54: 17 | X54: 10 | Y54: 4.5 | Z54: =+W54*2.54 -> 43.18 | AA54: =+X54*2.54 -> 25.4 | AB54: =+Y54*2.54 -> 11.43
L55: 14 | Z55: =+W55*2.54 -> 0 | AA55: =+X55*2.54 -> 0 | AB55: =+Y55*2.54 -> 0
A56: Master box 31-32 | C56: Master box | W56: 19 | X56: 11 | Y56: 8.5 | Z56: =+W56*2.54 -> 48.26 | AA56: =+X56*2.54 -> 27.94 | AB56: =+Y56*2.54 -> 21.59
A57: 31 | B57: 31 | C57: Small box | D57: NESSG758 | E57: 655 DESERT PINK | F57: 655 | G57: 7 | H57: 7 | P57: 1 | Q57: 7 | R57: =+T57/P57 -> 0.72 | S57: =+U57/P57 -> 0.96 | T57: 0.72 | U57: 0.96 | V57: =Z57&"*"&AA57&"*"&AB57 -> 25.4*22.86*8.89 | W57: 10 | X57: 9 | Y57: 3.5 | Z57: =+W57*2.54 -> 25.4 | AA57: =+X57*2.54 -> 22.86 | AB57: =+Y57*2.54 -> 8.89
A58: 32 | B58: 32 | C58: Small box | G58: 14 | I58: 14 | P58: 1 | Q58: 14 | V58: =Z58&"*"&AA58&"*"&AB58 -> 44.45*25.4*7.62 | W58: 17.5 | X58: 10 | Y58: 3 | Z58: =+W58*2.54 -> 44.45 | AA58: =+X58*2.54 -> 25.4 | AB58: =+Y58*2.54 -> 7.62
A59: 33 | B59: 33 | C59: ODD CARTON | G59: 19 | J59: 19 | P59: 1 | Q59: 19 | R59: =+T59/P59 -> 2.28 | S59: =+U59/P59 -> 3.08 | T59: 2.28 | U59: 3.08 | V59: =Z59&"*"&AA59&"*"&AB59 -> 53.34*43.18*7.62 | W59: 21 | X59: 17 | Y59: 3 | Z59: =+W59*2.54 -> 53.34 | AA59: =+X59*2.54 -> 43.18 | AB59: =+Y59*2.54 -> 7.62
A60: 34 | B60: 34 | C60: ODD CARTON | G60: 18 | K60: 18 | P60: 1 | Q60: 18 | R60: =+T60/P60 -> 2.44 | S60: =+U60/P60 -> 3.24 | T60: 2.44 | U60: 3.24 | V60: =Z60&"*"&AA60&"*"&AB60 -> 50.8*43.18*7.62 | W60: 20 | X60: 17 | Y60: 3 | Z60: =+W60*2.54 -> 50.8 | AA60: =+X60*2.54 -> 43.18 | AB60: =+Y60*2.54 -> 7.62
A61: 35 | B61: 35 | C61: ODD CARTON | G61: 14 | L61: 14 | P61: 1 | Q61: 14 | R61: =+T61/P61 -> 2.06 | S61: =+U61/P61 -> 2.54 | T61: 2.06 | U61: 2.54 | V61: =Z61&"*"&AA61&"*"&AB61 -> 43.18*25.4*11.43 | W61: 17 | X61: 10 | Y61: 4.5 | Z61: =+W61*2.54 -> 43.18 | AA61: =+X61*2.54 -> 25.4 | AB61: =+Y61*2.54 -> 11.43
L62: 14
L65: =SUM(L19:L64) -> 264 | M65: =SUM(M19:M64) -> 0 | N65: =SUM(N19:N64) -> 0 | O65: =SUM(O19:O64) -> 0 | P65: =SUM(P19:P64) -> 35 | Q65: =SUM(Q19:Q64) -> 696 | T65: =SUM(T19:T64) -> 78.02 | U65: =SUM(U19:U64) -> 103.44
C68: CUSTOMER PO | D68: Style | E68: Color | F68: Color Code | G68: xs | H68: S | I68: M | J68: L | K68: XL | P68: TOT CTNS | Q68: TOT PCS
C69: EV154 | D69: NESSB711 | E69: BLACK | F69: 001 | G69: 8 | H69: 25 | I69: 32 | J69: 31 | K69: 24 | P69: 5 | Q69: 120 | W69: =+SUM(G69:K69) -> 120 | X69: =+Q69-W69 -> 0
C70: EV154 | D70: NESSB711 | E70: ENERGY | F70: 385 | G70: 8 | H70: 25 | I70: 32 | J70: 31 | K70: 24 | P70: 5 | Q70: 120
C71: EV154 | D71: NESSB711 | E71: DESERT PINK | F71: 655 | G71: 8 | H71: 25 | I71: 32 | J71: 31 | K71: 24 | P71: 5 | Q71: 120
C72: EV154 | D72: NESSG730 | E72: BLACK | F72: 001 | G72: 9 | H72: 19 | I72: 26 | J72: 26 | K72: 16 | P72: 5 | Q72: 96
C73: EV154 | D73: NESSG730 | E73: DESERT PINK | F73: 655 | G73: 9 | H73: 19 | I73: 26 | J73: 26 | K73: 16 | P73: 5 | Q73: 96
C74: EV154 | D74: NESSG758 | E74: ENERGY | F74: 385 | G74: 7 | H74: 14 | I74: 19 | J74: 18 | K74: 14 | P74: 5 | Q74: 72
C75: EV154 | D75: NESSG758 | E75: DESERT PINK | F75: 655 | G75: 7 | H75: 14 | I75: 19 | J75: 18 | K75: 14 | P75: 5 | Q75: 72
J78: TOTAL | P78: =SUM(P69:P76) -> 35 | Q78: =SUM(Q69:Q76) -> 696

Sheet SOLID PL EV161
A4: PACKING LIST
G5: PEI
A6: ISSUE TO : | D6: =+'[1]INVOICE 11'!C7 -> SUPREME INTERNATIONAL, LLC | G6: STYLE:
G7: LABEL
G8: P.O.:
G9: PCS
G10: SIZES
A12: PAYMENT: T/C | G12: MADE IN
A13: PO NO: | B13: EV161 | G13: C# UP
A14: CUSTOMER PO.: | D14: =+B13 -> EV161
A15: INVOICE NO: | C15: =+'INVOICE 94'!M2 -> 7726477
A16: Detail Breakdown
A18: CASE FROM-TO | C18: REMARKS | D18: Style | E18: Color Name | F18: Color code | G18: Units/case | H18: xs | I18: S | J18: M | K18: L | L18: XL | M18: XXL | N18: 6 | O18: 6X | P18: TOT CTNS | Q18: TOT PCS | R18: NW | S18: GW | T18: TTL NW | U18: TTL GW | V18: CARTON SIZE ( CM)
A19: 1 | B19: 1 | D19: NESSG277 | E19: 001 BLACK | F19: 001 | G19: 36 | I19: 36 | P19: 1 | Q19: 36 | R19: =+T19/P19 -> 2.94 | S19: =+U19/P19 -> 3.64 | T19: 2.94 | U19: 3.64 | V19: =Z19&"*"&AA19&"*"&AB19 -> 40.64*38.1*11.43 | W19: 16 | X19: 15 | Y19: 4.5 | Z19: =+W19*2.54 -> 40.64 | AA19: =+X19*2.54 -> 38.1 | AB19: =+Y19*2.54 -> 11.43
A20: 2 | B20: 2 | G20: 36 | J20: 36 | P20: 1 | Q20: 36 | R20: =+T20/P20 -> 3.14 | S20: =+U20/P20 -> 3.84 | T20: 3.14 | U20: 3.84 | V20: =Z20&"*"&AA20&"*"&AB20 -> 40.64*38.1*11.43 | W20: 16 | X20: 15 | Y20: 4.5 | Z20: =+W20*2.54 -> 40.64 | AA20: =+X20*2.54 -> 38.1 | AB20: =+Y20*2.54 -> 11.43
A21: 3 | B21: 3 | G21: 36 | K21: 36 | P21: 1 | Q21: 36 | R21: =+T21/P21 -> 3.6 | S21: =+U21/P21 -> 4.32 | T21: 3.6 | U21: 4.32 | V21: =Z21&"*"&AA21&"*"&AB21 -> 40.64*38.1*13.97 | W21: 16 | X21: 15 | Y21: 5.5 | Z21: =+W21*2.54 -> 40.64 | AA21: =+X21*2.54 -> 38.1 | AB21: =+Y21*2.54 -> 13.97
A22: 4 | B22: 4 | C22: ODD CARTON | G22: 11 | H22: 11 | P22: 1 | Q22: 11 | R22: =+T22/P22 -> 0.68 | S22: =+U22/P22 -> 1.18 | T22: 0.68 | U22: 1.18 | V22: =Z22&"*"&AA22&"*"&AB22 -> 40.64*22.86*8.89 | W22: 16 | X22: 9 | Y22: 3.5 | Z22: =+W22*2.54 -> 40.64 | AA22: =+X22*2.54 -> 22.86 | AB22: =+Y22*2.54 -> 8.89
A23: 5 | B23: 5 | C23: ODD CARTON | G23: 18 | I23: 18 | P23: 1 | Q23: 18 | R23: =+T23/P23 -> 1.32 | S23: =+U23/P23 -> 1.84 | T23: 1.32 | U23: 1.84 | V23: =Z23&"*"&AA23&"*"&AB23 -> 40.64*22.86*11.43 | W23: 16 | X23: 9 | Y23: 4.5 | Z23: =+W23*2.54 -> 40.64 | AA23: =+X23*2.54 -> 22.86 | AB23: =+Y23*2.54 -> 11.43
A24: 6 | B24: 6 | C24: ODD CARTON | G24: 32 | J24: 32 | P24: 1 | Q24: 32 | R24: =+T24/P24 -> 2.6 | S24: =+U24/P24 -> 3.3 | T24: 2.6 | U24: 3.3 | V24: =Z24&"*"&AA24&"*"&AB24 -> 40.64*39.37*10.16 | W24: 16 | X24: 15.5 | Y24: 4 | Z24: =+W24*2.54 -> 40.64 | AA24: =+X24*2.54 -> 39.37 | AB24: =+Y24*2.54 -> 10.16
A25: 7 | B25: 7 | C25: ODD CARTON | G25: 13 | K25: 13 | P25: 1 | Q25: 13 | R25: =+T25/P25 -> 1.3 | S25: =+U25/P25 -> 1.6 | T25: 1.3 | U25: 1.6 | V25: =Z25&"*"&AA25&"*"&AB25 -> 40.64*22.86*8.89 | W25: 16 | X25: 9 | Y25: 3.5 | Z25: =+W25*2.54 -> 40.64 | AA25: =+X25*2.54 -> 22.86 | AB25: =+Y25*2.54 -> 8.89
A26: 8 | B26: 8 | C26: ODD CARTON | G26: 25 | L26: 25 | P26: 1 | Q26: 25 | R26: =+T26/P26 -> 2.64 | S26: =+U26/P26 -> 3.34 | T26: 2.64 | U26: 3.34 | V26: =Z26&"*"&AA26&"*"&AB26 -> 40.64*39.37*10.16 | W26: 16 | X26: 15.5 | Y26: 4 | Z26: =+W26*2.54 -> 40.64 | AA26: =+X26*2.54 -> 39.37 | AB26: =+Y26*2.54 -> 10.16
A27: 9 | B27: 9 | C27: ODD CARTON | G27: 9 | M27: 9 | P27: 1 | Q27: 9 | R27: =+T27/P27 -> 1.06 | S27: =+U27/P27 -> 136 | T27: 1.06 | U27: 136 | V27: =Z27&"*"&AA27&"*"&AB27 -> 40.64*22.86*8.89 | W27: 16 | X27: 9 | Y27: 3.5 | Z27: =+W27*2.54 -> 40.64 | AA27: =+X27*2.54 -> 22.86 | AB27: =+Y27*2.54 -> 8.89
Z28: =+W28*2.54 -> 0 | AA28: =+X28*2.54 -> 0 | AB28: =+Y28*2.54 -> 0
A29: 10 | B29: 10 | D29: NESSG280 | E29: 001 BLACK | F29: 001 | G29: 36 | J29: 36 | P29: 1 | Q29: 36 | R29: =+T29/P29 -> 5.56 | S29: =+U29/P29 -> 6.42 | T29: 5.56 | U29: 6.42 | V29: =Z29&"*"&AA29&"*"&AB29 -> 50.8*43.18*13.97 | W29: 20 | X29: 17 | Y29: 5.5 | Z29: =+W29*2.54 -> 50.8 | AA29: =+X29*2.54 -> 43.18 | AB29: =+Y29*2.54 -> 13.97
A30: 11 | B30: 11 | C30: ODD CARTON | G30: 34 | I30: 34 | P30: 1 | Q30: 34 | R30: =+T30/P30 -> 4.84 | S30: =+U30/P30 -> 5.7 | T30: 4.84 | U30: 5.7 | V30: =Z30&"*"&AA30&"*"&AB30 -> 50.8*43.18*13.97 | W30: 20 | X30: 17 | Y30: 5.5 | Z30: =+W30*2.54 -> 50.8 | AA30: =+X30*2.54 -> 43.18 | AB30: =+Y30*2.54 -> 13.97
A31: 12 | B31: 12 | C31: ODD CARTON | G31: 28 | K31: 28 | P31: 1 | Q31: 28 | R31: =+T31/P31 -> 4.74 | S31: =+U31/P31 -> 5.6 | T31: 4.74 | U31: 5.6 | V31: =Z31&"*"&AA31&"*"&AB31 -> 50.8*43.18*13.97 | W31: 20 | X31: 17 | Y31: 5.5 | Z31: =+W31*2.54 -> 50.8 | AA31: =+X31*2.54 -> 43.18 | AB31: =+Y31*2.54 -> 13.97
A32: 13 | B32: 13 | C32: ODD CARTON | G32: 13 | L32: 13 | P32: 1 | Q32: 13 | R32: =+T32/P32 -> 1.93 | S32: =+U32/P32 -> 2.78 | T32: 1.93 | U32: 2.78 | V32: =Z32&"*"&AA32&"*"&AB32 -> 43.18*25.4*11.43 | W32: 17 | X32: 10 | Y32: 4.5 | Z32: =+W32*2.54 -> 43.18 | AA32: =+X32*2.54 -> 25.4 | AB32: =+Y32*2.54 -> 11.43
A33: Master box 14-16 | C33: Master box | W33: 19 | X33: 11 | Y33: 8.5 | Z33: =+W33*2.54 -> 48.26 | AA33: =+X33*2.54 -> 27.94 | AB33: =+Y33*2.54 -> 21.59
A34: 14 | B34: 14 | C34: Small box | G34: 4 | H34: 4 | P34: 1 | Q34: 4 | R34: =+T34/P34 -> 0.52 | S34: =+U34/P34 -> 0.8 | T34: 0.52 | U34: 0.8 | V34: =Z34&"*"&AA34&"*"&AB34 -> 25.4*22.86*8.89 | W34: 10 | X34: 9 | Y34: 3.5 | Z34: =+W34*2.54 -> 25.4 | AA34: =+X34*2.54 -> 22.86 | AB34: =+Y34*2.54 -> 8.89
A35: 15 | B35: 15 | C35: Small box | G35: 3 | J35: 3 | Q35: 3 | T35: 0.44 | U35: 0.72 | V35: =Z35&"*"&AA35&"*"&AB35 -> 25.4*22.86*8.89 | W35: 10 | X35: 9 | Y35: 3.5 | Z35: =+W35*2.54 -> 25.4 | AA35: =+X35*2.54 -> 22.86 | AB35: =+Y35*2.54 -> 8.89
A36: 16 | B36: 16 | C36: Small box | G36: 2 | M36: 2 | Q36: 2 | T36: 0.38 | U36: 0.66 | V36: =Z36&"*"&AA36&"*"&AB36 -> 25.4*22.86*8.89 | W36: 10 | X36: 9 | Y36: 3.5 | Z36: =+W36*2.54 -> 25.4 | AA36: =+X36*2.54 -> 22.86 | AB36: =+Y36*2.54 -> 8.89
Z37: =+W37*2.54 -> 0 | AA37: =+X37*2.54 -> 0 | AB37: =+Y37*2.54 -> 0
A38: 17 | B38: 17 | C38: ODD CARTON | D38: NESSG410 | E38: 440 MIDNIGHT NAVY | F38: 440 | G38: 19 | I38: 19 | P38: 1 | Q38: 19 | R38: =+T38/P38 -> 3.21 | S38: =+U38/P38 -> 3.76 | T38: 3.21 | U38: 3.76 | V38: =Z38&"*"&AA38&"*"&AB38 -> 40.64*36.83*15.24 | W38: 16 | X38: 14.5 | Y38: 6 | Z38: =+W38*2.54 -> 40.64 | AA38: =+X38*2.54 -> 36.83 | AB38: =+Y38*2.54 -> 15.24
A39: 18 | B39: 18 | C39: ODD CARTON | G39: 23 | J39: 23 | P39: 1 | Q39: 23 | R39: =+T39/P39 -> 4.08 | S39: =+U39/P39 -> 4.64 | T39: 4.08 | U39: 4.64 | V39: =Z39&"*"&AA39&"*"&AB39 -> 40.64*35.56*17.78 | W39: 16 | X39: 14 | Y39: 7 | Z39: =+W39*2.54 -> 40.64 | AA39: =+X39*2.54 -> 35.56 | AB39: =+Y39*2.54 -> 17.78
A40: 19 | B40: 19 | C40: ODD CARTON | G40: 16 | K40: 16 | P40: 1 | Q40: 16 | R40: =+T40/P40 -> 3.1 | S40: =+U40/P40 -> 3.8 | T40: 3.1 | U40: 3.8 | V40: =Z40&"*"&AA40&"*"&AB40 -> 46.99*40.64*15.24 | W40: 18.5 | X40: 16 | Y40: 6 | Z40: =+W40*2.54 -> 46.99 | AA40: =+X40*2.54 -> 40.64 | AB40: =+Y40*2.54 -> 15.24
A41: 20 | B41: 20 | C41: ODD CARTON | G41: 9 | L41: 9 | P41: 1 | Q41: 9 | R41: =+T41/P41 -> 1.85 | S41: =+U41/P41 -> 2.5 | T41: 1.85 | U41: 2.5 | V41: =Z41&"*"&AA41&"*"&AB41 -> 46.99*40.64*11.43 | W41: 18.5 | X41: 16 | Y41: 4.5 | Z41: =+W41*2.54 -> 46.99 | AA41: =+X41*2.54 -> 40.64 | AB41: =+Y41*2.54 -> 11.43
A42: Master box 21-22 | C42: Master box | W42: 19 | X42: 11 | Y42: 4.5 | Z42: =+W42*2.54 -> 48.26 | AA42: =+X42*2.54 -> 27.94 | AB42: =+Y42*2.54 -> 11.43
A43: 21 | B43: 21 | C43: Small box | G43: 2 | H43: 2 | P43: 1 | Q43: 2 | R43: =+T43/P43 -> 0.32 | S43: =+U43/P43 -> 0.52 | T43: 0.32 | U43: 0.52 | V43: =Z43&"*"&AA43&"*"&AB43 -> 22.86*22.86*7.62 | W43: 9 | X43: 9 | Y43: 3 | Z43: =+W43*2.54 -> 22.86 | AA43: =+X43*2.54 -> 22.86 | AB43: =+Y43*2.54 -> 7.62
A44: 22 | B44: 22 | C44: Small box | G44: 3 | M44: 3 | Q44: 3 | T44: 0.7 | U44: 0.9 | V44: =Z44&"*"&AA44&"*"&AB44 -> 22.86*22.86*7.62 | W44: 9 | X44: 9 | Y44: 3 | Z44: =+W44*2.54 -> 22.86 | AA44: =+X44*2.54 -> 22.86 | AB44: =+Y44*2.54 -> 7.62
Z45: =+W45*2.54 -> 0 | AA45: =+X45*2.54 -> 0 | AB45: =+Y45*2.54 -> 0
A46: 23 | B46: 23 | C46: ODD CARTON | D46: NESSG410 | E46: 655 DESERT PINK | F46: 655 | G46: 19 | I46: 19 | P46: 1 | Q46: 19 | R46: =+T46/P46 -> 3.21 | S46: =+U46/P46 -> 3.76 | T46: 3.21 | U46: 3.76 | V46: =Z46&"*"&AA46&"*"&AB46 -> 40.64*36.83*15.24 | W46: 16 | X46: 14.5 | Y46: 6 | Z46: =+W46*2.54 -> 40.64 | AA46: =+X46*2.54 -> 36.83 | AB46: =+Y46*2.54 -> 15.24
A47: 24 | B47: 24 | C47: ODD CARTON | G47: 23 | J47: 23 | P47: 1 | Q47: 23 | R47: =+T47/P47 -> 4.08 | S47: =+U47/P47 -> 4.64 | T47: 4.08 | U47: 4.64 | V47: =Z47&"*"&AA47&"*"&AB47 -> 40.64*35.56*17.78 | W47: 16 | X47: 14 | Y47: 7 | Z47: =+W47*2.54 -> 40.64 | AA47: =+X47*2.54 -> 35.56 | AB47: =+Y47*2.54 -> 17.78
A48: 25 | B48: 25 | C48: ODD CARTON | G48: 16 | K48: 16 | P48: 1 | Q48: 16 | R48: =+T48/P48 -> 3.1 | S48: =+U48/P48 -> 3.8 | T48: 3.1 | U48: 3.8 | V48: =Z48&"*"&AA48&"*"&AB48 -> 46.99*40.64*15.24 | W48: 18.5 | X48: 16 | Y48: 6 | Z48: =+W48*2.54 -> 46.99 | AA48: =+X48*2.54 -> 40.64 | AB48: =+Y48*2.54 -> 15.24
A49: 26 | B49: 26 | C49: ODD CARTON | G49: 9 | L49: 9 | P49: 1 | Q49: 9 | R49: =+T49/P49 -> 1.85 | S49: =+U49/P49 -> 2.5 | T49: 1.85 | U49: 2.5 | V49: =Z49&"*"&AA49&"*"&AB49 -> 46.99*40.64*11.43 | W49: 18.5 | X49: 16 | Y49: 4.5 | Z49: =+W49*2.54 -> 46.99 | AA49: =+X49*2.54 -> 40.64 | AB49: =+Y49*2.54 -> 11.43
A50: Master box 27-28 | C50: Master box | W50: 19 | X50: 11 | Y50: 4.5 | Z50: =+W50*2.54 -> 48.26 | AA50: =+X50*2.54 -> 27.94 | AB50: =+Y50*2.54 -> 11.43
A51: 27 | B51: 27 | C51: Small box | G51: 2 | H51: 2 | P51: 1 | Q51: 2 | R51: =+T51/P51 -> 0.32 | S51: =+U51/P51 -> 0.52 | T51: 0.32 | U51: 0.52 | V51: =Z51&"*"&AA51&"*"&AB51 -> 22.86*22.86*7.62 | W51: 9 | X51: 9 | Y51: 3 | Z51: =+W51*2.54 -> 22.86 | AA51: =+X51*2.54 -> 22.86 | AB51: =+Y51*2.54 -> 7.62
A52: 28 | B52: 28 | C52: Small box | G52: 3 | M52: 3 | Q52: 3 | T52: 0.7 | U52: 0.9 | V52: =Z52&"*"&AA52&"*"&AB52 -> 22.86*22.86*7.62 | W52: 9 | X52: 9 | Y52: 3 | Z52: =+W52*2.54 -> 22.86 | AA52: =+X52*2.54 -> 22.86 | AB52: =+Y52*2.54 -> 7.62
N56: =SUM(N19:N55) -> 0 | O56: =SUM(O19:O55) -> 0 | P56: =SUM(P19:P55) -> 24 | Q56: =SUM(Q19:Q55) -> 480 | T56: =SUM(T19:T55) -> 64.21 | U56: =SUM(U19:U55) -> 213.98
C59: CUSTOMER PO | D59: Style | E59: Color | F59: Color Code | G59: xs | H59: S | I59: M | J59: L | K59: XL | L59: XXL | P59: TOT CTNS | Q59: TOT PCS
C60: EV161 | D60: NESSG277 | E60: BLACK | F60: 001 | G60: 11 | H60: 54 | I60: 68 | J60: 49 | K60: 25 | L60: 9 | P60: 9 | Q60: 216 | W60: =+SUM(G60:K60) -> 207 | X60: =+Q60-W60 -> 9
C61: EV161 | D61: NESSG280 | E61: BLACK | F61: 001 | G61: 4 | H61: 34 | I61: 39 | J61: 28 | K61: 13 | L61: 2 | P61: 5 | Q61: 120
C62: EV161 | D62: NESSG410 | E62: MIDNIGHT NAVY | F62: 440 | G62: 2 | H62: 19 | I62: 23 | J62: 16 | K62: 9 | L62: 3 | P62: 5 | Q62: 72
C63: EV161 | D63: NESSG410 | E63: DESERT PINK | F63: 655 | G63: 2 | H63: 19 | I63: 23 | J63: 16 | K63: 9 | L63: 3 | P63: 5 | Q63: 72
J66: TOTAL | P66: =SUM(P60:P64) -> 24 | Q66: =SUM(Q60:Q64) -> 480

Sheet IRREGULAR SS PL EV161
A4: PACKING LIST
G5: PEI
A6: ISSUE TO : | D6: =+'[1]INVOICE 11'!C7 -> SUPREME INTERNATIONAL, LLC | G6: STYLE:
G7: LABEL
G8: P.O.:
G9: PCS
G10: SIZES
A12: PAYMENT: T/C | G12: MADE IN
A13: PO NO: | B13: EV161 | G13: C# UP
A14: CUSTOMER PO.: | D14: =+B13 -> EV161
A15: INVOICE NO: | C15: =+'INVOICE 94'!M2 -> 7726477
A16: Detail Breakdown
A18: CASE FROM-TO | C18: REMARKS | D18: Style | E18: Color Name | F18: Color code | G18: Units/case | H18: xs | I18: S | J18: M | K18: L | L18: XL | M18: XXL | N18: 6 | O18: 6X | P18: TOT CTNS | Q18: TOT PCS | R18: NW | S18: GW | T18: TTL NW | U18: TTL GW | V18: CARTON SIZE ( CM)
A19: 1 | B19: 1 | D19: NESSG277 | E19: 001 BLACK | F19: 001 | G19: 36 | I19: 36 | P19: 1 | Q19: 36 | R19: =+T19/P19 -> 2.94 | S19: =+U19/P19 -> 3.64 | T19: 2.94 | U19: 3.64 | V19: =Z19&"*"&AA19&"*"&AB19 -> 40.64*38.1*11.43 | W19: 16 | X19: 15 | Y19: 4.5 | Z19: =+W19*2.54 -> 40.64 | AA19: =+X19*2.54 -> 38.1 | AB19: =+Y19*2.54 -> 11.43
A20: 2 | B20: 2 | G20: 36 | J20: 36 | P20: 1 | Q20: 36 | R20: =+T20/P20 -> 3.14 | S20: =+U20/P20 -> 3.84 | T20: 3.14 | U20: 3.84 | V20: =Z20&"*"&AA20&"*"&AB20 -> 40.64*38.1*11.43 | W20: 16 | X20: 15 | Y20: 4.5 | Z20: =+W20*2.54 -> 40.64 | AA20: =+X20*2.54 -> 38.1 | AB20: =+Y20*2.54 -> 11.43
A21: 3 | B21: 3 | G21: 36 | K21: 36 | P21: 1 | Q21: 36 | R21: =+T21/P21 -> 3.6 | S21: =+U21/P21 -> 4.32 | T21: 3.6 | U21: 4.32 | V21: =Z21&"*"&AA21&"*"&AB21 -> 40.64*38.1*13.97 | W21: 16 | X21: 15 | Y21: 5.5 | Z21: =+W21*2.54 -> 40.64 | AA21: =+X21*2.54 -> 38.1 | AB21: =+Y21*2.54 -> 13.97
A22: 4 | B22: 4 | C22: ODD CARTON | G22: 11 | H22: 11 | P22: 1 | Q22: 11 | R22: =+T22/P22 -> 0.68 | S22: =+U22/P22 -> 1.18 | T22: 0.68 | U22: 1.18 | V22: =Z22&"*"&AA22&"*"&AB22 -> 40.64*22.86*8.89 | W22: 16 | X22: 9 | Y22: 3.5 | Z22: =+W22*2.54 -> 40.64 | AA22: =+X22*2.54 -> 22.86 | AB22: =+Y22*2.54 -> 8.89
A23: 5 | B23: 5 | C23: ODD CARTON | G23: 18 | I23: 18 | P23: 1 | Q23: 18 | R23: =+T23/P23 -> 1.32 | S23: =+U23/P23 -> 1.84 | T23: 1.32 | U23: 1.84 | V23: =Z23&"*"&AA23&"*"&AB23 -> 40.64*22.86*11.43 | W23: 16 | X23: 9 | Y23: 4.5 | Z23: =+W23*2.54 -> 40.64 | AA23: =+X23*2.54 -> 22.86 | AB23: =+Y23*2.54 -> 11.43
A24: 6 | B24: 6 | C24: ODD CARTON | G24: 32 | J24: 32 | P24: 1 | Q24: 32 | R24: =+T24/P24 -> 2.6 | S24: =+U24/P24 -> 3.3 | T24: 2.6 | U24: 3.3 | V24: =Z24&"*"&AA24&"*"&AB24 -> 40.64*39.37*10.16 | W24: 16 | X24: 15.5 | Y24: 4 | Z24: =+W24*2.54 -> 40.64 | AA24: =+X24*2.54 -> 39.37 | AB24: =+Y24*2.54 -> 10.16
A25: 7 | B25: 7 | C25: ODD CARTON | G25: 13 | K25: 13 | P25: 1 | Q25: 13 | R25: =+T25/P25 -> 1.3 | S25: =+U25/P25 -> 1.6 | T25: 1.3 | U25: 1.6 | V25: =Z25&"*"&AA25&"*"&AB25 -> 40.64*22.86*8.89 | W25: 16 | X25: 9 | Y25: 3.5 | Z25: =+W25*2.54 -> 40.64 | AA25: =+X25*2.54 -> 22.86 | AB25: =+Y25*2.54 -> 8.89
A26: 8 | B26: 8 | C26: ODD CARTON | G26: 25 | L26: 25 | P26: 1 | Q26: 25 | R26: =+T26/P26 -> 2.64 | S26: =+U26/P26 -> 3.34 | T26: 2.64 | U26: 3.34 | V26: =Z26&"*"&AA26&"*"&AB26 -> 40.64*39.37*10.16 | W26: 16 | X26: 15.5 | Y26: 4 | Z26: =+W26*2.54 -> 40.64 | AA26: =+X26*2.54 -> 39.37 | AB26: =+Y26*2.54 -> 10.16
A27: 9 | B27: 9 | C27: ODD CARTON | G27: 9 | M27: 9 | P27: 1 | Q27: 9 | R27: =+T27/P27 -> 1.06 | S27: =+U27/P27 -> 136 | T27: 1.06 | U27: 136 | V27: =Z27&"*"&AA27&"*"&AB27 -> 40.64*22.86*8.89 | W27: 16 | X27: 9 | Y27: 3.5 | Z27: =+W27*2.54 -> 40.64 | AA27: =+X27*2.54 -> 22.86 | AB27: =+Y27*2.54 -> 8.89
Z28: =+W28*2.54 -> 0 | AA28: =+X28*2.54 -> 0 | AB28: =+Y28*2.54 -> 0
A29: 10 | B29: 10 | D29: NESSG280 | E29: 001 BLACK | F29: 001 | G29: 36 | J29: 36 | P29: 1 | Q29: 36 | R29: =+T29/P29 -> 5.56 | S29: =+U29/P29 -> 6.42 | T29: 5.56 | U29: 6.42 | V29: =Z29&"*"&AA29&"*"&AB29 -> 50.8*43.18*13.97 | W29: 20 | X29: 17 | Y29: 5.5 | Z29: =+W29*2.54 -> 50.8 | AA29: =+X29*2.54 -> 43.18 | AB29: =+Y29*2.54 -> 13.97
A30: 11 | B30: 11 | C30: ODD CARTON | G30: 34 | I30: 34 | P30: 1 | Q30: 34 | R30: =+T30/P30 -> 4.84 | S30: =+U30/P30 -> 5.7 | T30: 4.84 | U30: 5.7 | V30: =Z30&"*"&AA30&"*"&AB30 -> 50.8*43.18*13.97 | W30: 20 | X30: 17 | Y30: 5.5 | Z30: =+W30*2.54 -> 50.8 | AA30: =+X30*2.54 -> 43.18 | AB30: =+Y30*2.54 -> 13.97
A31: 12 | B31: 12 | C31: ODD CARTON | G31: 28 | K31: 28 | P31: 1 | Q31: 28 | R31: =+T31/P31 -> 4.74 | S31: =+U31/P31 -> 5.6 | T31: 4.74 | U31: 5.6 | V31: =Z31&"*"&AA31&"*"&AB31 -> 50.8*43.18*13.97 | W31: 20 | X31: 17 | Y31: 5.5 | Z31: =+W31*2.54 -> 50.8 | AA31: =+X31*2.54 -> 43.18 | AB31: =+Y31*2.54 -> 13.97
A32: 13 | B32: 13 | C32: ODD CARTON | G32: 13 | L32: 13 | P32: 1 | Q32: 13 | R32: =+T32/P32 -> 1.93 | S32: =+U32/P32 -> 2.78 | T32: 1.93 | U32: 2.78 | V32: =Z32&"*"&AA32&"*"&AB32 -> 43.18*25.4*11.43 | W32: 17 | X32: 10 | Y32: 4.5 | Z32: =+W32*2.54 -> 43.18 | AA32: =+X32*2.54 -> 25.4 | AB32: =+Y32*2.54 -> 11.43
A33: Master box 14-16 | C33: Master box | W33: 19 | X33: 11 | Y33: 8.5 | Z33: =+W33*2.54 -> 48.26 | AA33: =+X33*2.54 -> 27.94 | AB33: =+Y33*2.54 -> 21.59
A34: 14 | B34: 14 | C34: Small box | G34: 4 | H34: 4 | P34: 1 | Q34: 4 | R34: =+T34/P34 -> 0.52 | S34: =+U34/P34 -> 0.8 | T34: 0.52 | U34: 0.8 | V34: =Z34&"*"&AA34&"*"&AB34 -> 25.4*22.86*8.89 | W34: 10 | X34: 9 | Y34: 3.5 | Z34: =+W34*2.54 -> 25.4 | AA34: =+X34*2.54 -> 22.86 | AB34: =+Y34*2.54 -> 8.89
A35: 15 | B35: 15 | C35: Small box | G35: 3 | J35: 3 | P35: 1 | Q35: 3 | T35: 0.44 | U35: 0.72 | V35: =Z35&"*"&AA35&"*"&AB35 -> 25.4*22.86*8.89 | W35: 10 | X35: 9 | Y35: 3.5 | Z35: =+W35*2.54 -> 25.4 | AA35: =+X35*2.54 -> 22.86 | AB35: =+Y35*2.54 -> 8.89
A36: 16 | B36: 16 | C36: Small box | G36: 2 | M36: 2 | P36: 1 | Q36: 2 | T36: 0.38 | U36: 0.66 | V36: =Z36&"*"&AA36&"*"&AB36 -> 25.4*22.86*8.89 | W36: 10 | X36: 9 | Y36: 3.5 | Z36: =+W36*2.54 -> 25.4 | AA36: =+X36*2.54 -> 22.86 | AB36: =+Y36*2.54 -> 8.89
Z37: =+W37*2.54 -> 0 | AA37: =+X37*2.54 -> 0 | AB37: =+Y37*2.54 -> 0
A38: 17 | B38: 17 | C38: ODD CARTON | D38: NESSG410 | E38: 440 MIDNIGHT NAVY | F38: 440 | G38: 19 | I38: 19 | P38: 1 | Q38: 19 | R38: =+T38/P38 -> 3.21 | S38: =+U38/P38 -> 3.76 | T38: 3.21 | U38: 3.76 | V38: =Z38&"*"&AA38&"*"&AB38 -> 40.64*36.83*15.24 | W38: 16 | X38: 14.5 | Y38: 6 | Z38: =+W38*2.54 -> 40.64 | AA38: =+X38*2.54 -> 36.83 | AB38: =+Y38*2.54 -> 15.24
A39: 18 | B39: 18 | C39: ODD CARTON | G39: 23 | J39: 23 | P39: 1 | Q39: 23 | R39: =+T39/P39 -> 4.08 | S39: =+U39/P39 -> 4.64 | T39: 4.08 | U39: 4.64 | V39: =Z39&"*"&AA39&"*"&AB39 -> 40.64*35.56*17.78 | W39: 16 | X39: 14 | Y39: 7 | Z39: =+W39*2.54 -> 40.64 | AA39: =+X39*2.54 -> 35.56 | AB39: =+Y39*2.54 -> 17.78
A40: 19 | B40: 19 | C40: ODD CARTON | G40: 16 | K40: 16 | P40: 1 | Q40: 16 | R40: =+T40/P40 -> 3.1 | S40: =+U40/P40 -> 3.8 | T40: 3.1 | U40: 3.8 | V40: =Z40&"*"&AA40&"*"&AB40 -> 46.99*40.64*15.24 | W40: 18.5 | X40: 16 | Y40: 6 | Z40: =+W40*2.54 -> 46.99 | AA40: =+X40*2.54 -> 40.64 | AB40: =+Y40*2.54 -> 15.24
A41: 20 | B41: 20 | C41: ODD CARTON | G41: 9 | L41: 9 | P41: 1 | Q41: 9 | R41: =+T41/P41 -> 1.85 | S41: =+U41/P41 -> 2.5 | T41: 1.85 | U41: 2.5 | V41: =Z41&"*"&AA41&"*"&AB41 -> 46.99*40.64*11.43 | W41: 18.5 | X41: 16 | Y41: 4.5 | Z41: =+W41*2.54 -> 46.99 | AA41: =+X41*2.54 -> 40.64 | AB41: =+Y41*2.54 -> 11.43
A42: Master box 21-22 | C42: Master box | W42: 19 | X42: 11 | Y42: 4.5 | Z42: =+W42*2.54 -> 48.26 | AA42: =+X42*2.54 -> 27.94 | AB42: =+Y42*2.54 -> 11.43
A43: 21 | B43: 21 | C43: Small box | G43: 2 | H43: 2 | P43: 1 | Q43: 2 | R43: =+T43/P43 -> 0.32 | S43: =+U43/P43 -> 0.52 | T43: 0.32 | U43: 0.52 | V43: =Z43&"*"&AA43&"*"&AB43 -> 22.86*22.86*7.62 | W43: 9 | X43: 9 | Y43: 3 | Z43: =+W43*2.54 -> 22.86 | AA43: =+X43*2.54 -> 22.86 | AB43: =+Y43*2.54 -> 7.62
A44: 22 | B44: 22 | C44: Small box | G44: 3 | M44: 3 | P44: 1 | Q44: 3 | T44: 0.7 | U44: 0.9 | V44: =Z44&"*"&AA44&"*"&AB44 -> 22.86*22.86*7.62 | W44: 9 | X44: 9 | Y44: 3 | Z44: =+W44*2.54 -> 22.86 | AA44: =+X44*2.54 -> 22.86 | AB44: =+Y44*2.54 -> 7.62
Z45: =+W45*2.54 -> 0 | AA45: =+X45*2.54 -> 0 | AB45: =+Y45*2.54 -> 0
A46: 23 | B46: 23 | C46: ODD CARTON | D46: NESSG410 | E46: 655 DESERT PINK | F46: 655 | G46: 19 | I46: 19 | P46: 1 | Q46: 19 | R46: =+T46/P46 -> 3.21 | S46: =+U46/P46 -> 3.76 | T46: 3.21 | U46: 3.76 | V46: =Z46&"*"&AA46&"*"&AB46 -> 40.64*36.83*15.24 | W46: 16 | X46: 14.5 | Y46: 6 | Z46: =+W46*2.54 -> 40.64 | AA46: =+X46*2.54 -> 36.83 | AB46: =+Y46*2.54 -> 15.24
A47: 24 | B47: 24 | C47: ODD CARTON | G47: 23 | J47: 23 | P47: 1 | Q47: 23 | R47: =+T47/P47 -> 4.08 | S47: =+U47/P47 -> 4.64 | T47: 4.08 | U47: 4.64 | V47: =Z47&"*"&AA47&"*"&AB47 -> 40.64*35.56*17.78 | W47: 16 | X47: 14 | Y47: 7 | Z47: =+W47*2.54 -> 40.64 | AA47: =+X47*2.54 -> 35.56 | AB47: =+Y47*2.54 -> 17.78
A48: 25 | B48: 25 | C48: ODD CARTON | G48: 16 | K48: 16 | P48: 1 | Q48: 16 | R48: =+T48/P48 -> 3.1 | S48: =+U48/P48 -> 3.8 | T48: 3.1 | U48: 3.8 | V48: =Z48&"*"&AA48&"*"&AB48 -> 46.99*40.64*15.24 | W48: 18.5 | X48: 16 | Y48: 6 | Z48: =+W48*2.54 -> 46.99 | AA48: =+X48*2.54 -> 40.64 | AB48: =+Y48*2.54 -> 15.24
A49: 26 | B49: 26 | C49: ODD CARTON | G49: 9 | L49: 9 | P49: 1 | Q49: 9 | R49: =+T49/P49 -> 1.85 | S49: =+U49/P49 -> 2.5 | T49: 1.85 | U49: 2.5 | V49: =Z49&"*"&AA49&"*"&AB49 -> 46.99*40.64*11.43 | W49: 18.5 | X49: 16 | Y49: 4.5 | Z49: =+W49*2.54 -> 46.99 | AA49: =+X49*2.54 -> 40.64 | AB49: =+Y49*2.54 -> 11.43
A50: Master box 27-28 | C50: Master box | W50: 19 | X50: 11 | Y50: 4.5 | Z50: =+W50*2.54 -> 48.26 | AA50: =+X50*2.54 -> 27.94 | AB50: =+Y50*2.54 -> 11.43
A51: 27 | B51: 27 | C51: Small box | G51: 2 | H51: 2 | P51: 1 | Q51: 2 | R51: =+T51/P51 -> 0.32 | S51: =+U51/P51 -> 0.52 | T51: 0.32 | U51: 0.52 | V51: =Z51&"*"&AA51&"*"&AB51 -> 22.86*22.86*7.62 | W51: 9 | X51: 9 | Y51: 3 | Z51: =+W51*2.54 -> 22.86 | AA51: =+X51*2.54 -> 22.86 | AB51: =+Y51*2.54 -> 7.62
A52: 28 | B52: 28 | C52: Small box | G52: 3 | M52: 3 | P52: 1 | Q52: 3 | T52: 0.7 | U52: 0.9 | V52: =Z52&"*"&AA52&"*"&AB52 -> 22.86*22.86*7.62 | W52: 9 | X52: 9 | Y52: 3 | Z52: =+W52*2.54 -> 22.86 | AA52: =+X52*2.54 -> 22.86 | AB52: =+Y52*2.54 -> 7.62
N56: =SUM(N19:N55) -> 0 | O56: =SUM(O19:O55) -> 0 | P56: =SUM(P19:P55) -> 28 | Q56: =SUM(Q19:Q55) -> 480 | T56: =SUM(T19:T55) -> 64.21 | U56: =SUM(U19:U55) -> 213.98
C59: CUSTOMER PO | D59: Style | E59: Color | F59: Color Code | G59: xs | H59: S | I59: M | J59: L | K59: XL | L59: XXL | P59: TOT CTNS | Q59: TOT PCS
C60: EV161 | D60: NESSG277 | E60: BLACK | F60: 001 | G60: 11 | H60: 54 | I60: 68 | J60: 49 | K60: 25 | L60: 9 | P60: 9 | Q60: 216 | W60: =+SUM(G60:K60) -> 207 | X60: =+Q60-W60 -> 9
C61: EV161 | D61: NESSG280 | E61: BLACK | F61: 001 | G61: 4 | H61: 34 | I61: 39 | J61: 28 | K61: 13 | L61: 2 | P61: 7 | Q61: 120
C62: EV161 | D62: NESSG410 | E62: MIDNIGHT NAVY | F62: 440 | G62: 2 | H62: 19 | I62: 23 | J62: 16 | K62: 9 | L62: 3 | P62: 6 | Q62: 72
C63: EV161 | D63: NESSG410 | E63: DESERT PINK | F63: 655 | G63: 2 | H63: 19 | I63: 23 | J63: 16 | K63: 9 | L63: 3 | P63: 6 | Q63: 72
J66: TOTAL | P66: =SUM(P60:P64) -> 28 | Q66: =SUM(Q60:Q64) -> 480

Sheet FK245
A1: B'LAO SPORT COMPANY LIMITED
A2: Lot CN 37B, Zone C, Phong Dien Industrial Zone,
A3: Phong Thu Ward, Phong Dien Town, Hue City, Vietnam
A5: DETAIL BREAKDOWN - By MASTER BOX
A6: PO# | B6: FK245
A7: CTNS: | B7: =+L19 -> 6
A9: STYLE | B9: COLOR | C9: COLOR CODE | D9: CASE FROM- TO | F9: Units/case | G9: xs | H9: S | I9: M | J9: L | K9: XL | L9: TOT CTNS | M9: TOT PCS | N9: GW | O9: DIM
A10: NESSG277 | B10: 001 BLACK | C10: 001 | D10: 1 | E10: 1 | F10: 24 | G10: 24 | L10: 1 | M10: 24 | N10: 2.58 | O10: =+V10 -> 40.64*38.1*8.89 | P10: 16 | Q10: 15 | R10: 3.5 | S10: =+P10*2.54 -> 40.64 | T10: =+Q10*2.54 -> 38.1 | U10: =+R10*2.54 -> 8.89 | V10: =S10&"*"&T10&"*"&U10 -> 40.64*38.1*8.89
A11: NESSG277 | B11: 001 BLACK | C11: 001 | D11: 2 | E11: 2 | F11: 24 | H11: 24 | L11: 1 | M11: 24 | N11: 2.74 | O11: =+V11 -> 40.64*38.1*8.89 | P11: 16 | Q11: 15 | R11: 3.5 | S11: =+P11*2.54 -> 40.64 | T11: =+Q11*2.54 -> 38.1 | U11: =+R11*2.54 -> 8.89 | V11: =S11&"*"&T11&"*"&U11 -> 40.64*38.1*8.89
A12: NESSG277 | B12: 001 BLACK | C12: 001 | D12: 3 | E12: 3 | F12: 24 | I12: 24 | L12: 1 | M12: 24 | N12: 2.86 | O12: =+V12 -> 40.64*38.1*8.89 | P12: 16 | Q12: 15 | R12: 3.5 | S12: =+P12*2.54 -> 40.64 | T12: =+Q12*2.54 -> 38.1 | U12: =+R12*2.54 -> 8.89 | V12: =S12&"*"&T12&"*"&U12 -> 40.64*38.1*8.89
L13: 3 | M13: 72 | N13: 8.18 | S13: =+P13*2.54 -> 0 | T13: =+Q13*2.54 -> 0 | U13: =+R13*2.54 -> 0 | V13: =S13&"*"&T13&"*"&U13 -> 0*0*0
A14: NESSG278 | B14: 001 BLACK | C14: 001 | D14: 4 | E14: 4 | F14: 24 | G14: 24 | L14: 1 | M14: 24 | N14: 2.46 | O14: =+V14 -> 40.64*38.1*13.97 | P14: 16 | Q14: 15 | R14: 5.5 | S14: =+P14*2.54 -> 40.64 | T14: =+Q14*2.54 -> 38.1 | U14: =+R14*2.54 -> 13.97 | V14: =S14&"*"&T14&"*"&U14 -> 40.64*38.1*13.97
A15: NESSG278 | B15: 001 BLACK | C15: 001 | D15: 5 | E15: 5 | F15: 24 | H15: 24 | L15: 1 | M15: 24 | N15: 2.6 | O15: =+V15 -> 40.64*38.1*13.97 | P15: 16 | Q15: 15 | R15: 5.5 | S15: =+P15*2.54 -> 40.64 | T15: =+Q15*2.54 -> 38.1 | U15: =+R15*2.54 -> 13.97 | V15: =S15&"*"&T15&"*"&U15 -> 40.64*38.1*13.97
A16: NESSG278 | B16: 001 BLACK | C16: 001 | D16: 6 | E16: 6 | F16: 24 | I16: 24 | L16: 1 | M16: 24 | N16: 2.76 | O16: =+V16 -> 40.64*38.1*13.97 | P16: 16 | Q16: 15 | R16: 5.5 | S16: =+P16*2.54 -> 40.64 | T16: =+Q16*2.54 -> 38.1 | U16: =+R16*2.54 -> 13.97 | V16: =S16&"*"&T16&"*"&U16 -> 40.64*38.1*13.97
L17: 3 | M17: 72 | N17: 7.82 | S17: =+P17*2.54 -> 0 | T17: =+Q17*2.54 -> 0 | U17: =+R17*2.54 -> 0 | V17: =S17&"*"&T17&"*"&U17 -> 0*0*0
L19: =+L17+L13 -> 6 | M19: =+M17+M13 -> 144 | N19: =+N17+N13 -> 16

Sheet PLS FK245
A1: PACKING LIST - By MASTER BOX
A2: SUMMARY BREAKDOWN
A4: PO# | B4: =+'FK245'!B6 -> FK245
A5: CTNS: | B5: =+I10 -> 6
A6: STYLE | B6: COLOR | C6: COLOR CODE | D6: xs | E6: S | F6: M | G6: L | H6: XL | I6: TOT CTNS | J6: TOT PCS
A7: NESSG277 | B7: BLACK | C7: 001 | D7: 24 | E7: 24 | F7: 24 | I7: 3 | J7: 72 | K7: =+SUM(D7:H7) -> 72 | L7: =+K7-J7 -> 0
A8: NESSG278 | B8: BLACK | C8: 001 | D8: 24 | E8: 24 | F8: 24 | I8: 3 | J8: 72 | K8: =+SUM(D8:H8) -> 72 | L8: =+K8-J8 -> 0
A10: TOTAL | I10: =SUM(I7:I9) -> 6 | J10: =SUM(J7:J9) -> 144
A11: Carton Specs & Shipment Specs :
A12: Purchase Order: | B12: =+B4 -> FK245 | C12: GRAND TOTAL | D12: SIGNED BY:
A13: Total cartons: | B13: =+C13 -> 6 | C13: =+I10 -> 6
A14: Total Gross Wt:(kgs) | B14: =+C14/$B$13 -> 2.6666667 | C14: 16
A15: Total Net Wt:(kgs) | B15: =+C15/$B$13 -> 2.1166667 | C15: 12.7
A16: Total Net Net Wt:(kgs)
A17: Empty carton Wt
A18: CMB: | B18: =+C18/$B$13 -> 0.01836 | C18: 0.11016
A19: Carton Dimensions:
A20: CM
N26: =SUM(N10:N25) -> 0
B286: -52 | C286: -39
B287: -52 | C287: -39
B288: -52 | C288: -39
B289: -52 | C289: -39
B290: -52 | C290: -39
B291: -52 | C291: -39
B292: -52 | C292: -39
A293: TOTAL: | C293: -39
B294: -52 | C294: -39
B296: -52 | C296: -39
B297: -52 | C297: -39
B298: -52 | C298: -39
B299: -52 | C299: -39
B300: -52 | C300: -39
B301: -52 | C301: -39
B302: -52 | C302: -39
B304: 0 | C304: 0
A311: TOTAL:
A312: GRAND TOTAL:

Sheet SOLID PL GU113
A4: PACKING LIST
G5: PEI
A6: ISSUE TO : | D6: =+'[1]INVOICE 11'!C7 -> SUPREME INTERNATIONAL, LLC | G6: STYLE:
G7: LABEL
G8: P.O.:
G9: PCS
G10: SIZES
A12: PAYMENT: T/C | G12: MADE IN
A13: PO NO: | B13: GU113 | G13: C# UP
A14: CUSTOMER PO.: | D14: =+B13 -> GU113
A15: INVOICE NO: | C15: =+'INVOICE 94'!M2 -> 7726477
A16: Detail Breakdown
A18: CASE FROM-TO | C18: REMARKS | D18: Style | E18: Color Name | F18: Color code | G18: Units/case | H18: xs | I18: S | J18: M | K18: L | L18: XL | M18: XXL | N18: 6 | O18: 6X | P18: TOT CTNS | Q18: TOT PCS | R18: NW | S18: GW | T18: TTL NW | U18: TTL GW | V18: CARTON SIZE ( CM)
V19: =Z19&"*"&AA19&"*"&AB19 -> 43.18*25.4*21.59 | W19: 17 | X19: 10 | Y19: 8.5 | Z19: =+W19*2.54 -> 43.18 | AA19: =+X19*2.54 -> 25.4 | AB19: =+Y19*2.54 -> 21.59
A20: 1 | B20: 1 | C20: Small box | D20: NESSG729 | E20: 001 BLACK | F20: 001 | G20: 10 | H20: 10 | P20: 1 | Q20: 10 | R20: =+T20/P20 -> 0.84 | S20: =+U20/P20 -> 1.26 | T20: 0.84 | U20: 1.26 | V20: =Z20&"*"&AA20&"*"&AB20 -> 38.1*22.86*10.16 | W20: 15 | X20: 9 | Y20: 4 | Z20: =+W20*2.54 -> 38.1 | AA20: =+X20*2.54 -> 22.86 | AB20: =+Y20*2.54 -> 10.16
A21: 2 | B21: 2 | C21: Small box | G21: 6 | K21: 6 | Q21: 6 | V21: =Z21&"*"&AA21&"*"&AB21 -> 22.86*22.86*8.89 | W21: 9 | X21: 9 | Y21: 3.5 | Z21: =+W21*2.54 -> 22.86 | AA21: =+X21*2.54 -> 22.86 | AB21: =+Y21*2.54 -> 8.89
A22: 3 | B22: 3 | G22: 17 | I22: 17 | P22: 1 | Q22: 17 | R22: =+T22/P22 -> 1.92 | S22: =+U22/P22 -> 2.44 | T22: 1.92 | U22: 2.44 | V22: =Z22&"*"&AA22&"*"&AB22 -> 38.1*38.1*7.62 | W22: 15 | X22: 15 | Y22: 3 | Z22: =+W22*2.54 -> 38.1 | AA22: =+X22*2.54 -> 38.1 | AB22: =+Y22*2.54 -> 7.62
A23: 4 | B23: 4 | G23: 15 | J23: 15 | P23: 1 | Q23: 15 | R23: =+T23/P23 -> 1.88 | S23: =+U23/P23 -> 2.4 | T23: 1.88 | U23: 2.4 | V23: =Z23&"*"&AA23&"*"&AB23 -> 38.1*38.1*7.62 | W23: 15 | X23: 15 | Y23: 3 | Z23: =+W23*2.54 -> 38.1 | AA23: =+X23*2.54 -> 38.1 | AB23: =+Y23*2.54 -> 7.62
N26: =SUM(N20:N25) -> 0 | O26: =SUM(O20:O25) -> 0 | P26: =SUM(P20:P25) -> 3 | Q26: =SUM(Q20:Q25) -> 48 | T26: =SUM(T20:T25) -> 4.64 | U26: =SUM(U20:U25) -> 6.1
C29: CUSTOMER PO | D29: Style | E29: Color | F29: Color Code | G29: xs | H29: S | I29: M | J29: L | K29: XL | L29: XXL | P29: TOT CTNS | Q29: TOT PCS
C30: GU113 | D30: NESSG729 | E30: BLACK | F30: 001 | G30: 10 | H30: 6 | I30: 17 | J30: 15 | P30: 3 | Q30: 48 | W30: =+SUM(G30:K30) -> 48 | X30: =+Q30-W30 -> 0
J33: TOTAL | P33: =SUM(P30:P31) -> 3 | Q33: =SUM(Q30:Q31) -> 48

Sheet IRREGULAR SS PL GU113
A4: PACKING LIST
G5: PEI
A6: ISSUE TO : | D6: =+'[1]INVOICE 11'!C7 -> SUPREME INTERNATIONAL, LLC | G6: STYLE:
G7: LABEL
G8: P.O.:
G9: PCS
G10: SIZES
A12: PAYMENT: T/C | G12: MADE IN
A13: PO NO: | B13: GU113 | G13: C# UP
A14: CUSTOMER PO.: | D14: =+B13 -> GU113
A15: INVOICE NO: | C15: =+'INVOICE 94'!M2 -> 7726477
A16: Detail Breakdown
A18: CASE FROM-TO | C18: REMARKS | D18: Style | E18: Color Name | F18: Color code | G18: Units/case | H18: xs | I18: S | J18: M | K18: L | L18: XL | M18: XXL | N18: 6 | O18: 6X | P18: TOT CTNS | Q18: TOT PCS | R18: NW | S18: GW | T18: TTL NW | U18: TTL GW | V18: CARTON SIZE ( CM)
V19: =Z19&"*"&AA19&"*"&AB19 -> 43.18*25.4*21.59 | W19: 17 | X19: 10 | Y19: 8.5 | Z19: =+W19*2.54 -> 43.18 | AA19: =+X19*2.54 -> 25.4 | AB19: =+Y19*2.54 -> 21.59
A20: 1 | B20: 1 | C20: Small box | D20: NESSG729 | E20: 001 BLACK | F20: 001 | G20: 10 | H20: 10 | P20: 1 | Q20: 10 | R20: =+T20/P20 -> 0.84 | S20: =+U20/P20 -> 1.26 | T20: 0.84 | U20: 1.26 | V20: =Z20&"*"&AA20&"*"&AB20 -> 38.1*22.86*10.16 | W20: 15 | X20: 9 | Y20: 4 | Z20: =+W20*2.54 -> 38.1 | AA20: =+X20*2.54 -> 22.86 | AB20: =+Y20*2.54 -> 10.16
A21: 2 | B21: 2 | C21: Small box | G21: 6 | K21: 6 | P21: 1 | Q21: 6 | V21: =Z21&"*"&AA21&"*"&AB21 -> 22.86*22.86*8.89 | W21: 9 | X21: 9 | Y21: 3.5 | Z21: =+W21*2.54 -> 22.86 | AA21: =+X21*2.54 -> 22.86 | AB21: =+Y21*2.54 -> 8.89
A22: 3 | B22: 3 | G22: 17 | I22: 17 | P22: 1 | Q22: 17 | R22: =+T22/P22 -> 1.92 | S22: =+U22/P22 -> 2.44 | T22: 1.92 | U22: 2.44 | V22: =Z22&"*"&AA22&"*"&AB22 -> 38.1*38.1*7.62 | W22: 15 | X22: 15 | Y22: 3 | Z22: =+W22*2.54 -> 38.1 | AA22: =+X22*2.54 -> 38.1 | AB22: =+Y22*2.54 -> 7.62
A23: 4 | B23: 4 | G23: 15 | J23: 15 | P23: 1 | Q23: 15 | R23: =+T23/P23 -> 1.88 | S23: =+U23/P23 -> 2.4 | T23: 1.88 | U23: 2.4 | V23: =Z23&"*"&AA23&"*"&AB23 -> 38.1*38.1*7.62 | W23: 15 | X23: 15 | Y23: 3 | Z23: =+W23*2.54 -> 38.1 | AA23: =+X23*2.54 -> 38.1 | AB23: =+Y23*2.54 -> 7.62
N26: =SUM(N20:N25) -> 0 | O26: =SUM(O20:O25) -> 0 | P26: =SUM(P20:P25) -> 4 | Q26: =SUM(Q20:Q25) -> 48 | T26: =SUM(T20:T25) -> 4.64 | U26: =SUM(U20:U25) -> 6.1
C29: CUSTOMER PO | D29: Style | E29: Color | F29: Color Code | G29: xs | H29: S | I29: M | J29: L | K29: XL | L29: XXL | P29: TOT CTNS | Q29: TOT PCS
C30: GU113 | D30: NESSG729 | E30: BLACK | F30: 001 | G30: 10 | H30: 6 | I30: 17 | J30: 15 | P30: 4 | Q30: 48 | W30: =+SUM(G30:K30) -> 48 | X30: =+Q30-W30 -> 0
J33: TOTAL | P33: =SUM(P30:P31) -> 4 | Q33: =SUM(Q30:Q31) -> 48

Sheet SOLID PL GU117
A4: PACKING LIST
G5: PEI
A6: ISSUE TO : | D6: =+'[1]INVOICE 11'!C7 -> SUPREME INTERNATIONAL, LLC | G6: STYLE:
G7: LABEL
G8: P.O.:
G9: PCS
G10: SIZES
A12: PAYMENT: T/C | G12: MADE IN
A13: PO NO: | B13: GU117 | G13: C# UP
A14: CUSTOMER PO.: | D14: =+B13 -> GU117
A15: INVOICE NO: | C15: =+'INVOICE 94'!M2 -> 7726477
A16: Detail Breakdown
A18: CASE FROM-TO | C18: REMARKS | D18: Style | E18: Color Name | F18: Color code | G18: Units/case | H18: xs | I18: S | J18: M | K18: L | L18: XL | M18: XXL | N18: 6 | O18: 6X | P18: TOT CTNS | Q18: TOT PCS | R18: NW | S18: GW | T18: TTL NW | U18: TTL GW | V18: CARTON SIZE ( CM)
C19: Master box | V19: =Z19&"*"&AA19&"*"&AB19 -> 48.26*43.18*10.16 | W19: 19 | X19: 17 | Y19: 4 | Z19: =+W19*2.54 -> 48.26 | AA19: =+X19*2.54 -> 43.18 | AB19: =+Y19*2.54 -> 10.16
A20: 1 | B20: 1 | C20: Small box | D20: NESSG277 | E20: 001 BLACK | F20: 001 | G20: 12 | H20: 12 | P20: 1 | Q20: 12 | R20: =+T20/P20 -> 2.38 | S20: =+U20/P20 -> 2.9 | T20: 2.38 | U20: 2.9 | V20: =Z20&"*"&AA20&"*"&AB20 -> 40.64*22.86*8.89 | W20: 16 | X20: 9 | Y20: 3.5 | Z20: =+W20*2.54 -> 40.64 | AA20: =+X20*2.54 -> 22.86 | AB20: =+Y20*2.54 -> 8.89
A21: 2 | B21: 2 | C21: Small box | G21: 6 | K21: 6 | Q21: 6 | V21: =Z21&"*"&AA21&"*"&AB21 -> 22.86*22.86*7.62 | W21: 9 | X21: 9 | Y21: 3 | Z21: =+W21*2.54 -> 22.86 | AA21: =+X21*2.54 -> 22.86 | AB21: =+Y21*2.54 -> 7.62
A22: 3 | B22: 3 | G22: 15 | I22: 15 | P22: 1 | Q22: 15 | R22: =+T22/P22 -> 1.2 | S22: =+U22/P22 -> 1.6 | T22: 1.2 | U22: 1.6 | V22: =Z22&"*"&AA22&"*"&AB22 -> 40.64*22.86*11.43 | W22: 16 | X22: 9 | Y22: 4.5 | Z22: =+W22*2.54 -> 40.64 | AA22: =+X22*2.54 -> 22.86 | AB22: =+Y22*2.54 -> 11.43
A23: 4 | B23: 4 | G23: 15 | J23: 15 | P23: 1 | Q23: 15 | R23: =+T23/P23 -> 1.28 | S23: =+U23/P23 -> 1.68 | T23: 1.28 | U23: 1.68 | V23: =Z23&"*"&AA23&"*"&AB23 -> 40.64*22.86*11.43 | W23: 16 | X23: 9 | Y23: 4.5 | Z23: =+W23*2.54 -> 40.64 | AA23: =+X23*2.54 -> 22.86 | AB23: =+Y23*2.54 -> 11.43
N26: =SUM(N20:N25) -> 0 | O26: =SUM(O20:O25) -> 0 | P26: =SUM(P20:P25) -> 3 | Q26: =SUM(Q20:Q25) -> 48 | T26: =SUM(T20:T25) -> 4.86 | U26: =SUM(U20:U25) -> 6.18
C29: CUSTOMER PO | D29: Style | E29: Color | F29: Color Code | G29: xs | H29: S | I29: M | J29: L | K29: XL | L29: XXL | P29: TOT CTNS | Q29: TOT PCS
C30: GU117 | D30: NESSG277 | E30: BLACK | F30: 001 | G30: 10 | H30: 6 | I30: 17 | J30: 15 | P30: 3 | Q30: 48 | W30: =+SUM(G30:K30) -> 48 | X30: =+Q30-W30 -> 0
J33: TOTAL | P33: =SUM(P30:P31) -> 3 | Q33: =SUM(Q30:Q31) -> 48

Sheet IRREGULAR SS PL GU117
A4: PACKING LIST
G5: PEI
A6: ISSUE TO : | D6: =+'[1]INVOICE 11'!C7 -> SUPREME INTERNATIONAL, LLC | G6: STYLE:
G7: LABEL
G8: P.O.:
G9: PCS
G10: SIZES
A12: PAYMENT: T/C | G12: MADE IN
A13: PO NO: | B13: GU117 | G13: C# UP
A14: CUSTOMER PO.: | D14: =+B13 -> GU117
A15: INVOICE NO: | C15: =+'INVOICE 94'!M2 -> 7726477
A16: Detail Breakdown
A18: CASE FROM-TO | C18: REMARKS | D18: Style | E18: Color Name | F18: Color code | G18: Units/case | H18: xs | I18: S | J18: M | K18: L | L18: XL | M18: XXL | N18: 6 | O18: 6X | P18: TOT CTNS | Q18: TOT PCS | R18: NW | S18: GW | T18: TTL NW | U18: TTL GW | V18: CARTON SIZE ( CM)
C19: Master box | V19: =Z19&"*"&AA19&"*"&AB19 -> 48.26*43.18*10.16 | W19: 19 | X19: 17 | Y19: 4 | Z19: =+W19*2.54 -> 48.26 | AA19: =+X19*2.54 -> 43.18 | AB19: =+Y19*2.54 -> 10.16
A20: 1 | B20: 1 | C20: Small box | D20: NESSG277 | E20: 001 BLACK | F20: 001 | G20: 12 | H20: 12 | P20: 1 | Q20: 12 | R20: =+T20/P20 -> 2.38 | S20: =+U20/P20 -> 2.9 | T20: 2.38 | U20: 2.9 | V20: =Z20&"*"&AA20&"*"&AB20 -> 40.64*22.86*8.89 | W20: 16 | X20: 9 | Y20: 3.5 | Z20: =+W20*2.54 -> 40.64 | AA20: =+X20*2.54 -> 22.86 | AB20: =+Y20*2.54 -> 8.89
A21: 2 | B21: 2 | C21: Small box | G21: 6 | K21: 6 | P21: 1 | Q21: 6 | V21: =Z21&"*"&AA21&"*"&AB21 -> 22.86*22.86*7.62 | W21: 9 | X21: 9 | Y21: 3 | Z21: =+W21*2.54 -> 22.86 | AA21: =+X21*2.54 -> 22.86 | AB21: =+Y21*2.54 -> 7.62
A22: 3 | B22: 3 | G22: 15 | I22: 15 | P22: 1 | Q22: 15 | R22: =+T22/P22 -> 1.2 | S22: =+U22/P22 -> 1.6 | T22: 1.2 | U22: 1.6 | V22: =Z22&"*"&AA22&"*"&AB22 -> 40.64*22.86*11.43 | W22: 16 | X22: 9 | Y22: 4.5 | Z22: =+W22*2.54 -> 40.64 | AA22: =+X22*2.54 -> 22.86 | AB22: =+Y22*2.54 -> 11.43
A23: 4 | B23: 4 | G23: 15 | J23: 15 | P23: 1 | Q23: 15 | R23: =+T23/P23 -> 1.28 | S23: =+U23/P23 -> 1.68 | T23: 1.28 | U23: 1.68 | V23: =Z23&"*"&AA23&"*"&AB23 -> 40.64*22.86*11.43 | W23: 16 | X23: 9 | Y23: 4.5 | Z23: =+W23*2.54 -> 40.64 | AA23: =+X23*2.54 -> 22.86 | AB23: =+Y23*2.54 -> 11.43
N26: =SUM(N20:N25) -> 0 | O26: =SUM(O20:O25) -> 0 | P26: =SUM(P20:P25) -> 4 | Q26: =SUM(Q20:Q25) -> 48 | T26: =SUM(T20:T25) -> 4.86 | U26: =SUM(U20:U25) -> 6.18
C29: CUSTOMER PO | D29: Style | E29: Color | F29: Color Code | G29: xs | H29: S | I29: M | J29: L | K29: XL | L29: XXL | P29: TOT CTNS | Q29: TOT PCS
C30: GU117 | D30: NESSG277 | E30: BLACK | F30: 001 | G30: 10 | H30: 6 | I30: 17 | J30: 15 | P30: 4 | Q30: 48 | W30: =+SUM(G30:K30) -> 48 | X30: =+Q30-W30 -> 0
J33: TOTAL | P33: =SUM(P30:P31) -> 4 | Q33: =SUM(Q30:Q31) -> 48

Sheet SZ514
A1: B'LAO SPORT COMPANY LIMITED
A2: Lot CN 37B, Zone C, Phong Dien Industrial Zone,
A3: Phong Thu Ward, Phong Dien Town, Hue City, Vietnam
A5: DETAIL BREAKDOWN - By MASTER BOX
A6: PO# | B6: SZ514
A7: CTNS: | B7: =+L55 -> 37
A9: STYLE | B9: COLOR | C9: COLOR CODE | D9: CASE FROM- TO | F9: Units/case | G9: xs | H9: S | I9: M | J9: L | K9: XL | L9: TOT CTNS | M9: TOT PCS | N9: GW | O9: DIM
A10: NESSB711 | B10: 001 BLACK | C10: 001 | D10: 1 | E10: 1 | F10: 24 | G10: 24 | L10: 1 | M10: 24 | N10: 2.94 | O10: =+V10 -> 50.8*43.18*8.89 | P10: 20 | Q10: 17 | R10: 3.5 | S10: =+P10*2.54 -> 50.8 | T10: =+Q10*2.54 -> 43.18 | U10: =+R10*2.54 -> 8.89 | V10: =S10&"*"&T10&"*"&U10 -> 50.8*43.18*8.89
A11: NESSB711 | B11: 001 BLACK | C11: 001 | D11: 2 | E11: 2 | F11: 24 | H11: 24 | L11: 1 | M11: 24 | N11: 3.14 | O11: =+V11 -> 50.8*43.18*8.89 | P11: 20 | Q11: 17 | R11: 3.5 | S11: =+P11*2.54 -> 50.8 | T11: =+Q11*2.54 -> 43.18 | U11: =+R11*2.54 -> 8.89 | V11: =S11&"*"&T11&"*"&U11 -> 50.8*43.18*8.89
A12: NESSB711 | B12: 001 BLACK | C12: 001 | D12: 3 | E12: 3 | F12: 24 | I12: 24 | L12: 1 | M12: 24 | N12: 3.34 | O12: =+V12 -> 50.8*43.18*8.89 | P12: 20 | Q12: 17 | R12: 3.5 | S12: =+P12*2.54 -> 50.8 | T12: =+Q12*2.54 -> 43.18 | U12: =+R12*2.54 -> 8.89 | V12: =S12&"*"&T12&"*"&U12 -> 50.8*43.18*8.89
A13: NESSB711 | B13: 001 BLACK | C13: 001 | D13: 4 | E13: 4 | F13: 24 | J13: 24 | L13: 1 | M13: 24 | N13: 3.62 | O13: =+V13 -> 50.8*43.18*10.16 | P13: 20 | Q13: 17 | R13: 4 | S13: =+P13*2.54 -> 50.8 | T13: =+Q13*2.54 -> 43.18 | U13: =+R13*2.54 -> 10.16 | V13: =S13&"*"&T13&"*"&U13 -> 50.8*43.18*10.16
A14: NESSB711 | B14: 001 BLACK | C14: 001 | D14: 5 | E14: 5 | F14: 24 | K14: 24 | L14: 1 | M14: 24 | N14: 3.88 | O14: =+V14 -> 50.8*43.18*10.16 | P14: 20 | Q14: 17 | R14: 4 | S14: =+P14*2.54 -> 50.8 | T14: =+Q14*2.54 -> 43.18 | U14: =+R14*2.54 -> 10.16 | V14: =S14&"*"&T14&"*"&U14 -> 50.8*43.18*10.16
L15: 5 | M15: 120 | N15: 16.92 | S15: =+P15*2.54 -> 0 | T15: =+Q15*2.54 -> 0 | U15: =+R15*2.54 -> 0 | V15: =S15&"*"&T15&"*"&U15 -> 0*0*0
A16: NESSG278 | B16: 001 BLACK | C16: 001 | D16: 6 | E16: 6 | F16: 24 | G16: 24 | L16: 1 | M16: 24 | N16: 2.46 | O16: =+V16 -> 40.64*38.1*13.97 | P16: 16 | Q16: 15 | R16: 5.5 | S16: =+P16*2.54 -> 40.64 | T16: =+Q16*2.54 -> 38.1 | U16: =+R16*2.54 -> 13.97 | V16: =S16&"*"&T16&"*"&U16 -> 40.64*38.1*13.97
A17: NESSG278 | B17: 001 BLACK | C17: 001 | D17: 7 | E17: 7 | F17: 24 | H17: 24 | L17: 1 | M17: 24 | N17: 2.6 | O17: =+V17 -> 40.64*38.1*13.97 | P17: 16 | Q17: 15 | R17: 5.5 | S17: =+P17*2.54 -> 40.64 | T17: =+Q17*2.54 -> 38.1 | U17: =+R17*2.54 -> 13.97 | V17: =S17&"*"&T17&"*"&U17 -> 40.64*38.1*13.97
A18: NESSG278 | B18: 001 BLACK | C18: 001 | D18: 8 | E18: 8 | F18: 24 | I18: 24 | L18: 1 | M18: 24 | N18: 2.76 | O18: =+V18 -> 40.64*38.1*13.97 | P18: 16 | Q18: 15 | R18: 5.5 | S18: =+P18*2.54 -> 40.64 | T18: =+Q18*2.54 -> 38.1 | U18: =+R18*2.54 -> 13.97 | V18: =S18&"*"&T18&"*"&U18 -> 40.64*38.1*13.97
A19: NESSG278 | B19: 001 BLACK | C19: 001 | D19: 9 | E19: 9 | F19: 24 | J19: 24 | L19: 1 | M19: 24 | N19: 2.94 | O19: =+V19 -> 40.64*38.1*13.97 | P19: 16 | Q19: 15 | R19: 5.5 | S19: =+P19*2.54 -> 40.64 | T19: =+Q19*2.54 -> 38.1 | U19: =+R19*2.54 -> 13.97 | V19: =S19&"*"&T19&"*"&U19 -> 40.64*38.1*13.97
A20: NESSG278 | B20: 001 BLACK | C20: 001 | D20: 10 | E20: 10 | F20: 24 | K20: 24 | L20: 1 | M20: 24 | N20: 3.18 | O20: =+V20 -> 40.64*38.1*13.97 | P20: 16 | Q20: 15 | R20: 5.5 | S20: =+P20*2.54 -> 40.64 | T20: =+Q20*2.54 -> 38.1 | U20: =+R20*2.54 -> 13.97 | V20: =S20&"*"&T20&"*"&U20 -> 40.64*38.1*13.97
L21: 5 | M21: 120 | N21: 13.94 | S21: =+P21*2.54 -> 0 | T21: =+Q21*2.54 -> 0 | U21: =+R21*2.54 -> 0 | V21: =S21&"*"&T21&"*"&U21 -> 0*0*0
A22: NESSG280 | B22: 001 BLACK | C22: 001 | D22: 11 | E22: 11 | F22: 36 | H22: 36 | L22: 1 | M22: 36 | N22: 6.02 | O22: =+V22 -> 50.8*43.18*13.97 | P22: 20 | Q22: 17 | R22: 5.5 | S22: =+P22*2.54 -> 50.8 | T22: =+Q22*2.54 -> 43.18 | U22: =+R22*2.54 -> 13.97 | V22: =S22&"*"&T22&"*"&U22 -> 50.8*43.18*13.97
A23: NESSG280 | B23: 001 BLACK | C23: 001 | D23: 12 | E23: 12 | F23: 36 | I23: 36 | L23: 1 | M23: 36 | N23: 6.32 | O23: =+V23 -> 50.8*43.18*13.97 | P23: 20 | Q23: 17 | R23: 5.5 | S23: =+P23*2.54 -> 50.8 | T23: =+Q23*2.54 -> 43.18 | U23: =+R23*2.54 -> 13.97 | V23: =S23&"*"&T23&"*"&U23 -> 50.8*43.18*13.97
A24: NESSG280 | B24: 001 BLACK | C24: 001 | D24: 13 | E24: 13 | F24: 24 | G24: 24 | L24: 1 | M24: 24 | N24: 3.85 | O24: =+V24 -> 50.8*43.18*10.16 | P24: 20 | Q24: 17 | R24: 4 | S24: =+P24*2.54 -> 50.8 | T24: =+Q24*2.54 -> 43.18 | U24: =+R24*2.54 -> 10.16 | V24: =S24&"*"&T24&"*"&U24 -> 50.8*43.18*10.16
A25: NESSG280 | B25: 001 BLACK | C25: 001 | D25: 14 | E25: 14 | F25: 12 | H25: 12 | L25: 1 | M25: 12 | N25: 2.06 | O25: =+V25 -> 43.18*25.4*8.89 | P25: 17 | Q25: 10 | R25: 3.5 | S25: =+P25*2.54 -> 43.18 | T25: =+Q25*2.54 -> 25.4 | U25: =+R25*2.54 -> 8.89 | V25: =S25&"*"&T25&"*"&U25 -> 43.18*25.4*8.89
A26: NESSG280 | B26: 001 BLACK | C26: 001 | D26: 15 | E26: 15 | F26: 12 | I26: 12 | L26: 1 | M26: 12 | N26: 2.16 | O26: =+V26 -> 43.18*25.4*8.89 | P26: 17 | Q26: 10 | R26: 3.5 | S26: =+P26*2.54 -> 43.18 | T26: =+Q26*2.54 -> 25.4 | U26: =+R26*2.54 -> 8.89 | V26: =S26&"*"&T26&"*"&U26 -> 43.18*25.4*8.89
A27: NESSG280 | B27: 001 BLACK | C27: 001 | D27: 16 | E27: 16 | F27: 24 | J27: 24 | L27: 1 | M27: 24 | N27: 4.84 | O27: =+V27 -> 50.8*43.18*11.43 | P27: 20 | Q27: 17 | R27: 4.5 | S27: =+P27*2.54 -> 50.8 | T27: =+Q27*2.54 -> 43.18 | U27: =+R27*2.54 -> 11.43 | V27: =S27&"*"&T27&"*"&U27 -> 50.8*43.18*11.43
A28: NESSG280 | B28: 001 BLACK | C28: 001 | D28: 17 | E28: 17 | F28: 24 | K28: 24 | L28: 1 | M28: 24 | N28: 5.04 | O28: =+V28 -> 50.8*43.18*11.43 | P28: 20 | Q28: 17 | R28: 4.5 | S28: =+P28*2.54 -> 50.8 | T28: =+Q28*2.54 -> 43.18 | U28: =+R28*2.54 -> 11.43 | V28: =S28&"*"&T28&"*"&U28 -> 50.8*43.18*11.43
L29: 7 | M29: 168 | N29: 30.29 | S29: =+P29*2.54 -> 0 | T29: =+Q29*2.54 -> 0 | U29: =+R29*2.54 -> 0 | V29: =S29&"*"&T29&"*"&U29 -> 0*0*0
A30: NESSG410 | B30: 440 MIDNIGHT NAVY | C30: 440 | D30: 18 | E30: 18 | F30: 24 | G30: 24 | L30: 1 | M30: 24 | N30: 4.3 | O30: =+V30 -> 40.64*35.56*17.78 | P30: 16 | Q30: 14 | R30: 7 | S30: =+P30*2.54 -> 40.64 | T30: =+Q30*2.54 -> 35.56 | U30: =+R30*2.54 -> 17.78 | V30: =S30&"*"&T30&"*"&U30 -> 40.64*35.56*17.78
A31: NESSG410 | B31: 440 MIDNIGHT NAVY | C31: 440 | D31: 19 | E31: 19 | F31: 24 | H31: 24 | L31: 1 | M31: 24 | N31: 4.5 | O31: =+V31 -> 40.64*35.56*17.78 | P31: 16 | Q31: 14 | R31: 7 | S31: =+P31*2.54 -> 40.64 | T31: =+Q31*2.54 -> 35.56 | U31: =+R31*2.54 -> 17.78 | V31: =S31&"*"&T31&"*"&U31 -> 40.64*35.56*17.78
A32: NESSG410 | B32: 440 MIDNIGHT NAVY | C32: 440 | D32: 20 | E32: 20 | F32: 24 | I32: 24 | L32: 1 | M32: 24 | N32: 4.86 | O32: =+V32 -> 40.64*35.56*17.78 | P32: 16 | Q32: 14 | R32: 7 | S32: =+P32*2.54 -> 40.64 | T32: =+Q32*2.54 -> 35.56 | U32: =+R32*2.54 -> 17.78 | V32: =S32&"*"&T32&"*"&U32 -> 40.64*35.56*17.78
A33: NESSG410 | B33: 440 MIDNIGHT NAVY | C33: 440 | D33: 21 | E33: 21 | F33: 24 | J33: 24 | L33: 1 | M33: 24 | N33: 5.06 | O33: =+V33 -> 45.72*40.64*20.32 | P33: 18 | Q33: 16 | R33: 8 | S33: =+P33*2.54 -> 45.72 | T33: =+Q33*2.54 -> 40.64 | U33: =+R33*2.54 -> 20.32 | V33: =S33&"*"&T33&"*"&U33 -> 45.72*40.64*20.32
A34: NESSG410 | B34: 440 MIDNIGHT NAVY | C34: 440 | D34: 22 | E34: 22 | F34: 24 | K34: 24 | L34: 1 | M34: 24 | N34: 5.26 | O34: =+V34 -> 45.72*40.64*20.32 | P34: 18 | Q34: 16 | R34: 8 | S34: =+P34*2.54 -> 45.72 | T34: =+Q34*2.54 -> 40.64 | U34: =+R34*2.54 -> 20.32 | V34: =S34&"*"&T34&"*"&U34 -> 45.72*40.64*20.32
L35: 5 | M35: 120 | N35: 23.98 | S35: =+P35*2.54 -> 0 | T35: =+Q35*2.54 -> 0 | U35: =+R35*2.54 -> 0 | V35: =S35&"*"&T35&"*"&U35 -> 0*0*0
A36: NESSG410 | B36: 655 DESERT PINK | C36: 655 | D36: 23 | E36: 23 | F36: 24 | G36: 24 | L36: 1 | M36: 24 | N36: 4.3 | O36: =+V36 -> 40.64*35.56*17.78 | P36: 16 | Q36: 14 | R36: 7 | S36: =+P36*2.54 -> 40.64 | T36: =+Q36*2.54 -> 35.56 | U36: =+R36*2.54 -> 17.78 | V36: =S36&"*"&T36&"*"&U36 -> 40.64*35.56*17.78
A37: NESSG410 | B37: 655 DESERT PINK | C37: 655 | D37: 24 | E37: 24 | F37: 24 | H37: 24 | L37: 1 | M37: 24 | N37: 4.5 | O37: =+V37 -> 40.64*35.56*17.78 | P37: 16 | Q37: 14 | R37: 7 | S37: =+P37*2.54 -> 40.64 | T37: =+Q37*2.54 -> 35.56 | U37: =+R37*2.54 -> 17.78 | V37: =S37&"*"&T37&"*"&U37 -> 40.64*35.56*17.78
A38: NESSG410 | B38: 655 DESERT PINK | C38: 655 | D38: 25 | E38: 25 | F38: 24 | I38: 24 | L38: 1 | M38: 24 | N38: 4.86 | O38: =+V38 -> 40.64*35.56*17.78 | P38: 16 | Q38: 14 | R38: 7 | S38: =+P38*2.54 -> 40.64 | T38: =+Q38*2.54 -> 35.56 | U38: =+R38*2.54 -> 17.78 | V38: =S38&"*"&T38&"*"&U38 -> 40.64*35.56*17.78
A39: NESSG410 | B39: 655 DESERT PINK | C39: 655 | D39: 26 | E39: 26 | F39: 24 | J39: 24 | L39: 1 | M39: 24 | N39: 5.06 | O39: =+V39 -> 45.72*40.64*20.32 | P39: 18 | Q39: 16 | R39: 8 | S39: =+P39*2.54 -> 45.72 | T39: =+Q39*2.54 -> 40.64 | U39: =+R39*2.54 -> 20.32 | V39: =S39&"*"&T39&"*"&U39 -> 45.72*40.64*20.32
A40: NESSG410 | B40: 655 DESERT PINK | C40: 655 | D40: 27 | E40: 27 | F40: 24 | K40: 24 | L40: 1 | M40: 24 | N40: 5.26 | O40: =+V40 -> 45.72*40.64*20.32 | P40: 18 | Q40: 16 | R40: 8 | S40: =+P40*2.54 -> 45.72 | T40: =+Q40*2.54 -> 40.64 | U40: =+R40*2.54 -> 20.32 | V40: =S40&"*"&T40&"*"&U40 -> 45.72*40.64*20.32
L41: 5 | M41: 120 | N41: 23.98 | S41: =+P41*2.54 -> 0 | T41: =+Q41*2.54 -> 0 | U41: =+R41*2.54 -> 0 | V41: =S41&"*"&T41&"*"&U41 -> 0*0*0
A42: NESSG758 | B42: 385 ENERGY | C42: 385 | D42: 28 | E42: 28 | F42: 24 | G42: 24 | L42: 1 | M42: 24 | N42: 3.24 | O42: =+V42 -> 50.8*43.18*8.89 | P42: 20 | Q42: 17 | R42: 3.5 | S42: =+P42*2.54 -> 50.8 | T42: =+Q42*2.54 -> 43.18 | U42: =+R42*2.54 -> 8.89 | V42: =S42&"*"&T42&"*"&U42 -> 50.8*43.18*8.89
A43: NESSG758 | B43: 385 ENERGY | C43: 385 | D43: 29 | E43: 29 | F43: 24 | H43: 24 | L43: 1 | M43: 24 | N43: 3.44 | O43: =+V43 -> 50.8*43.18*8.89 | P43: 20 | Q43: 17 | R43: 3.5 | S43: =+P43*2.54 -> 50.8 | T43: =+Q43*2.54 -> 43.18 | U43: =+R43*2.54 -> 8.89 | V43: =S43&"*"&T43&"*"&U43 -> 50.8*43.18*8.89
A44: NESSG758 | B44: 385 ENERGY | C44: 385 | D44: 30 | E44: 30 | F44: 24 | I44: 24 | L44: 1 | M44: 24 | N44: 3.74 | O44: =+V44 -> 50.8*43.18*8.89 | P44: 20 | Q44: 17 | R44: 3.5 | S44: =+P44*2.54 -> 50.8 | T44: =+Q44*2.54 -> 43.18 | U44: =+R44*2.54 -> 8.89 | V44: =S44&"*"&T44&"*"&U44 -> 50.8*43.18*8.89
A45: NESSG758 | B45: 385 ENERGY | C45: 385 | D45: 31 | E45: 31 | F45: 24 | J45: 24 | L45: 1 | M45: 24 | N45: 4.04 | O45: =+V45 -> 50.8*43.18*10.16 | P45: 20 | Q45: 17 | R45: 4 | S45: =+P45*2.54 -> 50.8 | T45: =+Q45*2.54 -> 43.18 | U45: =+R45*2.54 -> 10.16 | V45: =S45&"*"&T45&"*"&U45 -> 50.8*43.18*10.16
A46: NESSG758 | B46: 385 ENERGY | C46: 385 | D46: 32 | E46: 32 | F46: 24 | K46: 24 | L46: 1 | M46: 24 | N46: 4.46 | O46: =+V46 -> 50.8*43.18*10.16 | P46: 20 | Q46: 17 | R46: 4 | S46: =+P46*2.54 -> 50.8 | T46: =+Q46*2.54 -> 43.18 | U46: =+R46*2.54 -> 10.16 | V46: =S46&"*"&T46&"*"&U46 -> 50.8*43.18*10.16
L47: 5 | M47: 120 | N47: 18.92 | S47: =+P47*2.54 -> 0 | T47: =+Q47*2.54 -> 0 | U47: =+R47*2.54 -> 0 | V47: =S47&"*"&T47&"*"&U47 -> 0*0*0
A48: NESSG758 | B48: 655 DESERT PINK | C48: 655 | D48: 33 | E48: 33 | F48: 24 | G48: 24 | L48: 1 | M48: 24 | N48: 3.24 | O48: =+V48 -> 50.8*43.18*8.89 | P48: 20 | Q48: 17 | R48: 3.5 | S48: =+P48*2.54 -> 50.8 | T48: =+Q48*2.54 -> 43.18 | U48: =+R48*2.54 -> 8.89 | V48: =S48&"*"&T48&"*"&U48 -> 50.8*43.18*8.89
A49: NESSG758 | B49: 655 DESERT PINK | C49: 655 | D49: 34 | E49: 34 | F49: 24 | H49: 24 | L49: 1 | M49: 24 | N49: 3.44 | O49: =+V49 -> 50.8*43.18*8.89 | P49: 20 | Q49: 17 | R49: 3.5 | S49: =+P49*2.54 -> 50.8 | T49: =+Q49*2.54 -> 43.18 | U49: =+R49*2.54 -> 8.89 | V49: =S49&"*"&T49&"*"&U49 -> 50.8*43.18*8.89
A50: NESSG758 | B50: 655 DESERT PINK | C50: 655 | D50: 35 | E50: 35 | F50: 24 | I50: 24 | L50: 1 | M50: 24 | N50: 3.74 | O50: =+V50 -> 50.8*43.18*8.89 | P50: 20 | Q50: 17 | R50: 3.5 | S50: =+P50*2.54 -> 50.8 | T50: =+Q50*2.54 -> 43.18 | U50: =+R50*2.54 -> 8.89 | V50: =S50&"*"&T50&"*"&U50 -> 50.8*43.18*8.89
A51: NESSG758 | B51: 655 DESERT PINK | C51: 655 | D51: 36 | E51: 36 | F51: 24 | J51: 24 | L51: 1 | M51: 24 | N51: 4.04 | O51: =+V51 -> 50.8*43.18*10.16 | P51: 20 | Q51: 17 | R51: 4 | S51: =+P51*2.54 -> 50.8 | T51: =+Q51*2.54 -> 43.18 | U51: =+R51*2.54 -> 10.16 | V51: =S51&"*"&T51&"*"&U51 -> 50.8*43.18*10.16
A52: NESSG758 | B52: 655 DESERT PINK | C52: 655 | D52: 37 | E52: 37 | F52: 24 | K52: 24 | L52: 1 | M52: 24 | N52: 4.46 | O52: =+V52 -> 50.8*43.18*10.16 | P52: 20 | Q52: 17 | R52: 4 | S52: =+P52*2.54 -> 50.8 | T52: =+Q52*2.54 -> 43.18 | U52: =+R52*2.54 -> 10.16 | V52: =S52&"*"&T52&"*"&U52 -> 50.8*43.18*10.16
L53: 5 | M53: 120 | N53: 18.92 | S53: =+P53*2.54 -> 0 | T53: =+Q53*2.54 -> 0 | U53: =+R53*2.54 -> 0 | V53: =S53&"*"&T53&"*"&U53 -> 0*0*0
L55: =+L53+L47+L41+L35+L29+L21+L15 -> 37 | M55: =+M53+M47+M41+M35+M29+M21+M15 -> 888 | N55: =+N53+N47+N41+N35+N29+N21+N15 -> 146.95

Sheet PLS SZ514
A1: PACKING LIST - By MASTER BOX
A2: SUMMARY BREAKDOWN
A4: PO# | B4: =+'SZ514'!B6 -> SZ514
A5: CTNS: | B5: =+I15 -> 37
A6: STYLE | B6: COLOR | C6: COLOR CODE | D6: xs | E6: S | F6: M | G6: L | H6: XL | I6: TOT CTNS | J6: TOT PCS
A7: NESSB711 | B7: BLACK | C7: 001 | D7: 24 | E7: 24 | F7: 24 | G7: 24 | H7: 24 | I7: 5 | J7: 120 | K7: =+SUM(D7:H7) -> 120 | L7: =+K7-J7 -> 0
A8: NESSG278 | B8: BLACK | C8: 001 | D8: 24 | E8: 24 | F8: 24 | G8: 24 | H8: 24 | I8: 5 | J8: 120 | K8: =+SUM(D8:H8) -> 120 | L8: =+K8-J8 -> 0
A9: NESSG280 | B9: BLACK | C9: 001 | D9: 24 | E9: 48 | F9: 48 | G9: 24 | H9: 24 | I9: 7 | J9: 168 | K9: =+SUM(D9:H9) -> 168 | L9: =+K9-J9 -> 0
A10: NESSG410 | B10: MIDNIGHT NAVY | C10: 440 | D10: 24 | E10: 24 | F10: 24 | G10: 24 | H10: 24 | I10: 5 | J10: 120 | K10: =+SUM(D10:H10) -> 120 | L10: =+K10-J10 -> 0
A11: NESSG410 | B11: DESERT PINK | C11: 655 | D11: 24 | E11: 24 | F11: 24 | G11: 24 | H11: 24 | I11: 5 | J11: 120 | K11: =+SUM(D11:H11) -> 120 | L11: =+K11-J11 -> 0
A12: NESSG758 | B12: ENERGY | C12: 385 | D12: 24 | E12: 24 | F12: 24 | G12: 24 | H12: 24 | I12: 5 | J12: 120 | K12: =+SUM(D12:H12) -> 120 | L12: =+K12-J12 -> 0
A13: NESSG758 | B13: DESERT PINK | C13: 655 | D13: 24 | E13: 24 | F13: 24 | G13: 24 | H13: 24 | I13: 5 | J13: 120 | K13: =+SUM(D13:H13) -> 120 | L13: =+K13-J13 -> 0
A15: TOTAL | I15: =SUM(I7:I14) -> 37 | J15: =SUM(J7:J14) -> 888
A16: Carton Specs & Shipment Specs :
A17: Purchase Order: | B17: =+B4 -> SZ514 | C17: GRAND TOTAL | D17: SIGNED BY:
A18: Total cartons: | B18: =+C18 -> 37 | C18: =+I15 -> 37
A19: Total Gross Wt:(kgs) | B19: =+C19/$B$18 -> 3.9716216 | C19: 146.95
A20: Total Net Wt:(kgs) | B20: =+C20/$B$18 -> 3.2051351 | C20: 118.59
A21: Total Net Net Wt:(kgs)
A22: Empty carton Wt
A23: CMB: | B23: =+C23/$B$18 -> 0.024555351 | C23: 0.908548
A24: Carton Dimensions:
A25: CM
N31: =SUM(N15:N30) -> 0
B291: -52 | C291: -39
B292: -52 | C292: -39
B293: -52 | C293: -39
B294: -52 | C294: -39
B295: -52 | C295: -39
B296: -52 | C296: -39
B297: -52 | C297: -39
A298: TOTAL: | C298: -39
B299: -52 | C299: -39
B301: -52 | C301: -39
B302: -52 | C302: -39
B303: -52 | C303: -39
B304: -52 | C304: -39
B305: -52 | C305: -39
B306: -52 | C306: -39
B307: -52 | C307: -39
B309: 0 | C309: 0
A316: TOTAL:
A317: GRAND TOTAL:

Sheet SOLID PLWH88
A4: PACKING LIST
G5: PEI
A6: ISSUE TO : | D6: =+'[1]INVOICE 11'!C7 -> SUPREME INTERNATIONAL, LLC | G6: STYLE:
G7: LABEL
G8: P.O.:
G9: PCS
G10: SIZES
A12: PAYMENT: T/C | G12: MADE IN
A13: PO NO: | B13: WH88 | G13: C# UP
A14: CUSTOMER PO.: | D14: =+B13 -> WH88
A15: INVOICE NO: | C15: =+'INVOICE 94'!M2 -> 7726477
A16: Detail Breakdown
A18: CASE FROM-TO | C18: REMARKS | D18: Style | E18: Color Name | F18: Color code | G18: Units/case | H18: xs | I18: S | J18: M | K18: L | L18: XL | M18: XXL | N18: 6 | O18: 6X | P18: TOT CTNS | Q18: TOT PCS | R18: NW | S18: GW | T18: TTL NW | U18: TTL GW | V18: CARTON SIZE ( CM)
A19: Master box 1-3 | C19: Master box | W19: 19 | X19: 11 | Y19: 8.5 | Z19: =+W19*2.54 -> 48.26 | AA19: =+X19*2.54 -> 27.94 | AB19: =+Y19*2.54 -> 21.59
A20: 1 | B20: 1 | C20: Small box | D20: NESSB711 | E20: 385 ENERGY | F20: 385 | G20: 2 | H20: 2 | P20: 1 | Q20: 2 | R20: =+T20/P20 -> 0.22 | S20: =+U20/P20 -> 0.46 | T20: 0.22 | U20: 0.46 | V20: =Z20&"*"&AA20&"*"&AB20 -> 25.4*22.86*8.89 | W20: 10 | X20: 9 | Y20: 3.5 | Z20: =+W20*2.54 -> 25.4 | AA20: =+X20*2.54 -> 22.86 | AB20: =+Y20*2.54 -> 8.89
A21: 2 | B21: 2 | C21: Small box | G21: 5 | I21: 5 | Q21: 5 | T21: 0.54 | U21: 0.78 | V21: =Z21&"*"&AA21&"*"&AB21 -> 25.4*22.86*8.89 | W21: 10 | X21: 9 | Y21: 3.5 | Z21: =+W21*2.54 -> 25.4 | AA21: =+X21*2.54 -> 22.86 | AB21: =+Y21*2.54 -> 8.89
A22: 3 | B22: 3 | C22: Small box | G22: 7 | J22: 7 | Q22: 7 | T22: 0.8 | U22: 1.04 | V22: =Z22&"*"&AA22&"*"&AB22 -> 25.4*22.86*8.89 | W22: 10 | X22: 9 | Y22: 3.5 | Z22: =+W22*2.54 -> 25.4 | AA22: =+X22*2.54 -> 22.86 | AB22: =+Y22*2.54 -> 8.89
A23: Master box 4-5 | C23: Master box | W23: 19 | X23: 11 | Y23: 4.5 | Z23: =+W23*2.54 -> 48.26 | AA23: =+X23*2.54 -> 27.94 | AB23: =+Y23*2.54 -> 11.43
A24: 4 | B24: 4 | C24: Small box | G24: 6 | K24: 6 | P24: 1 | Q24: 6 | R24: =+T24/P24 -> 0.8 | S24: =+U24/P24 -> 1.04 | T24: 0.8 | U24: 1.04 | V24: =Z24&"*"&AA24&"*"&AB24 -> 25.4*22.86*8.89 | W24: 10 | X24: 9 | Y24: 3.5 | Z24: =+W24*2.54 -> 25.4 | AA24: =+X24*2.54 -> 22.86 | AB24: =+Y24*2.54 -> 8.89
A25: 5 | B25: 5 | C25: Small box | G25: 4 | L25: 4 | Q25: 4 | T25: 0.56 | U25: 0.8 | V25: =Z25&"*"&AA25&"*"&AB25 -> 25.4*22.86*8.89 | W25: 10 | X25: 9 | Y25: 3.5 | Z25: =+W25*2.54 -> 25.4 | AA25: =+X25*2.54 -> 22.86 | AB25: =+Y25*2.54 -> 8.89
Z26: =+W26*2.54 -> 0 | AA26: =+X26*2.54 -> 0 | AB26: =+Y26*2.54 -> 0
A27: Master box 6-8 | C27: Master box | W27: 19 | X27: 11 | Y27: 8.5 | Z27: =+W27*2.54 -> 48.26 | AA27: =+X27*2.54 -> 27.94 | AB27: =+Y27*2.54 -> 21.59
A28: 6 | B28: 6 | C28: Small box | D28: NESSB711 | E28: 655 DESERT PINK | F28: 655 | G28: 2 | H28: 2 | P28: 1 | Q28: 2 | R28: =+T28/P28 -> 0.22 | S28: =+U28/P28 -> 0.46 | T28: 0.22 | U28: 0.46 | V28: =Z28&"*"&AA28&"*"&AB28 -> 25.4*22.86*8.89 | W28: 10 | X28: 9 | Y28: 3.5 | Z28: =+W28*2.54 -> 25.4 | AA28: =+X28*2.54 -> 22.86 | AB28: =+Y28*2.54 -> 8.89
A29: 7 | B29: 7 | C29: Small box | G29: 5 | I29: 5 | Q29: 5 | T29: 0.54 | U29: 0.78 | V29: =Z29&"*"&AA29&"*"&AB29 -> 25.4*22.86*8.89 | W29: 10 | X29: 9 | Y29: 3.5 | Z29: =+W29*2.54 -> 25.4 | AA29: =+X29*2.54 -> 22.86 | AB29: =+Y29*2.54 -> 8.89
A30: 8 | B30: 8 | C30: Small box | G30: 7 | J30: 7 | Q30: 7 | T30: 0.8 | U30: 1.04 | V30: =Z30&"*"&AA30&"*"&AB30 -> 25.4*22.86*8.89 | W30: 10 | X30: 9 | Y30: 3.5 | Z30: =+W30*2.54 -> 25.4 | AA30: =+X30*2.54 -> 22.86 | AB30: =+Y30*2.54 -> 8.89
A31: Master box 9-10 | C31: Master box | W31: 19 | X31: 11 | Y31: 4.5 | Z31: =+W31*2.54 -> 48.26 | AA31: =+X31*2.54 -> 27.94 | AB31: =+Y31*2.54 -> 11.43
A32: 9 | B32: 9 | C32: Small box | G32: 6 | K32: 6 | P32: 1 | Q32: 6 | R32: =+T32/P32 -> 0.8 | S32: =+U32/P32 -> 1.04 | T32: 0.8 | U32: 1.04 | V32: =Z32&"*"&AA32&"*"&AB32 -> 25.4*22.86*8.89 | W32: 10 | X32: 9 | Y32: 3.5 | Z32: =+W32*2.54 -> 25.4 | AA32: =+X32*2.54 -> 22.86 | AB32: =+Y32*2.54 -> 8.89
A33: 10 | B33: 10 | C33: Small box | G33: 4 | L33: 4 | Q33: 4 | T33: 0.56 | U33: 0.8 | V33: =Z33&"*"&AA33&"*"&AB33 -> 25.4*22.86*8.89 | W33: 10 | X33: 9 | Y33: 3.5 | Z33: =+W33*2.54 -> 25.4 | AA33: =+X33*2.54 -> 22.86 | AB33: =+Y33*2.54 -> 8.89
Z34: =+W34*2.54 -> 0 | AA34: =+X34*2.54 -> 0 | AB34: =+Y34*2.54 -> 0
A35: Master box 11-13 | C35: Master box | W35: 10 | X35: 10 | Y35: 11.5 | Z35: =+W35*2.54 -> 25.4 | AA35: =+X35*2.54 -> 25.4 | AB35: =+Y35*2.54 -> 29.21
A36: 11 | B36: 11 | C36: Small box | D36: NESSG729 | E36: 001 BLACK | F36: 001 | G36: 2 | H36: 2 | P36: 1 | Q36: 2 | R36: =+T36/P36 -> 0.2 | S36: =+U36/P36 -> 0.44 | T36: 0.2 | U36: 0.44 | V36: =Z36&"*"&AA36&"*"&AB36 -> 22.86*22.86*8.89 | W36: 9 | X36: 9 | Y36: 3.5 | Z36: =+W36*2.54 -> 22.86 | AA36: =+X36*2.54 -> 22.86 | AB36: =+Y36*2.54 -> 8.89
A37: 12 | B37: 12 | C37: Small box | G37: 5 | I37: 5 | Q37: 5 | T37: 0 | U37: 0 | V37: =Z37&"*"&AA37&"*"&AB37 -> 22.86*22.86*8.89 | W37: 9 | X37: 9 | Y37: 3.5 | Z37: =+W37*2.54 -> 22.86 | AA37: =+X37*2.54 -> 22.86 | AB37: =+Y37*2.54 -> 8.89
A38: 13 | B38: 13 | C38: Small box | G38: 7 | J38: 7 | Q38: 7 | T38: 0 | U38: 0 | V38: =Z38&"*"&AA38&"*"&AB38 -> 22.86*22.86*8.89 | W38: 9 | X38: 9 | Y38: 3.5 | Z38: =+W38*2.54 -> 22.86 | AA38: =+X38*2.54 -> 22.86 | AB38: =+Y38*2.54 -> 8.89
A39: Master box 14-15 | C39: Master box | W39: 19 | X39: 11 | Y39: 4.5 | Z39: =+W39*2.54 -> 48.26 | AA39: =+X39*2.54 -> 27.94 | AB39: =+Y39*2.54 -> 11.43
A40: 14 | B40: 14 | C40: Small box | G40: 6 | K40: 6 | P40: 1 | Q40: 6 | R40: =+T40/P40 -> 0.78 | S40: =+U40/P40 -> 1.02 | T40: 0.78 | U40: 1.02 | V40: =Z40&"*"&AA40&"*"&AB40 -> 22.86*22.86*8.89 | W40: 9 | X40: 9 | Y40: 3.5 | Z40: =+W40*2.54 -> 22.86 | AA40: =+X40*2.54 -> 22.86 | AB40: =+Y40*2.54 -> 8.89
A41: 15 | B41: 15 | C41: Small box | G41: 4 | L41: 4 | Q41: 4 | T41: 0 | U41: 0 | V41: =Z41&"*"&AA41&"*"&AB41 -> 22.86*22.86*8.89 | W41: 9 | X41: 9 | Y41: 3.5 | Z41: =+W41*2.54 -> 22.86 | AA41: =+X41*2.54 -> 22.86 | AB41: =+Y41*2.54 -> 8.89
Z42: =+W42*2.54 -> 0 | AA42: =+X42*2.54 -> 0 | AB42: =+Y42*2.54 -> 0
A43: Master box 16-18 | C43: Master box | W43: 19 | X43: 11 | Y43: 8.5 | Z43: =+W43*2.54 -> 48.26 | AA43: =+X43*2.54 -> 27.94 | AB43: =+Y43*2.54 -> 21.59
A44: 16 | B44: 16 | C44: Small box | D44: NESSG758 | E44: 385 ENERGY | F44: 385 | G44: 2 | H44: 2 | P44: 1 | Q44: 2 | R44: =+T44/P44 -> 0.24 | S44: =+U44/P44 -> 0.48 | T44: 0.24 | U44: 0.48 | V44: =Z44&"*"&AA44&"*"&AB44 -> 25.4*22.86*8.89 | W44: 10 | X44: 9 | Y44: 3.5 | Z44: =+W44*2.54 -> 25.4 | AA44: =+X44*2.54 -> 22.86 | AB44: =+Y44*2.54 -> 8.89
A45: 17 | B45: 17 | C45: Small box | G45: 5 | I45: 5 | Q45: 5 | T45: 0 | U45: 0 | V45: =Z45&"*"&AA45&"*"&AB45 -> 25.4*22.86*8.89 | W45: 10 | X45: 9 | Y45: 3.5 | Z45: =+W45*2.54 -> 25.4 | AA45: =+X45*2.54 -> 22.86 | AB45: =+Y45*2.54 -> 8.89
A46: 18 | B46: 18 | C46: Small box | G46: 7 | J46: 7 | Q46: 7 | T46: 0 | U46: 0 | V46: =Z46&"*"&AA46&"*"&AB46 -> 25.4*22.86*8.89 | W46: 10 | X46: 9 | Y46: 3.5 | Z46: =+W46*2.54 -> 25.4 | AA46: =+X46*2.54 -> 22.86 | AB46: =+Y46*2.54 -> 8.89
A47: Master box 19-20 | C47: Master box | W47: 19 | X47: 11 | Y47: 4.5 | Z47: =+W47*2.54 -> 48.26 | AA47: =+X47*2.54 -> 27.94 | AB47: =+Y47*2.54 -> 11.43
A48: 19 | B48: 19 | C48: Small box | G48: 6 | K48: 6 | P48: 1 | Q48: 6 | R48: =+T48/P48 -> 0.84 | S48: =+U48/P48 -> 1.08 | T48: 0.84 | U48: 1.08 | V48: =Z48&"*"&AA48&"*"&AB48 -> 25.4*22.86*8.89 | W48: 10 | X48: 9 | Y48: 3.5 | Z48: =+W48*2.54 -> 25.4 | AA48: =+X48*2.54 -> 22.86 | AB48: =+Y48*2.54 -> 8.89
A49: 20 | B49: 20 | C49: Small box | G49: 4 | L49: 4 | Q49: 4 | T49: 0 | U49: 0 | V49: =Z49&"*"&AA49&"*"&AB49 -> 25.4*22.86*8.89 | W49: 10 | X49: 9 | Y49: 3.5 | Z49: =+W49*2.54 -> 25.4 | AA49: =+X49*2.54 -> 22.86 | AB49: =+Y49*2.54 -> 8.89
Z50: =+W50*2.54 -> 0 | AA50: =+X50*2.54 -> 0 | AB50: =+Y50*2.54 -> 0
A51: Master box 21-23 | C51: Master box | W51: 19 | X51: 11 | Y51: 8.5 | Z51: =+W51*2.54 -> 48.26 | AA51: =+X51*2.54 -> 27.94 | AB51: =+Y51*2.54 -> 21.59
A52: 21 | B52: 21 | C52: Small box | D52: NESSG758 | E52: 655 DESERT PINK | F52: 655 | G52: 2 | H52: 2 | P52: 1 | Q52: 2 | R52: =+T52/P52 -> 0.24 | S52: =+U52/P52 -> 0.48 | T52: 0.24 | U52: 0.48 | V52: =Z52&"*"&AA52&"*"&AB52 -> 25.4*22.86*8.89 | W52: 10 | X52: 9 | Y52: 3.5 | Z52: =+W52*2.54 -> 25.4 | AA52: =+X52*2.54 -> 22.86 | AB52: =+Y52*2.54 -> 8.89
A53: 22 | B53: 22 | C53: Small box | G53: 5 | I53: 5 | Q53: 5 | T53: 0 | U53: 0 | V53: =Z53&"*"&AA53&"*"&AB53 -> 25.4*22.86*8.89 | W53: 10 | X53: 9 | Y53: 3.5 | Z53: =+W53*2.54 -> 25.4 | AA53: =+X53*2.54 -> 22.86 | AB53: =+Y53*2.54 -> 8.89
A54: 23 | B54: 23 | C54: Small box | G54: 7 | J54: 7 | Q54: 7 | T54: 0 | U54: 0 | V54: =Z54&"*"&AA54&"*"&AB54 -> 25.4*22.86*8.89 | W54: 10 | X54: 9 | Y54: 3.5 | Z54: =+W54*2.54 -> 25.4 | AA54: =+X54*2.54 -> 22.86 | AB54: =+Y54*2.54 -> 8.89
A55: Master box 24-25 | C55: Master box | W55: 19 | X55: 11 | Y55: 4.5 | Z55: =+W55*2.54 -> 48.26 | AA55: =+X55*2.54 -> 27.94 | AB55: =+Y55*2.54 -> 11.43
A56: 24 | B56: 24 | C56: Small box | G56: 6 | K56: 6 | P56: 1 | Q56: 6 | R56: =+T56/P56 -> 0.84 | S56: =+U56/P56 -> 1.08 | T56: 0.84 | U56: 1.08 | V56: =Z56&"*"&AA56&"*"&AB56 -> 25.4*22.86*8.89 | W56: 10 | X56: 9 | Y56: 3.5 | Z56: =+W56*2.54 -> 25.4 | AA56: =+X56*2.54 -> 22.86 | AB56: =+Y56*2.54 -> 8.89
A57: 25 | B57: 25 | C57: Small box | G57: 4 | L57: 4 | Q57: 4 | T57: 0 | U57: 0 | V57: =Z57&"*"&AA57&"*"&AB57 -> 25.4*22.86*8.89 | W57: 10 | X57: 9 | Y57: 3.5 | Z57: =+W57*2.54 -> 25.4 | AA57: =+X57*2.54 -> 22.86 | AB57: =+Y57*2.54 -> 8.89
N60: =SUM(N20:N59) -> 0 | O60: =SUM(O20:O59) -> 0 | P60: =SUM(P20:P59) -> 10 | Q60: =SUM(Q20:Q59) -> 120 | T60: =SUM(T20:T59) -> 8.98 | U60: =SUM(U20:U59) -> 12.82
C63: CUSTOMER PO | D63: Style | E63: Color | F63: Color Code | G63: xs | H63: S | I63: M | J63: L | K63: XL | L63: XXL | P63: TOT CTNS | Q63: TOT PCS
C64: WH88 | D64: NESSB711 | E64: ENERGY | F64: 385 | G64: 2 | H64: 5 | I64: 7 | J64: 6 | K64: 4 | P64: 2 | Q64: 24 | W64: =+SUM(G64:K64) -> 24 | X64: =+Q64-W64 -> 0
C65: WH88 | D65: NESSB711 | E65: DESERT PINK | F65: 655 | G65: 2 | H65: 5 | I65: 7 | J65: 6 | K65: 4 | P65: 2 | Q65: 24
C66: WH88 | D66: NESSG729 | E66: BLACK | F66: 001 | G66: 2 | H66: 5 | I66: 7 | J66: 6 | K66: 4 | P66: 2 | Q66: 24
C67: WH88 | D67: NESSG758 | E67: ENERGY | F67: 385 | G67: 2 | H67: 5 | I67: 7 | J67: 6 | K67: 4 | P67: 2 | Q67: 24
C68: WH88 | D68: NESSG758 | E68: DESERT PINK | F68: 655 | G68: 2 | H68: 5 | I68: 7 | J68: 6 | K68: 4 | P68: 2 | Q68: 24
J71: TOTAL | P71: =SUM(P64:P69) -> 10 | Q71: =SUM(Q64:Q69) -> 120

Sheet IRREGULAR SS PL WH88
A4: PACKING LIST
G5: PEI
A6: ISSUE TO : | D6: =+'[1]INVOICE 11'!C7 -> SUPREME INTERNATIONAL, LLC | G6: STYLE:
G7: LABEL
G8: P.O.:
G9: PCS
G10: SIZES
A12: PAYMENT: T/C | G12: MADE IN
A13: PO NO: | B13: WH88 | G13: C# UP
A14: CUSTOMER PO.: | D14: =+B13 -> WH88
A15: INVOICE NO: | C15: =+'INVOICE 94'!M2 -> 7726477
A16: Detail Breakdown
A18: CASE FROM-TO | C18: REMARKS | D18: Style | E18: Color Name | F18: Color code | G18: Units/case | H18: xs | I18: S | J18: M | K18: L | L18: XL | M18: XXL | N18: 6 | O18: 6X | P18: TOT CTNS | Q18: TOT PCS | R18: NW | S18: GW | T18: TTL NW | U18: TTL GW | V18: CARTON SIZE ( CM)
A19: Master box 1-3 | C19: Master box | W19: 19 | X19: 11 | Y19: 8.5 | Z19: =+W19*2.54 -> 48.26 | AA19: =+X19*2.54 -> 27.94 | AB19: =+Y19*2.54 -> 21.59
A20: 1 | B20: 1 | C20: Small box | D20: NESSB711 | E20: 385 ENERGY | F20: 385 | G20: 2 | H20: 2 | P20: 1 | Q20: 2 | R20: =+T20/P20 -> 0.22 | S20: =+U20/P20 -> 0.46 | T20: 0.22 | U20: 0.46 | V20: =Z20&"*"&AA20&"*"&AB20 -> 25.4*22.86*8.89 | W20: 10 | X20: 9 | Y20: 3.5 | Z20: =+W20*2.54 -> 25.4 | AA20: =+X20*2.54 -> 22.86 | AB20: =+Y20*2.54 -> 8.89
A21: 2 | B21: 2 | C21: Small box | G21: 5 | I21: 5 | P21: 1 | Q21: 5 | T21: 0.54 | U21: 0.78 | V21: =Z21&"*"&AA21&"*"&AB21 -> 25.4*22.86*8.89 | W21: 10 | X21: 9 | Y21: 3.5 | Z21: =+W21*2.54 -> 25.4 | AA21: =+X21*2.54 -> 22.86 | AB21: =+Y21*2.54 -> 8.89
A22: 3 | B22: 3 | C22: Small box | G22: 7 | J22: 7 | P22: 1 | Q22: 7 | T22: 0.8 | U22: 1.04 | V22: =Z22&"*"&AA22&"*"&AB22 -> 25.4*22.86*8.89 | W22: 10 | X22: 9 | Y22: 3.5 | Z22: =+W22*2.54 -> 25.4 | AA22: =+X22*2.54 -> 22.86 | AB22: =+Y22*2.54 -> 8.89
A23: Master box 4-5 | C23: Master box | W23: 19 | X23: 11 | Y23: 4.5 | Z23: =+W23*2.54 -> 48.26 | AA23: =+X23*2.54 -> 27.94 | AB23: =+Y23*2.54 -> 11.43
A24: 4 | B24: 4 | C24: Small box | G24: 6 | K24: 6 | P24: 1 | Q24: 6 | R24: =+T24/P24 -> 0.8 | S24: =+U24/P24 -> 1.04 | T24: 0.8 | U24: 1.04 | V24: =Z24&"*"&AA24&"*"&AB24 -> 25.4*22.86*8.89 | W24: 10 | X24: 9 | Y24: 3.5 | Z24: =+W24*2.54 -> 25.4 | AA24: =+X24*2.54 -> 22.86 | AB24: =+Y24*2.54 -> 8.89
A25: 5 | B25: 5 | C25: Small box | G25: 4 | L25: 4 | P25: 1 | Q25: 4 | T25: 0.56 | U25: 0.8 | V25: =Z25&"*"&AA25&"*"&AB25 -> 25.4*22.86*8.89 | W25: 10 | X25: 9 | Y25: 3.5 | Z25: =+W25*2.54 -> 25.4 | AA25: =+X25*2.54 -> 22.86 | AB25: =+Y25*2.54 -> 8.89
Z26: =+W26*2.54 -> 0 | AA26: =+X26*2.54 -> 0 | AB26: =+Y26*2.54 -> 0
A27: Master box 6-8 | C27: Master box | W27: 19 | X27: 11 | Y27: 8.5 | Z27: =+W27*2.54 -> 48.26 | AA27: =+X27*2.54 -> 27.94 | AB27: =+Y27*2.54 -> 21.59
A28: 6 | B28: 6 | C28: Small box | D28: NESSB711 | E28: 655 DESERT PINK | F28: 655 | G28: 2 | H28: 2 | P28: 1 | Q28: 2 | R28: =+T28/P28 -> 0.22 | S28: =+U28/P28 -> 0.46 | T28: 0.22 | U28: 0.46 | V28: =Z28&"*"&AA28&"*"&AB28 -> 25.4*22.86*8.89 | W28: 10 | X28: 9 | Y28: 3.5 | Z28: =+W28*2.54 -> 25.4 | AA28: =+X28*2.54 -> 22.86 | AB28: =+Y28*2.54 -> 8.89
A29: 7 | B29: 7 | C29: Small box | G29: 5 | I29: 5 | P29: 1 | Q29: 5 | T29: 0.54 | U29: 0.78 | V29: =Z29&"*"&AA29&"*"&AB29 -> 25.4*22.86*8.89 | W29: 10 | X29: 9 | Y29: 3.5 | Z29: =+W29*2.54 -> 25.4 | AA29: =+X29*2.54 -> 22.86 | AB29: =+Y29*2.54 -> 8.89
A30: 8 | B30: 8 | C30: Small box | G30: 7 | J30: 7 | P30: 1 | Q30: 7 | T30: 0.8 | U30: 1.04 | V30: =Z30&"*"&AA30&"*"&AB30 -> 25.4*22.86*8.89 | W30: 10 | X30: 9 | Y30: 3.5 | Z30: =+W30*2.54 -> 25.4 | AA30: =+X30*2.54 -> 22.86 | AB30: =+Y30*2.54 -> 8.89
A31: Master box 9-10 | C31: Master box | W31: 19 | X31: 11 | Y31: 4.5 | Z31: =+W31*2.54 -> 48.26 | AA31: =+X31*2.54 -> 27.94 | AB31: =+Y31*2.54 -> 11.43
A32: 9 | B32: 9 | C32: Small box | G32: 6 | K32: 6 | P32: 1 | Q32: 6 | R32: =+T32/P32 -> 0.8 | S32: =+U32/P32 -> 1.04 | T32: 0.8 | U32: 1.04 | V32: =Z32&"*"&AA32&"*"&AB32 -> 25.4*22.86*8.89 | W32: 10 | X32: 9 | Y32: 3.5 | Z32: =+W32*2.54 -> 25.4 | AA32: =+X32*2.54 -> 22.86 | AB32: =+Y32*2.54 -> 8.89
A33: 10 | B33: 10 | C33: Small box | G33: 4 | L33: 4 | P33: 1 | Q33: 4 | T33: 0.56 | U33: 0.8 | V33: =Z33&"*"&AA33&"*"&AB33 -> 25.4*22.86*8.89 | W33: 10 | X33: 9 | Y33: 3.5 | Z33: =+W33*2.54 -> 25.4 | AA33: =+X33*2.54 -> 22.86 | AB33: =+Y33*2.54 -> 8.89
Z34: =+W34*2.54 -> 0 | AA34: =+X34*2.54 -> 0 | AB34: =+Y34*2.54 -> 0
A35: Master box 11-13 | C35: Master box | W35: 10 | X35: 10 | Y35: 11.5 | Z35: =+W35*2.54 -> 25.4 | AA35: =+X35*2.54 -> 25.4 | AB35: =+Y35*2.54 -> 29.21
A36: 11 | B36: 11 | C36: Small box | D36: NESSG729 | E36: 001 BLACK | F36: 001 | G36: 2 | H36: 2 | P36: 1 | Q36: 2 | R36: =+T36/P36 -> 0.2 | S36: =+U36/P36 -> 0.44 | T36: 0.2 | U36: 0.44 | V36: =Z36&"*"&AA36&"*"&AB36 -> 22.86*22.86*8.89 | W36: 9 | X36: 9 | Y36: 3.5 | Z36: =+W36*2.54 -> 22.86 | AA36: =+X36*2.54 -> 22.86 | AB36: =+Y36*2.54 -> 8.89
A37: 12 | B37: 12 | C37: Small box | G37: 5 | I37: 5 | P37: 1 | Q37: 5 | T37: 0 | U37: 0 | V37: =Z37&"*"&AA37&"*"&AB37 -> 22.86*22.86*8.89 | W37: 9 | X37: 9 | Y37: 3.5 | Z37: =+W37*2.54 -> 22.86 | AA37: =+X37*2.54 -> 22.86 | AB37: =+Y37*2.54 -> 8.89
A38: 13 | B38: 13 | C38: Small box | G38: 7 | J38: 7 | P38: 1 | Q38: 7 | T38: 0 | U38: 0 | V38: =Z38&"*"&AA38&"*"&AB38 -> 22.86*22.86*8.89 | W38: 9 | X38: 9 | Y38: 3.5 | Z38: =+W38*2.54 -> 22.86 | AA38: =+X38*2.54 -> 22.86 | AB38: =+Y38*2.54 -> 8.89
A39: Master box 14-15 | C39: Master box | W39: 19 | X39: 11 | Y39: 4.5 | Z39: =+W39*2.54 -> 48.26 | AA39: =+X39*2.54 -> 27.94 | AB39: =+Y39*2.54 -> 11.43
A40: 14 | B40: 14 | C40: Small box | G40: 6 | K40: 6 | P40: 1 | Q40: 6 | R40: =+T40/P40 -> 0.78 | S40: =+U40/P40 -> 1.02 | T40: 0.78 | U40: 1.02 | V40: =Z40&"*"&AA40&"*"&AB40 -> 22.86*22.86*8.89 | W40: 9 | X40: 9 | Y40: 3.5 | Z40: =+W40*2.54 -> 22.86 | AA40: =+X40*2.54 -> 22.86 | AB40: =+Y40*2.54 -> 8.89
A41: 15 | B41: 15 | C41: Small box | G41: 4 | L41: 4 | P41: 1 | Q41: 4 | T41: 0 | U41: 0 | V41: =Z41&"*"&AA41&"*"&AB41 -> 22.86*22.86*8.89 | W41: 9 | X41: 9 | Y41: 3.5 | Z41: =+W41*2.54 -> 22.86 | AA41: =+X41*2.54 -> 22.86 | AB41: =+Y41*2.54 -> 8.89
Z42: =+W42*2.54 -> 0 | AA42: =+X42*2.54 -> 0 | AB42: =+Y42*2.54 -> 0
A43: Master box 16-18 | C43: Master box | W43: 19 | X43: 11 | Y43: 8.5 | Z43: =+W43*2.54 -> 48.26 | AA43: =+X43*2.54 -> 27.94 | AB43: =+Y43*2.54 -> 21.59
A44: 16 | B44: 16 | C44: Small box | D44: NESSG758 | E44: 385 ENERGY | F44: 385 | G44: 2 | H44: 2 | P44: 1 | Q44: 2 | R44: =+T44/P44 -> 0.24 | S44: =+U44/P44 -> 0.48 | T44: 0.24 | U44: 0.48 | V44: =Z44&"*"&AA44&"*"&AB44 -> 25.4*22.86*8.89 | W44: 10 | X44: 9 | Y44: 3.5 | Z44: =+W44*2.54 -> 25.4 | AA44: =+X44*2.54 -> 22.86 | AB44: =+Y44*2.54 -> 8.89
A45: 17 | B45: 17 | C45: Small box | G45: 5 | I45: 5 | P45: 1 | Q45: 5 | T45: 0 | U45: 0 | V45: =Z45&"*"&AA45&"*"&AB45 -> 25.4*22.86*8.89 | W45: 10 | X45: 9 | Y45: 3.5 | Z45: =+W45*2.54 -> 25.4 | AA45: =+X45*2.54 -> 22.86 | AB45: =+Y45*2.54 -> 8.89
A46: 18 | B46: 18 | C46: Small box | G46: 7 | J46: 7 | P46: 1 | Q46: 7 | T46: 0 | U46: 0 | V46: =Z46&"*"&AA46&"*"&AB46 -> 25.4*22.86*8.89 | W46: 10 | X46: 9 | Y46: 3.5 | Z46: =+W46*2.54 -> 25.4 | AA46: =+X46*2.54 -> 22.86 | AB46: =+Y46*2.54 -> 8.89
A47: Master box 19-20 | C47: Master box | W47: 19 | X47: 11 | Y47: 4.5 | Z47: =+W47*2.54 -> 48.26 | AA47: =+X47*2.54 -> 27.94 | AB47: =+Y47*2.54 -> 11.43
A48: 19 | B48: 19 | C48: Small box | G48: 6 | K48: 6 | P48: 1 | Q48: 6 | R48: =+T48/P48 -> 0.84 | S48: =+U48/P48 -> 1.08 | T48: 0.84 | U48: 1.08 | V48: =Z48&"*"&AA48&"*"&AB48 -> 25.4*22.86*8.89 | W48: 10 | X48: 9 | Y48: 3.5 | Z48: =+W48*2.54 -> 25.4 | AA48: =+X48*2.54 -> 22.86 | AB48: =+Y48*2.54 -> 8.89
A49: 20 | B49: 20 | C49: Small box | G49: 4 | L49: 4 | P49: 1 | Q49: 4 | T49: 0 | U49: 0 | V49: =Z49&"*"&AA49&"*"&AB49 -> 25.4*22.86*8.89 | W49: 10 | X49: 9 | Y49: 3.5 | Z49: =+W49*2.54 -> 25.4 | AA49: =+X49*2.54 -> 22.86 | AB49: =+Y49*2.54 -> 8.89
Z50: =+W50*2.54 -> 0 | AA50: =+X50*2.54 -> 0 | AB50: =+Y50*2.54 -> 0
A51: Master box 21-23 | C51: Master box | W51: 19 | X51: 11 | Y51: 8.5 | Z51: =+W51*2.54 -> 48.26 | AA51: =+X51*2.54 -> 27.94 | AB51: =+Y51*2.54 -> 21.59
A52: 21 | B52: 21 | C52: Small box | D52: NESSG758 | E52: 655 DESERT PINK | F52: 655 | G52: 2 | H52: 2 | P52: 1 | Q52: 2 | R52: =+T52/P52 -> 0.24 | S52: =+U52/P52 -> 0.48 | T52: 0.24 | U52: 0.48 | V52: =Z52&"*"&AA52&"*"&AB52 -> 25.4*22.86*8.89 | W52: 10 | X52: 9 | Y52: 3.5 | Z52: =+W52*2.54 -> 25.4 | AA52: =+X52*2.54 -> 22.86 | AB52: =+Y52*2.54 -> 8.89
A53: 22 | B53: 22 | C53: Small box | G53: 5 | I53: 5 | P53: 1 | Q53: 5 | T53: 0 | U53: 0 | V53: =Z53&"*"&AA53&"*"&AB53 -> 25.4*22.86*8.89 | W53: 10 | X53: 9 | Y53: 3.5 | Z53: =+W53*2.54 -> 25.4 | AA53: =+X53*2.54 -> 22.86 | AB53: =+Y53*2.54 -> 8.89
A54: 23 | B54: 23 | C54: Small box | G54: 7 | J54: 7 | P54: 1 | Q54: 7 | T54: 0 | U54: 0 | V54: =Z54&"*"&AA54&"*"&AB54 -> 25.4*22.86*8.89 | W54: 10 | X54: 9 | Y54: 3.5 | Z54: =+W54*2.54 -> 25.4 | AA54: =+X54*2.54 -> 22.86 | AB54: =+Y54*2.54 -> 8.89
A55: Master box 24-25 | C55: Master box | W55: 19 | X55: 11 | Y55: 4.5 | Z55: =+W55*2.54 -> 48.26 | AA55: =+X55*2.54 -> 27.94 | AB55: =+Y55*2.54 -> 11.43
A56: 24 | B56: 24 | C56: Small box | G56: 6 | K56: 6 | P56: 1 | Q56: 6 | R56: =+T56/P56 -> 0.84 | S56: =+U56/P56 -> 1.08 | T56: 0.84 | U56: 1.08 | V56: =Z56&"*"&AA56&"*"&AB56 -> 25.4*22.86*8.89 | W56: 10 | X56: 9 | Y56: 3.5 | Z56: =+W56*2.54 -> 25.4 | AA56: =+X56*2.54 -> 22.86 | AB56: =+Y56*2.54 -> 8.89
A57: 25 | B57: 25 | C57: Small box | G57: 4 | L57: 4 | P57: 1 | Q57: 4 | T57: 0 | U57: 0 | V57: =Z57&"*"&AA57&"*"&AB57 -> 25.4*22.86*8.89 | W57: 10 | X57: 9 | Y57: 3.5 | Z57: =+W57*2.54 -> 25.4 | AA57: =+X57*2.54 -> 22.86 | AB57: =+Y57*2.54 -> 8.89
N60: =SUM(N20:N59) -> 0 | O60: =SUM(O20:O59) -> 0 | P60: =SUM(P20:P59) -> 25 | Q60: =SUM(Q20:Q59) -> 120 | T60: =SUM(T20:T59) -> 8.98 | U60: =SUM(U20:U59) -> 12.82
C63: CUSTOMER PO | D63: Style | E63: Color | F63: Color Code | G63: xs | H63: S | I63: M | J63: L | K63: XL | L63: XXL | P63: TOT CTNS | Q63: TOT PCS
C64: WH88 | D64: NESSB711 | E64: ENERGY | F64: 385 | G64: 2 | H64: 5 | I64: 7 | J64: 6 | K64: 4 | P64: 5 | Q64: 24 | W64: =+SUM(G64:K64) -> 24 | X64: =+Q64-W64 -> 0
C65: WH88 | D65: NESSB711 | E65: DESERT PINK | F65: 655 | G65: 2 | H65: 5 | I65: 7 | J65: 6 | K65: 4 | P65: 5 | Q65: 24
C66: WH88 | D66: NESSG729 | E66: BLACK | F66: 001 | G66: 2 | H66: 5 | I66: 7 | J66: 6 | K66: 4 | P66: 5 | Q66: 24
C67: WH88 | D67: NESSG758 | E67: ENERGY | F67: 385 | G67: 2 | H67: 5 | I67: 7 | J67: 6 | K67: 4 | P67: 5 | Q67: 24
C68: WH88 | D68: NESSG758 | E68: DESERT PINK | F68: 655 | G68: 2 | H68: 5 | I68: 7 | J68: 6 | K68: 4 | P68: 5 | Q68: 24
J71: TOTAL | P71: =SUM(P64:P69) -> 25 | Q71: =SUM(Q64:Q69) -> 120

Sheet IRREGULAR SS PL WH96
A4: PACKING LIST
G5: PEI
A6: ISSUE TO : | D6: =+'[1]INVOICE 11'!C7 -> SUPREME INTERNATIONAL, LLC | G6: STYLE:
G7: LABEL
G8: P.O.:
G9: PCS
G10: SIZES
A12: PAYMENT: T/C | G12: MADE IN
A13: PO NO: | B13: WH96 | G13: C# UP
A14: CUSTOMER PO.: | D14: =+B13 -> WH96
A15: INVOICE NO: | C15: =+'INVOICE 94'!M2 -> 7726477
A16: Detail Breakdown
A18: CASE FROM-TO | C18: REMARKS | D18: Style | E18: Color Name | F18: Color code | G18: Units/case | H18: xs | I18: S | J18: M | K18: L | L18: XL | M18: XXL | N18: 6 | O18: 6X | P18: TOT CTNS | Q18: TOT PCS | R18: NW | S18: GW | T18: TTL NW | U18: TTL GW | V18: CARTON SIZE ( CM)
A20: 1 | B20: 1 | D20: NESSG277 | E20: 001 BLACK | F20: 001 | G20: 36 | J20: 36 | P20: 1 | Q20: 36 | R20: =+T20/P20 -> 3.23 | S20: =+U20/P20 -> 3.88 | T20: 3.23 | U20: 3.88 | V20: =Z20&"*"&AA20&"*"&AB20 -> 40.64*38.1*11.43 | W20: 16 | X20: 15 | Y20: 4.5 | Z20: =+W20*2.54 -> 40.64 | AA20: =+X20*2.54 -> 38.1 | AB20: =+Y20*2.54 -> 11.43
A21: 2 | B21: 2 | C21: ODD CARTON | G21: 29 | I21: 29 | P21: 1 | Q21: 29 | R21: =+T21/P21 -> 2.24 | S21: =+U21/P21 -> 3.06 | T21: 2.24 | U21: 3.06 | V21: =Z21&"*"&AA21&"*"&AB21 -> 40.64*39.37*10.16 | W21: 16 | X21: 15.5 | Y21: 4 | Z21: =+W21*2.54 -> 40.64 | AA21: =+X21*2.54 -> 39.37 | AB21: =+Y21*2.54 -> 10.16
A22: 3 | B22: 3 | C22: ODD CARTON | G22: 29 | K22: 29 | P22: 1 | Q22: 29 | R22: =+T22/P22 -> 2.85 | S22: =+U22/P22 -> 3.5 | T22: 2.85 | U22: 3.5 | V22: =Z22&"*"&AA22&"*"&AB22 -> 40.64*38.1*11.43 | W22: 16 | X22: 15 | Y22: 4.5 | Z22: =+W22*2.54 -> 40.64 | AA22: =+X22*2.54 -> 38.1 | AB22: =+Y22*2.54 -> 11.43
A23: 4 | B23: 4 | C23: ODD CARTON | G23: 13 | L23: 13 | P23: 1 | Q23: 13 | R23: =+T23/P23 -> 1.22 | S23: =+U23/P23 -> 1.7 | T23: 1.22 | U23: 1.7 | V23: =Z23&"*"&AA23&"*"&AB23 -> 40.64*22.86*8.89 | W23: 16 | X23: 9 | Y23: 3.5 | Z23: =+W23*2.54 -> 40.64 | AA23: =+X23*2.54 -> 22.86 | AB23: =+Y23*2.54 -> 8.89
A24: Master box 5-6 | C24: Master box | W24: 19 | X24: 11 | Y24: 4.5 | Z24: =+W24*2.54 -> 48.26 | AA24: =+X24*2.54 -> 27.94 | AB24: =+Y24*2.54 -> 11.43
A25: 5 | B25: 5 | C25: Small box | G25: 5 | H25: 5 | P25: 1 | Q25: 5 | R25: =+T25/P25 -> 0.44 | S25: =+U25/P25 -> 0.64 | T25: 0.44 | U25: 0.64 | V25: =Z25&"*"&AA25&"*"&AB25 -> 22.86*22.86*7.62 | W25: 9 | X25: 9 | Y25: 3 | Z25: =+W25*2.54 -> 22.86 | AA25: =+X25*2.54 -> 22.86 | AB25: =+Y25*2.54 -> 7.62
A26: 6 | B26: 6 | C26: Small box | G26: 8 | M26: 8 | Q26: 8 | U26: 0 | V26: =Z26&"*"&AA26&"*"&AB26 -> 22.86*22.86*7.62 | W26: 9 | X26: 9 | Y26: 3 | Z26: =+W26*2.54 -> 22.86 | AA26: =+X26*2.54 -> 22.86 | AB26: =+Y26*2.54 -> 7.62
Z27: =+W27*2.54 -> 0 | AA27: =+X27*2.54 -> 0 | AB27: =+Y27*2.54 -> 0
A28: 7 | B28: 7 | C28: ODD CARTON | D28: NESSG278 | E28: 001 BLACK | F28: 001 | G28: 30 | I28: 30 | P28: 1 | Q28: 30 | R28: =+T28/P28 -> 2.23 | S28: =+U28/P28 -> 2.98 | T28: 2.23 | U28: 2.98 | V28: =Z28&"*"&AA28&"*"&AB28 -> 40.64*40.64*16.51 | W28: 16 | X28: 16 | Y28: 6.5 | Z28: =+W28*2.54 -> 40.64 | AA28: =+X28*2.54 -> 40.64 | AB28: =+Y28*2.54 -> 16.51
A29: 8 | B29: 8 | C29: ODD CARTON | G29: 35 | J29: 35 | P29: 1 | Q29: 35 | R29: =+T29/P29 -> 2.79 | S29: =+U29/P29 -> 3.56 | T29: 2.79 | U29: 3.56 | V29: =Z29&"*"&AA29&"*"&AB29 -> 40.64*38.1*19.05 | W29: 16 | X29: 15 | Y29: 7.5 | Z29: =+W29*2.54 -> 40.64 | AA29: =+X29*2.54 -> 38.1 | AB29: =+Y29*2.54 -> 19.05
A30: 9 | B30: 9 | C30: ODD CARTON | G30: 29 | K30: 29 | P30: 1 | Q30: 29 | R30: =+T30/P30 -> 2.61 | S30: =+U30/P30 -> 3.36 | T30: 2.61 | U30: 3.36 | V30: =Z30&"*"&AA30&"*"&AB30 -> 40.64*40.64*16.51 | W30: 16 | X30: 16 | Y30: 6.5 | Z30: =+W30*2.54 -> 40.64 | AA30: =+X30*2.54 -> 40.64 | AB30: =+Y30*2.54 -> 16.51
A31: 10 | B31: 10 | C31: ODD CARTON | G31: 13 | L31: 13 | P31: 1 | Q31: 13 | R31: =+T31/P31 -> 1.48 | S31: =+U31/P31 -> 2.06 | T31: 1.48 | U31: 2.06 | V31: =Z31&"*"&AA31&"*"&AB31 -> 40.64*39.37*7.62 | W31: 16 | X31: 15.5 | Y31: 3 | Z31: =+W31*2.54 -> 40.64 | AA31: =+X31*2.54 -> 39.37 | AB31: =+Y31*2.54 -> 7.62
A32: Master box 11-12 | C32: Master box | W32: 19 | X32: 17 | Y32: 4 | Z32: =+W32*2.54 -> 48.26 | AA32: =+X32*2.54 -> 43.18 | AB32: =+Y32*2.54 -> 10.16
A33: 11 | B33: 11 | C33: Small box | G33: 5 | H33: 5 | P33: 1 | Q33: 5 | R33: =+T33/P33 -> 0.38 | S33: =+U33/P33 -> 0.68 | T33: 0.38 | U33: 0.68 | V33: =Z33&"*"&AA33&"*"&AB33 -> 40.64*22.86*7.62 | W33: 16 | X33: 9 | Y33: 3 | Z33: =+W33*2.54 -> 40.64 | AA33: =+X33*2.54 -> 22.86 | AB33: =+Y33*2.54 -> 7.62
A34: 12 | B34: 12 | C34: Small box | G34: 8 | M34: 8 | Q34: 8 | U34: 1.2 | V34: =Z34&"*"&AA34&"*"&AB34 -> 40.64*22.86*7.62 | W34: 16 | X34: 9 | Y34: 3 | Z34: =+W34*2.54 -> 40.64 | AA34: =+X34*2.54 -> 22.86 | AB34: =+Y34*2.54 -> 7.62
Z35: =+W35*2.54 -> 0 | AA35: =+X35*2.54 -> 0 | AB35: =+Y35*2.54 -> 0
A36: 13 | B36: 13 | D36: NESSG280 | E36: 001 BLACK | F36: 001 | G36: 36 | J36: 36 | P36: 1 | Q36: 36 | R36: =+T36/P36 -> 5.64 | S36: =+U36/P36 -> 6.5 | T36: 5.64 | U36: 6.5 | V36: =Z36&"*"&AA36&"*"&AB36 -> 50.8*43.18*13.97 | W36: 20 | X36: 17 | Y36: 5.5 | Z36: =+W36*2.54 -> 50.8 | AA36: =+X36*2.54 -> 43.18 | AB36: =+Y36*2.54 -> 13.97
A37: 14 | B37: 14 | C37: ODD CARTON | G37: 29 | I37: 29 | P37: 1 | Q37: 29 | R37: =+T37/P37 -> 4.14 | S37: =+U37/P37 -> 4.94 | T37: 4.14 | U37: 4.94 | V37: =Z37&"*"&AA37&"*"&AB37 -> 50.8*43.18*12.7 | W37: 20 | X37: 17 | Y37: 5 | Z37: =+W37*2.54 -> 50.8 | AA37: =+X37*2.54 -> 43.18 | AB37: =+Y37*2.54 -> 12.7
A38: 15 | B38: 15 | C38: ODD CARTON | G38: 30 | K38: 30 | P38: 1 | Q38: 30 | R38: =+T38/P38 -> 5.06 | S38: =+U38/P38 -> 5.92 | T38: 5.06 | U38: 5.92 | V38: =Z38&"*"&AA38&"*"&AB38 -> 50.8*43.18*13.97 | W38: 20 | X38: 17 | Y38: 5.5 | Z38: =+W38*2.54 -> 50.8 | AA38: =+X38*2.54 -> 43.18 | AB38: =+Y38*2.54 -> 13.97
A39: 16 | B39: 16 | C39: ODD CARTON | G39: 13 | L39: 13 | P39: 1 | Q39: 13 | R39: =+T39/P39 -> 2.1 | S39: =+U39/P39 -> 2.78 | T39: 2.1 | U39: 2.78 | V39: =Z39&"*"&AA39&"*"&AB39 -> 43.18*25.4*11.43 | W39: 17 | X39: 10 | Y39: 4.5 | Z39: =+W39*2.54 -> 43.18 | AA39: =+X39*2.54 -> 25.4 | AB39: =+Y39*2.54 -> 11.43
A40: Master box 17-18 | C40: Master box | W40: 19 | X40: 11 | Y40: 8.5 | Z40: =+W40*2.54 -> 48.26 | AA40: =+X40*2.54 -> 27.94 | AB40: =+Y40*2.54 -> 21.59
A41: 17 | B41: 17 | C41: Small box | G41: 4 | H41: 4 | P41: 1 | Q41: 4 | R41: =+T41/P41 -> 0.52 | S41: =+U41/P41 -> 0.82 | T41: 0.52 | U41: 0.82 | V41: =Z41&"*"&AA41&"*"&AB41 -> 25.4*22.86*8.89 | W41: 10 | X41: 9 | Y41: 3.5 | Z41: =+W41*2.54 -> 25.4 | AA41: =+X41*2.54 -> 22.86 | AB41: =+Y41*2.54 -> 8.89
A42: 18 | B42: 18 | C42: Small box | G42: 8 | M42: 8 | Q42: 8 | U42: 0 | V42: =Z42&"*"&AA42&"*"&AB42 -> 44.45*25.4*7.62 | W42: 17.5 | X42: 10 | Y42: 3 | Z42: =+W42*2.54 -> 44.45 | AA42: =+X42*2.54 -> 25.4 | AB42: =+Y42*2.54 -> 7.62
Z43: =+W43*2.54 -> 0 | AA43: =+X43*2.54 -> 0 | AB43: =+Y43*2.54 -> 0
A44: Master box 19-22 | C44: Master box | W44: 19 | X44: 17 | Y44: 9.5 | Z44: =+W44*2.54 -> 48.26 | AA44: =+X44*2.54 -> 43.18 | AB44: =+Y44*2.54 -> 24.13
A45: 19 | B45: 19 | C45: Small box | D45: NESSG410 | E45: 440 MIDNIGHT NAVY | F45: 440 | G45: 7 | I45: 7 | P45: 1 | Q45: 7 | R45: =+T45/P45 -> 0.77 | S45: =+U45/P45 -> 1.42 | T45: 0.77 | U45: 1.42 | V45: =Z45&"*"&AA45&"*"&AB45 -> 40.64*22.86*11.43 | W45: 16 | X45: 9 | Y45: 4.5 | Z45: =+W45*2.54 -> 40.64 | AA45: =+X45*2.54 -> 22.86 | AB45: =+Y45*2.54 -> 11.43
A46: 20 | B46: 20 | C46: Small box | G46: 8 | J46: 8 | Q46: 8 | U46: 0 | V46: =Z46&"*"&AA46&"*"&AB46 -> 40.64*22.86*11.43 | W46: 16 | X46: 9 | Y46: 4.5 | Z46: =+W46*2.54 -> 40.64 | AA46: =+X46*2.54 -> 22.86 | AB46: =+Y46*2.54 -> 11.43
A47: 21 | B47: 21 | C47: Small box | G47: 7 | K47: 7 | Q47: 7 | U47: 0 | V47: =Z47&"*"&AA47&"*"&AB47 -> 40.64*22.86*11.43 | W47: 16 | X47: 9 | Y47: 4.5 | Z47: =+W47*2.54 -> 40.64 | AA47: =+X47*2.54 -> 22.86 | AB47: =+Y47*2.54 -> 11.43
A48: 22 | B48: 22 | C48: Small box | G48: 2 | L48: 2 | Q48: 2 | U48: 0 | V48: =Z48&"*"&AA48&"*"&AB48 -> 40.64*22.86*11.43 | W48: 16 | X48: 9 | Y48: 4.5 | Z48: =+W48*2.54 -> 40.64 | AA48: =+X48*2.54 -> 22.86 | AB48: =+Y48*2.54 -> 11.43
Z49: =+W49*2.54 -> 0 | AA49: =+X49*2.54 -> 0 | AB49: =+Y49*2.54 -> 0
A50: Master box 23-26 | C50: Master box | W50: 19 | X50: 17 | Y50: 9.5 | Z50: =+W50*2.54 -> 48.26 | AA50: =+X50*2.54 -> 43.18 | AB50: =+Y50*2.54 -> 24.13
A51: 23 | B51: 23 | C51: Small box | D51: NESSG410 | E51: 655 DESERT PINK | F51: 655 | G51: 7 | I51: 7 | P51: 1 | Q51: 7 | R51: =+T51/P51 -> 0.77 | S51: =+U51/P51 -> 1.42 | T51: 0.77 | U51: 1.42 | V51: =Z51&"*"&AA51&"*"&AB51 -> 40.64*22.86*11.43 | W51: 16 | X51: 9 | Y51: 4.5 | Z51: =+W51*2.54 -> 40.64 | AA51: =+X51*2.54 -> 22.86 | AB51: =+Y51*2.54 -> 11.43
A52: 24 | B52: 24 | C52: Small box | G52: 8 | J52: 8 | Q52: 8 | U52: 0 | V52: =Z52&"*"&AA52&"*"&AB52 -> 40.64*22.86*11.43 | W52: 16 | X52: 9 | Y52: 4.5 | Z52: =+W52*2.54 -> 40.64 | AA52: =+X52*2.54 -> 22.86 | AB52: =+Y52*2.54 -> 11.43
A53: 25 | B53: 25 | C53: Small box | G53: 7 | K53: 7 | Q53: 7 | U53: 0 | V53: =Z53&"*"&AA53&"*"&AB53 -> 40.64*22.86*11.43 | W53: 16 | X53: 9 | Y53: 4.5 | Z53: =+W53*2.54 -> 40.64 | AA53: =+X53*2.54 -> 22.86 | AB53: =+Y53*2.54 -> 11.43
A54: 26 | B54: 26 | C54: Small box | G54: 2 | L54: 2 | Q54: 2 | U54: 0 | V54: =Z54&"*"&AA54&"*"&AB54 -> 40.64*22.86*11.43 | W54: 16 | X54: 9 | Y54: 4.5 | Z54: =+W54*2.54 -> 40.64 | AA54: =+X54*2.54 -> 22.86 | AB54: =+Y54*2.54 -> 11.43
N56: =SUM(N20:N55) -> 0 | O56: =SUM(O20:O55) -> 0 | P56: =SUM(P20:P55) -> 17 | Q56: =SUM(Q20:Q55) -> 408 | T56: =SUM(T20:T55) -> 38.47 | U56: =SUM(U20:U55) -> 50.42
C59: CUSTOMER PO | D59: Style | E59: Color | F59: Color Code | G59: xs | H59: S | I59: M | J59: L | K59: XL | L59: XXL | P59: TOT CTNS | Q59: TOT PCS
C60: WH96 | D60: NESSG277 | E60: BLACK | F60: 001 | G60: 2 | H60: 5 | I60: 7 | J60: 6 | K60: 4 | P60: 5 | Q60: 120 | W60: =+SUM(G60:K60) -> 24 | X60: =+Q60-W60 -> 96
C61: WH96 | D61: NESSG278 | E61: BLACK | F61: 001 | G61: 2 | H61: 5 | I61: 7 | J61: 6 | K61: 4 | P61: 5 | Q61: 120
C62: WH96 | D62: NESSG280 | E62: BLACK | F62: 001 | G62: 2 | H62: 5 | I62: 7 | J62: 6 | K62: 4 | P62: 5 | Q62: 120
C63: WH96 | D63: NESSG410 | E63: MIDNIGHT NAVY | F63: 440 | G63: 2 | H63: 5 | I63: 7 | J63: 6 | K63: 4 | P63: 1 | Q63: 24
C64: WH96 | D64: NESSG410 | E64: DESERT PINK | F64: 655 | G64: 2 | H64: 5 | I64: 7 | J64: 6 | K64: 4 | P64: 1 | Q64: 24
J67: TOTAL | P67: =SUM(P60:P65) -> 17 | Q67: =SUM(Q60:Q65) -> 408

Sheet SOLID PL WH96
A4: PACKING LIST
G5: PEI
A6: ISSUE TO : | D6: =+'[1]INVOICE 11'!C7 -> SUPREME INTERNATIONAL, LLC | G6: STYLE:
G7: LABEL
G8: P.O.:
G9: PCS
G10: SIZES
A12: PAYMENT: T/C | G12: MADE IN
A13: PO NO: | B13: WH96 | G13: C# UP
A14: CUSTOMER PO.: | D14: =+B13 -> WH96
A15: INVOICE NO: | C15: =+'INVOICE 94'!M2 -> 7726477
A16: Detail Breakdown
A18: CASE FROM-TO | C18: REMARKS | D18: Style | E18: Color Name | F18: Color code | G18: Units/case | H18: xs | I18: S | J18: M | K18: L | L18: XL | M18: XXL | N18: 6 | O18: 6X | P18: TOT CTNS | Q18: TOT PCS | R18: NW | S18: GW | T18: TTL NW | U18: TTL GW | V18: CARTON SIZE ( CM)
A20: 1 | B20: 1 | D20: NESSG277 | E20: 001 BLACK | F20: 001 | G20: 36 | J20: 36 | P20: 1 | Q20: 36 | R20: =+T20/P20 -> 3.23 | S20: =+U20/P20 -> 3.88 | T20: 3.23 | U20: 3.88 | V20: =Z20&"*"&AA20&"*"&AB20 -> 40.64*38.1*11.43 | W20: 16 | X20: 15 | Y20: 4.5 | Z20: =+W20*2.54 -> 40.64 | AA20: =+X20*2.54 -> 38.1 | AB20: =+Y20*2.54 -> 11.43
A21: 2 | B21: 2 | C21: ODD CARTON | G21: 29 | I21: 29 | P21: 1 | Q21: 29 | R21: =+T21/P21 -> 2.24 | S21: =+U21/P21 -> 3.06 | T21: 2.24 | U21: 3.06 | V21: =Z21&"*"&AA21&"*"&AB21 -> 40.64*39.37*10.16 | W21: 16 | X21: 15.5 | Y21: 4 | Z21: =+W21*2.54 -> 40.64 | AA21: =+X21*2.54 -> 39.37 | AB21: =+Y21*2.54 -> 10.16
A22: 3 | B22: 3 | C22: ODD CARTON | G22: 29 | K22: 29 | P22: 1 | Q22: 29 | R22: =+T22/P22 -> 2.85 | S22: =+U22/P22 -> 3.5 | T22: 2.85 | U22: 3.5 | V22: =Z22&"*"&AA22&"*"&AB22 -> 40.64*38.1*11.43 | W22: 16 | X22: 15 | Y22: 4.5 | Z22: =+W22*2.54 -> 40.64 | AA22: =+X22*2.54 -> 38.1 | AB22: =+Y22*2.54 -> 11.43
A23: 4 | B23: 4 | C23: ODD CARTON | G23: 13 | L23: 13 | P23: 1 | Q23: 13 | R23: =+T23/P23 -> 1.22 | S23: =+U23/P23 -> 1.7 | T23: 1.22 | U23: 1.7 | V23: =Z23&"*"&AA23&"*"&AB23 -> 40.64*22.86*8.89 | W23: 16 | X23: 9 | Y23: 3.5 | Z23: =+W23*2.54 -> 40.64 | AA23: =+X23*2.54 -> 22.86 | AB23: =+Y23*2.54 -> 8.89
A24: Master box 5-6 | C24: Master box | W24: 19 | X24: 11 | Y24: 4.5 | Z24: =+W24*2.54 -> 48.26 | AA24: =+X24*2.54 -> 27.94 | AB24: =+Y24*2.54 -> 11.43
A25: 5 | B25: 5 | C25: Small box | G25: 5 | H25: 5 | P25: 1 | Q25: 5 | R25: =+T25/P25 -> 0.44 | S25: =+U25/P25 -> 0.64 | T25: 0.44 | U25: 0.64 | V25: =Z25&"*"&AA25&"*"&AB25 -> 22.86*22.86*7.62 | W25: 9 | X25: 9 | Y25: 3 | Z25: =+W25*2.54 -> 22.86 | AA25: =+X25*2.54 -> 22.86 | AB25: =+Y25*2.54 -> 7.62
A26: 6 | B26: 6 | C26: Small box | G26: 8 | M26: 8 | P26: 1 | Q26: 8 | U26: 0 | V26: =Z26&"*"&AA26&"*"&AB26 -> 22.86*22.86*7.62 | W26: 9 | X26: 9 | Y26: 3 | Z26: =+W26*2.54 -> 22.86 | AA26: =+X26*2.54 -> 22.86 | AB26: =+Y26*2.54 -> 7.62
Z27: =+W27*2.54 -> 0 | AA27: =+X27*2.54 -> 0 | AB27: =+Y27*2.54 -> 0
A28: 7 | B28: 7 | C28: ODD CARTON | D28: NESSG278 | E28: 001 BLACK | F28: 001 | G28: 30 | I28: 30 | P28: 1 | Q28: 30 | R28: =+T28/P28 -> 2.23 | S28: =+U28/P28 -> 2.98 | T28: 2.23 | U28: 2.98 | V28: =Z28&"*"&AA28&"*"&AB28 -> 40.64*40.64*16.51 | W28: 16 | X28: 16 | Y28: 6.5 | Z28: =+W28*2.54 -> 40.64 | AA28: =+X28*2.54 -> 40.64 | AB28: =+Y28*2.54 -> 16.51
A29: 8 | B29: 8 | C29: ODD CARTON | G29: 35 | J29: 35 | P29: 1 | Q29: 35 | R29: =+T29/P29 -> 2.79 | S29: =+U29/P29 -> 3.56 | T29: 2.79 | U29: 3.56 | V29: =Z29&"*"&AA29&"*"&AB29 -> 40.64*38.1*19.05 | W29: 16 | X29: 15 | Y29: 7.5 | Z29: =+W29*2.54 -> 40.64 | AA29: =+X29*2.54 -> 38.1 | AB29: =+Y29*2.54 -> 19.05
A30: 9 | B30: 9 | C30: ODD CARTON | G30: 29 | K30: 29 | P30: 1 | Q30: 29 | R30: =+T30/P30 -> 2.61 | S30: =+U30/P30 -> 3.36 | T30: 2.61 | U30: 3.36 | V30: =Z30&"*"&AA30&"*"&AB30 -> 40.64*40.64*16.51 | W30: 16 | X30: 16 | Y30: 6.5 | Z30: =+W30*2.54 -> 40.64 | AA30: =+X30*2.54 -> 40.64 | AB30: =+Y30*2.54 -> 16.51
A31: 10 | B31: 10 | C31: ODD CARTON | G31: 13 | L31: 13 | P31: 1 | Q31: 13 | R31: =+T31/P31 -> 1.48 | S31: =+U31/P31 -> 2.06 | T31: 1.48 | U31: 2.06 | V31: =Z31&"*"&AA31&"*"&AB31 -> 40.64*39.37*7.62 | W31: 16 | X31: 15.5 | Y31: 3 | Z31: =+W31*2.54 -> 40.64 | AA31: =+X31*2.54 -> 39.37 | AB31: =+Y31*2.54 -> 7.62
A32: Master box 11-12 | C32: Master box | W32: 19 | X32: 17 | Y32: 4 | Z32: =+W32*2.54 -> 48.26 | AA32: =+X32*2.54 -> 43.18 | AB32: =+Y32*2.54 -> 10.16
A33: 11 | B33: 11 | C33: Small box | G33: 5 | H33: 5 | P33: 1 | Q33: 5 | R33: =+T33/P33 -> 0.38 | S33: =+U33/P33 -> 0.68 | T33: 0.38 | U33: 0.68 | V33: =Z33&"*"&AA33&"*"&AB33 -> 40.64*22.86*7.62 | W33: 16 | X33: 9 | Y33: 3 | Z33: =+W33*2.54 -> 40.64 | AA33: =+X33*2.54 -> 22.86 | AB33: =+Y33*2.54 -> 7.62
A34: 12 | B34: 12 | C34: Small box | G34: 8 | M34: 8 | P34: 1 | Q34: 8 | U34: 1.2 | V34: =Z34&"*"&AA34&"*"&AB34 -> 40.64*22.86*7.62 | W34: 16 | X34: 9 | Y34: 3 | Z34: =+W34*2.54 -> 40.64 | AA34: =+X34*2.54 -> 22.86 | AB34: =+Y34*2.54 -> 7.62
Z35: =+W35*2.54 -> 0 | AA35: =+X35*2.54 -> 0 | AB35: =+Y35*2.54 -> 0
A36: 13 | B36: 13 | D36: NESSG280 | E36: 001 BLACK | F36: 001 | G36: 36 | J36: 36 | P36: 1 | Q36: 36 | R36: =+T36/P36 -> 5.64 | S36: =+U36/P36 -> 6.5 | T36: 5.64 | U36: 6.5 | V36: =Z36&"*"&AA36&"*"&AB36 -> 50.8*43.18*13.97 | W36: 20 | X36: 17 | Y36: 5.5 | Z36: =+W36*2.54 -> 50.8 | AA36: =+X36*2.54 -> 43.18 | AB36: =+Y36*2.54 -> 13.97
A37: 14 | B37: 14 | C37: ODD CARTON | G37: 29 | I37: 29 | P37: 1 | Q37: 29 | R37: =+T37/P37 -> 4.14 | S37: =+U37/P37 -> 4.94 | T37: 4.14 | U37: 4.94 | V37: =Z37&"*"&AA37&"*"&AB37 -> 50.8*43.18*12.7 | W37: 20 | X37: 17 | Y37: 5 | Z37: =+W37*2.54 -> 50.8 | AA37: =+X37*2.54 -> 43.18 | AB37: =+Y37*2.54 -> 12.7
A38: 15 | B38: 15 | C38: ODD CARTON | G38: 30 | K38: 30 | P38: 1 | Q38: 30 | R38: =+T38/P38 -> 5.06 | S38: =+U38/P38 -> 5.92 | T38: 5.06 | U38: 5.92 | V38: =Z38&"*"&AA38&"*"&AB38 -> 50.8*43.18*13.97 | W38: 20 | X38: 17 | Y38: 5.5 | Z38: =+W38*2.54 -> 50.8 | AA38: =+X38*2.54 -> 43.18 | AB38: =+Y38*2.54 -> 13.97
A39: 16 | B39: 16 | C39: ODD CARTON | G39: 13 | L39: 13 | P39: 1 | Q39: 13 | R39: =+T39/P39 -> 2.1 | S39: =+U39/P39 -> 2.78 | T39: 2.1 | U39: 2.78 | V39: =Z39&"*"&AA39&"*"&AB39 -> 43.18*25.4*11.43 | W39: 17 | X39: 10 | Y39: 4.5 | Z39: =+W39*2.54 -> 43.18 | AA39: =+X39*2.54 -> 25.4 | AB39: =+Y39*2.54 -> 11.43
A40: Master box 17-18 | C40: Master box | W40: 19 | X40: 11 | Y40: 8.5 | Z40: =+W40*2.54 -> 48.26 | AA40: =+X40*2.54 -> 27.94 | AB40: =+Y40*2.54 -> 21.59
A41: 17 | B41: 17 | C41: Small box | G41: 4 | H41: 4 | P41: 1 | Q41: 4 | R41: =+T41/P41 -> 0.52 | S41: =+U41/P41 -> 0.82 | T41: 0.52 | U41: 0.82 | V41: =Z41&"*"&AA41&"*"&AB41 -> 25.4*22.86*8.89 | W41: 10 | X41: 9 | Y41: 3.5 | Z41: =+W41*2.54 -> 25.4 | AA41: =+X41*2.54 -> 22.86 | AB41: =+Y41*2.54 -> 8.89
A42: 18 | B42: 18 | C42: Small box | G42: 8 | M42: 8 | P42: 1 | Q42: 8 | U42: 0 | V42: =Z42&"*"&AA42&"*"&AB42 -> 44.45*25.4*7.62 | W42: 17.5 | X42: 10 | Y42: 3 | Z42: =+W42*2.54 -> 44.45 | AA42: =+X42*2.54 -> 25.4 | AB42: =+Y42*2.54 -> 7.62
Z43: =+W43*2.54 -> 0 | AA43: =+X43*2.54 -> 0 | AB43: =+Y43*2.54 -> 0
A44: Master box 19-22 | C44: Master box | W44: 19 | X44: 17 | Y44: 9.5 | Z44: =+W44*2.54 -> 48.26 | AA44: =+X44*2.54 -> 43.18 | AB44: =+Y44*2.54 -> 24.13
A45: 19 | B45: 19 | C45: Small box | D45: NESSG410 | E45: 440 MIDNIGHT NAVY | F45: 440 | G45: 7 | I45: 7 | P45: 1 | Q45: 7 | R45: =+T45/P45 -> 0.77 | S45: =+U45/P45 -> 1.42 | T45: 0.77 | U45: 1.42 | V45: =Z45&"*"&AA45&"*"&AB45 -> 40.64*22.86*11.43 | W45: 16 | X45: 9 | Y45: 4.5 | Z45: =+W45*2.54 -> 40.64 | AA45: =+X45*2.54 -> 22.86 | AB45: =+Y45*2.54 -> 11.43
A46: 20 | B46: 20 | C46: Small box | G46: 8 | J46: 8 | P46: 1 | Q46: 8 | U46: 0 | V46: =Z46&"*"&AA46&"*"&AB46 -> 40.64*22.86*11.43 | W46: 16 | X46: 9 | Y46: 4.5 | Z46: =+W46*2.54 -> 40.64 | AA46: =+X46*2.54 -> 22.86 | AB46: =+Y46*2.54 -> 11.43
A47: 21 | B47: 21 | C47: Small box | G47: 7 | K47: 7 | P47: 1 | Q47: 7 | U47: 0 | V47: =Z47&"*"&AA47&"*"&AB47 -> 40.64*22.86*11.43 | W47: 16 | X47: 9 | Y47: 4.5 | Z47: =+W47*2.54 -> 40.64 | AA47: =+X47*2.54 -> 22.86 | AB47: =+Y47*2.54 -> 11.43
A48: 22 | B48: 22 | C48: Small box | G48: 2 | L48: 2 | P48: 1 | Q48: 2 | U48: 0 | V48: =Z48&"*"&AA48&"*"&AB48 -> 40.64*22.86*11.43 | W48: 16 | X48: 9 | Y48: 4.5 | Z48: =+W48*2.54 -> 40.64 | AA48: =+X48*2.54 -> 22.86 | AB48: =+Y48*2.54 -> 11.43
Z49: =+W49*2.54 -> 0 | AA49: =+X49*2.54 -> 0 | AB49: =+Y49*2.54 -> 0
A50: Master box 23-26 | C50: Master box | W50: 19 | X50: 17 | Y50: 9.5 | Z50: =+W50*2.54 -> 48.26 | AA50: =+X50*2.54 -> 43.18 | AB50: =+Y50*2.54 -> 24.13
A51: 23 | B51: 23 | C51: Small box | D51: NESSG410 | E51: 655 DESERT PINK | F51: 655 | G51: 7 | I51: 7 | P51: 1 | Q51: 7 | R51: =+T51/P51 -> 0.77 | S51: =+U51/P51 -> 1.42 | T51: 0.77 | U51: 1.42 | V51: =Z51&"*"&AA51&"*"&AB51 -> 40.64*22.86*11.43 | W51: 16 | X51: 9 | Y51: 4.5 | Z51: =+W51*2.54 -> 40.64 | AA51: =+X51*2.54 -> 22.86 | AB51: =+Y51*2.54 -> 11.43
A52: 24 | B52: 24 | C52: Small box | G52: 8 | J52: 8 | P52: 1 | Q52: 8 | U52: 0 | V52: =Z52&"*"&AA52&"*"&AB52 -> 40.64*22.86*11.43 | W52: 16 | X52: 9 | Y52: 4.5 | Z52: =+W52*2.54 -> 40.64 | AA52: =+X52*2.54 -> 22.86 | AB52: =+Y52*2.54 -> 11.43
A53: 25 | B53: 25 | C53: Small box | G53: 7 | K53: 7 | P53: 1 | Q53: 7 | U53: 0 | V53: =Z53&"*"&AA53&"*"&AB53 -> 40.64*22.86*11.43 | W53: 16 | X53: 9 | Y53: 4.5 | Z53: =+W53*2.54 -> 40.64 | AA53: =+X53*2.54 -> 22.86 | AB53: =+Y53*2.54 -> 11.43
A54: 26 | B54: 26 | C54: Small box | G54: 2 | L54: 2 | P54: 1 | Q54: 2 | U54: 0 | V54: =Z54&"*"&AA54&"*"&AB54 -> 40.64*22.86*11.43 | W54: 16 | X54: 9 | Y54: 4.5 | Z54: =+W54*2.54 -> 40.64 | AA54: =+X54*2.54 -> 22.86 | AB54: =+Y54*2.54 -> 11.43
N56: =SUM(N20:N55) -> 0 | O56: =SUM(O20:O55) -> 0 | P56: =SUM(P20:P55) -> 26 | Q56: =SUM(Q20:Q55) -> 408 | T56: =SUM(T20:T55) -> 38.47 | U56: =SUM(U20:U55) -> 50.42
C59: CUSTOMER PO | D59: Style | E59: Color | F59: Color Code | G59: xs | H59: S | I59: M | J59: L | K59: XL | L59: XXL | P59: TOT CTNS | Q59: TOT PCS
C60: WH96 | D60: NESSG277 | E60: BLACK | F60: 001 | G60: 2 | H60: 5 | I60: 7 | J60: 6 | K60: 4 | P60: 6 | Q60: 120 | W60: =+SUM(G60:K60) -> 24 | X60: =+Q60-W60 -> 96
C61: WH96 | D61: NESSG278 | E61: BLACK | F61: 001 | G61: 2 | H61: 5 | I61: 7 | J61: 6 | K61: 4 | P61: 6 | Q61: 120
C62: WH96 | D62: NESSG280 | E62: BLACK | F62: 001 | G62: 2 | H62: 5 | I62: 7 | J62: 6 | K62: 4 | P62: 6 | Q62: 120
C63: WH96 | D63: NESSG410 | E63: MIDNIGHT NAVY | F63: 440 | G63: 2 | H63: 5 | I63: 7 | J63: 6 | K63: 4 | P63: 4 | Q63: 24
C64: WH96 | D64: NESSG410 | E64: DESERT PINK | F64: 655 | G64: 2 | H64: 5 | I64: 7 | J64: 6 | K64: 4 | P64: 4 | Q64: 24
J67: TOTAL | P67: =SUM(P60:P65) -> 26 | Q67: =SUM(Q60:Q65) -> 408

Sheet IRREGULAR SS PL XL102
A4: PACKING LIST
G5: PEI
A6: ISSUE TO : | D6: =+'[1]INVOICE 11'!C7 -> SUPREME INTERNATIONAL, LLC | G6: STYLE:
G7: LABEL
G8: P.O.:
G9: PCS
G10: SIZES
A12: PAYMENT: T/C | G12: MADE IN
A13: PO NO: | B13: XL102 | G13: C# UP
A14: CUSTOMER PO.: | D14: =+B13 -> XL102
A15: INVOICE NO: | C15: =+'INVOICE 94'!M2 -> 7726477
A16: Detail Breakdown
A18: CASE FROM-TO | C18: REMARKS | D18: Style | E18: Color Name | F18: Color code | G18: Units/case | H18: xs | I18: S | J18: M | K18: L | L18: XL | M18: XXL | N18: 6 | O18: 6X | P18: TOT CTNS | Q18: TOT PCS | R18: NW | S18: GW | T18: TTL NW | U18: TTL GW | V18: CARTON SIZE ( CM)
A20: 1 | B20: 1 | D20: NESSB711 | E20: 001 BLACK | F20: 001 | G20: 12 | H20: 12 | P20: 1 | Q20: 12 | R20: =+T20/P20 -> 1.04 | S20: =+U20/P20 -> 1.44 | T20: 1.04 | U20: 1.44 | V20: =Z20&"*"&AA20&"*"&AB20 -> 44.45*25.4*7.62 | W20: 17.5 | X20: 10 | Y20: 3 | Z20: =+W20*2.54 -> 44.45 | AA20: =+X20*2.54 -> 25.4 | AB20: =+Y20*2.54 -> 7.62
A21: 2 | B21: 2 | C21: ODD CARTON | G21: 24 | I21: 24 | P21: 1 | Q21: 24 | R21: =+T21/P21 -> 2.16 | S21: =+U21/P21 -> 3.06 | T21: 2.16 | U21: 3.06 | V21: =Z21&"*"&AA21&"*"&AB21 -> 50.8*43.18*8.89 | W21: 20 | X21: 17 | Y21: 3.5 | Z21: =+W21*2.54 -> 50.8 | AA21: =+X21*2.54 -> 43.18 | AB21: =+Y21*2.54 -> 8.89
A22: 3 | B22: 3 | C22: ODD CARTON | G22: 24 | J22: 24 | P22: 1 | Q22: 24 | R22: =+T22/P22 -> 2.28 | S22: =+U22/P22 -> 3.18 | T22: 2.28 | U22: 3.18 | V22: =Z22&"*"&AA22&"*"&AB22 -> 50.8*43.18*8.89 | W22: 20 | X22: 17 | Y22: 3.5 | Z22: =+W22*2.54 -> 50.8 | AA22: =+X22*2.54 -> 43.18 | AB22: =+Y22*2.54 -> 8.89
A23: 4 | B23: 4 | C23: ODD CARTON | G23: 12 | K23: 12 | P23: 1 | Q23: 12 | R23: =+T23/P23 -> 1.4 | S23: =+U23/P23 -> 1.8 | T23: 1.4 | U23: 1.8 | V23: =Z23&"*"&AA23&"*"&AB23 -> 44.45*25.4*7.62 | W23: 17.5 | X23: 10 | Y23: 3 | Z23: =+W23*2.54 -> 44.45 | AA23: =+X23*2.54 -> 25.4 | AB23: =+Y23*2.54 -> 7.62
C24: Master box | Z24: =+W24*2.54 -> 0 | AA24: =+X24*2.54 -> 0 | AB24: =+Y24*2.54 -> 0
A25: Master box 5-8 | C25: Small box | V25: =Z25&"*"&AA25&"*"&AB25 -> 48.26*27.94*21.59 | W25: 19 | X25: 11 | Y25: 8.5 | Z25: =+W25*2.54 -> 48.26 | AA25: =+X25*2.54 -> 27.94 | AB25: =+Y25*2.54 -> 21.59
A26: 5 | B26: 5 | C26: Small box | D26: NESSB711 | E26: 655 DESERT PINK | F26: 655 | G26: 8 | I26: 8 | P26: 1 | Q26: 8 | R26: =+T26/P26 -> 0.82 | S26: =+U26/P26 -> 1.06 | T26: 0.82 | U26: 1.06 | V26: =Z26&"*"&AA26&"*"&AB26 -> 25.4*22.86*8.89 | W26: 10 | X26: 9 | Y26: 3.5 | Z26: =+W26*2.54 -> 25.4 | AA26: =+X26*2.54 -> 22.86 | AB26: =+Y26*2.54 -> 8.89
A27: 6 | B27: 6 | G27: 8 | J27: 8 | Q27: 8 | V27: =Z27&"*"&AA27&"*"&AB27 -> 25.4*22.86*8.89 | W27: 10 | X27: 9 | Y27: 3.5 | Z27: =+W27*2.54 -> 25.4 | AA27: =+X27*2.54 -> 22.86 | AB27: =+Y27*2.54 -> 8.89
A28: 7 | B28: 7 | C28: ODD CARTON | G28: 4 | H28: 4 | Q28: 4 | V28: =Z28&"*"&AA28&"*"&AB28 -> 25.4*22.86*8.89 | W28: 10 | X28: 9 | Y28: 3.5 | Z28: =+W28*2.54 -> 25.4 | AA28: =+X28*2.54 -> 22.86 | AB28: =+Y28*2.54 -> 8.89
A29: 8 | B29: 8 | C29: ODD CARTON | G29: 4 | K29: 4 | Q29: 4 | V29: =Z29&"*"&AA29&"*"&AB29 -> 25.4*22.86*8.89 | W29: 10 | X29: 9 | Y29: 3.5 | Z29: =+W29*2.54 -> 25.4 | AA29: =+X29*2.54 -> 22.86 | AB29: =+Y29*2.54 -> 8.89
N31: =SUM(N20:N30) -> 0 | O31: =SUM(O20:O30) -> 0 | P31: =SUM(P20:P30) -> 5 | Q31: =SUM(Q20:Q30) -> 96 | T31: =SUM(T20:T30) -> 7.7 | U31: =SUM(U20:U30) -> 10.54
C34: CUSTOMER PO | D34: Style | E34: Color | F34: Color Code | G34: xs | H34: S | I34: M | J34: L | K34: XL | L34: XXL | P34: TOT CTNS | Q34: TOT PCS
C35: XL102 | D35: NESSB711 | E35: BLACK | F35: 001 | G35: 12 | H35: 24 | I35: 24 | J35: 12 | P35: 4 | Q35: 72 | W35: =+SUM(G35:K35) -> 72 | X35: =+Q35-W35 -> 0
C36: XL102 | D36: NESSB711 | E36: DESERT PINK | F36: 655 | G36: 4 | H36: 8 | I36: 8 | J36: 4 | P36: 1 | Q36: 24
J39: TOTAL | P39: =SUM(P35:P37) -> 5 | Q39: =SUM(Q35:Q37) -> 96

Sheet SOLID PL XL102
A4: PACKING LIST
G5: PEI
A6: ISSUE TO : | D6: =+'[1]INVOICE 11'!C7 -> SUPREME INTERNATIONAL, LLC | G6: STYLE:
G7: LABEL
G8: P.O.:
G9: PCS
G10: SIZES
A12: PAYMENT: T/C | G12: MADE IN
A13: PO NO: | B13: XL102 | G13: C# UP
A14: CUSTOMER PO.: | D14: =+B13 -> XL102
A15: INVOICE NO: | C15: =+'INVOICE 94'!M2 -> 7726477
A16: Detail Breakdown
A18: CASE FROM-TO | C18: REMARKS | D18: Style | E18: Color Name | F18: Color code | G18: Units/case | H18: xs | I18: S | J18: M | K18: L | L18: XL | M18: XXL | N18: 6 | O18: 6X | P18: TOT CTNS | Q18: TOT PCS | R18: NW | S18: GW | T18: TTL NW | U18: TTL GW | V18: CARTON SIZE ( CM)
A20: 1 | B20: 1 | D20: NESSB711 | E20: 001 BLACK | F20: 001 | G20: 12 | H20: 12 | P20: 1 | Q20: 12 | R20: =+T20/P20 -> 1.04 | S20: =+U20/P20 -> 1.44 | T20: 1.04 | U20: 1.44 | V20: =Z20&"*"&AA20&"*"&AB20 -> 44.45*25.4*7.62 | W20: 17.5 | X20: 10 | Y20: 3 | Z20: =+W20*2.54 -> 44.45 | AA20: =+X20*2.54 -> 25.4 | AB20: =+Y20*2.54 -> 7.62
A21: 2 | B21: 2 | C21: ODD CARTON | G21: 24 | I21: 24 | P21: 1 | Q21: 24 | R21: =+T21/P21 -> 2.16 | S21: =+U21/P21 -> 3.06 | T21: 2.16 | U21: 3.06 | V21: =Z21&"*"&AA21&"*"&AB21 -> 50.8*43.18*8.89 | W21: 20 | X21: 17 | Y21: 3.5 | Z21: =+W21*2.54 -> 50.8 | AA21: =+X21*2.54 -> 43.18 | AB21: =+Y21*2.54 -> 8.89
A22: 3 | B22: 3 | C22: ODD CARTON | G22: 24 | J22: 24 | P22: 1 | Q22: 24 | R22: =+T22/P22 -> 2.28 | S22: =+U22/P22 -> 3.18 | T22: 2.28 | U22: 3.18 | V22: =Z22&"*"&AA22&"*"&AB22 -> 50.8*43.18*8.89 | W22: 20 | X22: 17 | Y22: 3.5 | Z22: =+W22*2.54 -> 50.8 | AA22: =+X22*2.54 -> 43.18 | AB22: =+Y22*2.54 -> 8.89
A23: 4 | B23: 4 | C23: ODD CARTON | G23: 12 | K23: 12 | P23: 1 | Q23: 12 | R23: =+T23/P23 -> 1.4 | S23: =+U23/P23 -> 1.8 | T23: 1.4 | U23: 1.8 | V23: =Z23&"*"&AA23&"*"&AB23 -> 44.45*25.4*7.62 | W23: 17.5 | X23: 10 | Y23: 3 | Z23: =+W23*2.54 -> 44.45 | AA23: =+X23*2.54 -> 25.4 | AB23: =+Y23*2.54 -> 7.62
C24: Master box | Z24: =+W24*2.54 -> 0 | AA24: =+X24*2.54 -> 0 | AB24: =+Y24*2.54 -> 0
A25: Master box 5-8 | C25: Small box | V25: =Z25&"*"&AA25&"*"&AB25 -> 48.26*27.94*21.59 | W25: 19 | X25: 11 | Y25: 8.5 | Z25: =+W25*2.54 -> 48.26 | AA25: =+X25*2.54 -> 27.94 | AB25: =+Y25*2.54 -> 21.59
A26: 5 | B26: 5 | C26: Small box | D26: NESSB711 | E26: 655 DESERT PINK | F26: 655 | G26: 8 | I26: 8 | P26: 1 | Q26: 8 | R26: =+T26/P26 -> 0.82 | S26: =+U26/P26 -> 1.06 | T26: 0.82 | U26: 1.06 | V26: =Z26&"*"&AA26&"*"&AB26 -> 25.4*22.86*8.89 | W26: 10 | X26: 9 | Y26: 3.5 | Z26: =+W26*2.54 -> 25.4 | AA26: =+X26*2.54 -> 22.86 | AB26: =+Y26*2.54 -> 8.89
A27: 6 | B27: 6 | G27: 8 | J27: 8 | P27: 1 | Q27: 8 | V27: =Z27&"*"&AA27&"*"&AB27 -> 25.4*22.86*8.89 | W27: 10 | X27: 9 | Y27: 3.5 | Z27: =+W27*2.54 -> 25.4 | AA27: =+X27*2.54 -> 22.86 | AB27: =+Y27*2.54 -> 8.89
A28: 7 | B28: 7 | C28: ODD CARTON | G28: 4 | H28: 4 | P28: 1 | Q28: 4 | V28: =Z28&"*"&AA28&"*"&AB28 -> 25.4*22.86*8.89 | W28: 10 | X28: 9 | Y28: 3.5 | Z28: =+W28*2.54 -> 25.4 | AA28: =+X28*2.54 -> 22.86 | AB28: =+Y28*2.54 -> 8.89
A29: 8 | B29: 8 | C29: ODD CARTON | G29: 4 | K29: 4 | P29: 1 | Q29: 4 | V29: =Z29&"*"&AA29&"*"&AB29 -> 25.4*22.86*8.89 | W29: 10 | X29: 9 | Y29: 3.5 | Z29: =+W29*2.54 -> 25.4 | AA29: =+X29*2.54 -> 22.86 | AB29: =+Y29*2.54 -> 8.89
N31: =SUM(N20:N30) -> 0 | O31: =SUM(O20:O30) -> 0 | P31: =SUM(P20:P30) -> 8 | Q31: =SUM(Q20:Q30) -> 96 | T31: =SUM(T20:T30) -> 7.7 | U31: =SUM(U20:U30) -> 10.54
C34: CUSTOMER PO | D34: Style | E34: Color | F34: Color Code | G34: xs | H34: S | I34: M | J34: L | K34: XL | L34: XXL | P34: TOT CTNS | Q34: TOT PCS
C35: XL102 | D35: NESSB711 | E35: BLACK | F35: 001 | G35: 12 | H35: 24 | I35: 24 | J35: 12 | P35: 4 | Q35: 72 | W35: =+SUM(G35:K35) -> 72 | X35: =+Q35-W35 -> 0
C36: XL102 | D36: NESSB711 | E36: DESERT PINK | F36: 655 | G36: 4 | H36: 8 | I36: 8 | J36: 4 | P36: 4 | Q36: 24
J39: TOTAL | P39: =SUM(P35:P37) -> 8 | Q39: =SUM(Q35:Q37) -> 96

Sheet Sheet6

Sheet Sheet1
A1: 17.5*15.5*6" | B1: 44.45 | C1: 39.37 | D1: 15.24 | F1: =+B1&"x"&C1&"x"&D1 -> 44.45x39.37x15.24 | I1: 44.45x39.37x15.24
A2: 17.5*15.5*6.5" | B2: 44.45 | C2: 39.37 | D2: 16.51 | F2: =+B2&"x"&C2&"x"&D2 -> 44.45x39.37x16.51 | I2: 44.45x39.37x16.51
A3: 17.5*15.5*8.5" | B3: 44.45 | C3: 39.37 | D3: 21.59 | F3: =+B3&"x"&C3&"x"&D3 -> 44.45x39.37x21.59 | I3: 44.45x39.37x21.59
A4: 19.5*17*9" | B4: 49.53 | C4: 43.18 | D4: 22.86 | F4: =+B4&"x"&C4&"x"&D4 -> 49.53x43.18x22.86 | I4: 49.53x43.18x22.86
A5: 19.5*19*10 | B5: 49.53 | C5: 48.26 | D5: 25.4 | F5: =+B5&"x"&C5&"x"&D5 -> 49.53x48.26x25.4 | I5: 49.53x48.26x25.4
A6: 19.5*19*8.5 | B6: 49.53 | C6: 48.26 | D6: 21.59 | F6: =+B6&"x"&C6&"x"&D6 -> 49.53x48.26x21.59 | I6: 49.53x48.26x21.59
A7: 21*19*8.5 " | B7: 53.34 | C7: 48.26 | D7: 21.59 | F7: =+B7&"x"&C7&"x"&D7 -> 53.34x48.26x21.59 | I7: 53.34x48.26x21.59
A8: 21.5*18*6" | B8: 54.61 | C8: 45.72 | D8: 15.24 | F8: =+B8&"x"&C8&"x"&D8 -> 54.61x45.72x15.24 | I8: 54.61x45.72x15.24
A9: 21.5*19*10" | B9: 54.61 | C9: 48.26 | D9: 25.4 | F9: =+B9&"x"&C9&"x"&D9 -> 54.61x48.26x25.4 | I9: 54.61x48.26x25.4
A10: 23.5*15.5*6" | B10: 59.69 | C10: 39.37 | D10: 15.24 | F10: =+B10&"x"&C10&"x"&D10 -> 59.69x39.37x15.24 | I10: 59.69x39.37x15.24
A11: 23.5*15.5*6.5" | B11: 59.69 | C11: 39.37 | D11: 16.51 | F11: =+B11&"x"&C11&"x"&D11 -> 59.69x39.37x16.51 | I11: 59.69x39.37x16.51
A12: 23.5*17*7.5" | B12: 59.69 | C12: 43.18 | D12: 19.05 | F12: =+B12&"x"&C12&"x"&D12 -> 59.69x43.18x19.05 | I12: 59.69x43.18x19.05
... A19: 28*19*9.5 | B19: 71.12 | C19: 48.26 | D19: 24.13 | F19: =+B19&"x"&C19&"x"&D19 -> 71.12x48.26x24.13 | I19: 71.12x48.26x24.13
